Workbook

Sheet Summary
A1: STR DSCR Search: Summary of Top Picks
A2: As of 2026-10-18. Every number below is a live link (green) to the market tabs; change inputs there or on Assumptions.
A4: Market Tab | B4: Address | C4: City / ZIP | D4: Offer Price | E4: Stated Gross ($/yr) | F4: PITIA ($/mo) | G4: DSCR (gross) | H4: DSCR (lender haircut) | I4: Cash to Close | J4: Cash Flow Self-Managed ($/yr) | K4: Cash Flow Full PM ($/yr) | L4: Verdict
A5: Manatee-Sarasota | B5: ='Manatee-Sarasota'!$B$6 -> 8404 43rd Ave Terrace W | C5: ='Manatee-Sarasota'!$C$6 -> Bradenton 34209 | D5: ='Manatee-Sarasota'!$H$6 -> 560000 | E5: ='Manatee-Sarasota'!$K$6 -> 85000 | F5: ='Manatee-Sarasota'!$W$6 -> 4315.1404 | G5: ='Manatee-Sarasota'!$X$6 -> 1.641507 | H5: ='Manatee-Sarasota'!$Y$6 -> 1.3132056 | I5: ='Manatee-Sarasota'!$Z$6 -> 145600 | J5: ='Manatee-Sarasota'!$AD$6 -> 4668.3155 | K5: ='Manatee-Sarasota'!$AE$6 -> -12331.685 | L5: #1 OVERALL: write it. PropertyRadar: ~$516k loan (3% equity) and an exemption flag (possible homestead). Seller may not clear payoff at $560k + 3%; verify homestead, T12, FEMA, appraisal.
A6: Manatee-Sarasota | B6: ='Manatee-Sarasota'!$B$7 -> 5318 17th St W (duplex) | C6: ='Manatee-Sarasota'!$C$7 -> Bradenton 34207 | D6: ='Manatee-Sarasota'!$H$7 -> 460000 | E6: ='Manatee-Sarasota'!$K$7 -> 73000 | F6: ='Manatee-Sarasota'!$W$7 -> 3678.5082 | G6: ='Manatee-Sarasota'!$X$7 -> 1.6537501 | H6: ='Manatee-Sarasota'!$Y$7 -> 1.3230001 | I6: ='Manatee-Sarasota'!$Z$7 -> 133400 | J6: ='Manatee-Sarasota'!$AD$7 -> 4867.902 | K6: ='Manatee-Sarasota'!$AE$7 -> -9732.098 | L6: Backup: cheapest, STR + LTR hedge. Confirm legal duplex.
A7: Manatee-Sarasota | B7: ='Manatee-Sarasota'!$B$8 -> 2801 23rd Ave W ("Beachin' Escape") | C7: ='Manatee-Sarasota'!$C$8 -> Bradenton 34205 | D7: ='Manatee-Sarasota'!$H$8 -> 600000 | E7: ='Manatee-Sarasota'!$K$8 -> 89000 | F7: ='Manatee-Sarasota'!$W$8 -> 4569.7933 | G7: ='Manatee-Sarasota'!$X$8 -> 1.6229764 | H7: ='Manatee-Sarasota'!$Y$8 -> 1.2983811 | I7: ='Manatee-Sarasota'!$Z$8 -> 156000 | J7: ='Manatee-Sarasota'!$AD$8 -> 4692.4809 | K7: ='Manatee-Sarasota'!$AE$8 -> -13107.519 | L7: Best income record; appraisal + sq-ft risk. Aggressive offer only.
A8: Pinellas | B8: =Pinellas!$B$6 -> 12565 81st Ave | C8: =Pinellas!$C$6 -> Seminole 33776 | D8: =Pinellas!$H$6 -> 485000 | E8: =Pinellas!$K$6 -> 71000 | F8: =Pinellas!$W$6 -> 3878.0829 | G8: =Pinellas!$X$6 -> 1.5256679 | H8: =Pinellas!$Y$6 -> 1.2205343 | I8: =Pinellas!$Z$6 -> 140650 | J8: =Pinellas!$AD$6 -> -866.99462 | K8: =Pinellas!$AE$6 -> -15066.995 | L8: Best Pinellas: licensed since 2022. 'Estimated' $71k: get T12. Confirm Seminole license transfers.
A9: Pinellas | B9: =Pinellas!$B$7 -> 4000 46th St N | C9: =Pinellas!$C$7 -> St Petersburg 33714 | D9: =Pinellas!$H$7 -> 485000 | E9: =Pinellas!$K$7 -> 85000 | F9: =Pinellas!$W$7 -> 3878.0829 | G9: =Pinellas!$X$7 -> 1.8265039 | H9: =Pinellas!$Y$7 -> 1.4612031 | I9: =Pinellas!$Z$7 -> 140650 | J9: =Pinellas!$AD$7 -> 9913.0054 | K9: =Pinellas!$AE$7 -> -7086.9946 | L9: Highest yield, but <12 months history + jurisdiction (St. Pete vs Lealman) unconfirmed.
A10: Pinellas | B10: =Pinellas!$B$8 -> 341 Wertz Dr | C10: =Pinellas!$C$8 -> Largo 33771 | D10: =Pinellas!$H$8 -> 340000 | E10: =Pinellas!$K$8 -> 51000 | F10: =Pinellas!$W$8 -> 2942.8828 | G10: =Pinellas!$X$8 -> 1.4441621 | H10: =Pinellas!$Y$8 -> 1.1553297 | I10: =Pinellas!$Z$8 -> 98600 | J10: =Pinellas!$AD$8 -> -3244.5942 | K10: =Pinellas!$AE$8 -> -13444.594 | L10: Cheap Largo STR; history is pre-hurricane. Negotiable (257 DOM).
A11: Other SWFL Listings | B11: ='Other SWFL Listings'!$B$6 -> 326 NW 21st Ter | C11: ='Other SWFL Listings'!$C$6 -> Cape Coral 33993 | D11: ='Other SWFL Listings'!$H$6 -> 460000 | E11: ='Other SWFL Listings'!$K$6 -> 60000 | F11: ='Other SWFL Listings'!$W$6 -> 3755.1748 | G11: ='Other SWFL Listings'!$X$6 -> 1.3314959 | H11: ='Other SWFL Listings'!$Y$6 -> 1.0651967 | I11: ='Other SWFL Listings'!$Z$6 -> 133400 | J11: ='Other SWFL Listings'!$AD$6 -> -7862.098 | K11: ='Other SWFL Listings'!$AE$6 -> -19862.098 | L11: Only SWFL listing that clears after haircut; inland NW Cape, check utility assessment.
A12: Monroe (Keys) | B12: ='Monroe (Keys)'!$B$7 -> 500 Burton Dr #2212 (Ocean Pointe) | C12: ='Monroe (Keys)'!$C$7 -> Tavernier 33070 | D12: ='Monroe (Keys)'!$H$7 -> 625000 | E12: ='Monroe (Keys)'!$K$7 -> 100000 | F12: ='Monroe (Keys)'!$W$7 -> 5390.493 | G12: ='Monroe (Keys)'!$X$7 -> 1.5459316 | H12: ='Monroe (Keys)'!$Y$7 -> 1.2367453 | I12: ='Monroe (Keys)'!$Z$7 -> 181250 | J12: ='Monroe (Keys)'!$AD$7 -> 5114.0842 | K12: ='Monroe (Keys)'!$AE$7 -> -14885.916 | L12: Best Keys DSCR on paper, but $100k avg on an 826 sf condo is agent-owner marketing: statements first.
A13: Monroe (Keys) | B13: ='Monroe (Keys)'!$B$6 -> 1500 Ocean Bay Dr #E5 (Kawama Yacht Club) | C13: ='Monroe (Keys)'!$C$6 -> Key Largo 33037 | D13: ='Monroe (Keys)'!$H$6 -> 760000 | E13: ='Monroe (Keys)'!$K$6 -> 98980 | F13: ='Monroe (Keys)'!$W$6 -> 5940.0715 | G13: ='Monroe (Keys)'!$X$6 -> 1.3885916 | H13: ='Monroe (Keys)'!$Y$6 -> 1.1108733 | I13: ='Monroe (Keys)'!$Z$6 -> 220400 | J13: ='Monroe (Keys)'!$AD$6 -> -2266.2576 | K13: ='Monroe (Keys)'!$AE$6 -> -22062.258 | L13: Cleanest Keys income claim; nightly allowed. Stretch price: ~$220k cash at 25% down.
A15: Key takeaways
A16: - Buyer: 800 FICO, $150k earmarked + $550k brokerage + $60k checking. Recommended structure: 25% down, 3% seller credit to rate buydown.
A17: - Rates are placeholders (7.50 / 7.25 / 7.125% by LTV tier): overwrite on the Assumptions tab and every tab reflows.
A18: - Cleaning is not a cost (passed through to guests as a cleaning fee): use gross EXCLUDING guest-paid cleaning fees. Platform fees 10%. #1 nets ~+$4.7k/yr self-managed; a 10-15% co-host is about breakeven; full-service PM does not cash flow at today's rates.
A19: - Pinellas: nightly SFH STRs are legal mainly in unincorporated county (Certificate of Use), Largo, Indian Rocks Beach, Redington Beach. St. Pete, St. Pete Beach, Clearwater residential, Gulfport, Dunedin = 30-day+.
A20: - Other SWFL: Cape Coral Gulf-access canals (33904/33914) are the best alternative market; Charlotte Harbor canals and unincorporated East Naples next. Avoid Pasco, Citrus, Hernando, City of Naples.
A21: - Keys: under $950k, documented income is almost all condos in a few STR-legal complexes (Ocean Pointe, Kawama, Hawks Cay). Houses with transferable rental rights are $1M+; county/Islamorada permits don't transfer, Marathon/Key Colony Beach (weekly) are the house plays. Keys insurance and HOAs push PITIA ~40% above the mainland.
A22: - PropertyRadar pull (193 listed absentee-owned homes, 3 counties): nothing beats 8404 43rd Ave Ter W. Best screen is 216 SW 29th St, Cape Coral (needs ~$52k gross for DSCR 1.00 at list) but it has no rental history; the only house with STR evidence is 930 SW 37th Ter, Cape Coral (state vacation-rental license, no $ figures).
A23: - All income is seller-stated until verified with 12-24 months of platform payouts + tourist-tax filings.

Sheet Assumptions
B1: STR / Seasonal DSCR Model: Assumptions
B2: As of 2026-10-18. Blue = input you can change. Yellow = key lever. Black = formula. Green = pulled from another tab.
B4: BUYER | C4: Value | I4: Note / source
B5: Credit score (FICO) | C5: 800 | I5: Per broker; top DSCR pricing tier.
B6: Cash earmarked for down + closing | C6: 150000 | I6: Per broker.
B7: Brokerage (reserves / extra down) | C7: 550000 | I7: Per broker. CPA: check capital gains before liquidating.
B8: Checking (EMD) | C8: 60000 | I8: Per broker. Earnest money 3-5% to compete.
B10: LOAN TERMS (DSCR) | C10: Value | I10: Note / source
B11: Rate at LTV > 75% (i.e., 80% LTV) | C11: 0.075 | I11: Placeholder for 800 FICO STR DSCR. Overwrite with live rate sheet.
B12: Rate at LTV > 70% to 75% | C12: 0.0725 | I12: Placeholder. Overwrite with live rate sheet.
B13: Rate at LTV <= 70% | C13: 0.07125 | I13: Placeholder. Overwrite with live rate sheet.
B14: Amortization (months) | C14: 360 | I14: 30-year fixed.
B15: Default down payment % | C15: 0.25 | I15: Recommended 25% (rate tier + DSCR + cash flow). Each candidate row can override.
B16: Closing costs (% of price) | C16: 0.04 | I16: Points/fees, FL doc stamps 0.35% + intangible 0.2% of loan, title, 12-mo prepaid insurance, escrow.
B17: Reserves required (months PITIA) | C17: 6 | I17: Covered by brokerage; shown for lender sizing only.
B18: Lender income haircut (counted share of gross) | C18: 0.8 | I18: Many STR DSCR lenders count ~80% of gross or T12 net of mgmt. Use DSCR (haircut) column to qualify.
B19: Default base insurance ($/yr): HO + wind + $1M STR liability | C19: 7000 | I19: Mainland CBS home ~$500k. Per-county overrides in the county table below (e.g., Monroe/Keys).
B21: FLOOD INSURANCE BY FEMA ZONE ($/yr) | C21: $/yr | I21: Note / source
B22: X | C22: 1000 | I22: Citizens requires flood on all wind policies by 1/1/2027, including X zones.
B23: AE | C23: 4500 | I23: NFIP Risk Rating 2.0 est.; elevation certificate drives price.
B24: VE | C24: 9000 | I24: Coastal high-hazard; avoid for this buyer.
B25: Unknown | C25: 2000 | I25: Placeholder until FEMA zone verified.
B27: BY COUNTY: PROPERTY TAX (% of price, non-homestead) + BASE INSURANCE | C27: Tax rate | D27: Base ins. $/yr | I27: Note / source
B28: Manatee | C28: 0.015 | D28: =$C$19 -> 7000 | I28: Unincorporated ~13.3 mills (2025) + city + non-ad valorem; reset to purchase price.
B29: Sarasota | C29: 0.0135 | D29: =$C$19 -> 7000 | I29: 11.47 mills countywide (2025); City of Sarasota ~14.9 mills.
B30: Pinellas | C30: 0.016 | D30: =$C$19 -> 7000 | I30: Beach towns ~15.8-16.6 mills (2025) + non-ad valorem; ~1.4-1.7% of price est.
B31: Lee | C31: 0.017 | D31: =$C$19 -> 7000 | I31: Placeholder: Cape Coral/Fort Myers ~16-19 mills; North Cape utility assessments extra (~$3.4k/yr).
B32: Charlotte | C32: 0.0165 | D32: =$C$19 -> 7000 | I32: Placeholder.
B33: Collier | C33: 0.014 | D33: =$C$19 -> 7000 | I33: Placeholder: lowest millage on the coast; ~1.4-1.5% incl. non-ad valorem.
B34: Monroe | C34: 0.0095 | D34: 8000 | I34: Keys: ~7.9-9.0 mills (2026) -> 0.70-0.90% of price + $800-1,200/yr non-ad valorem (solid waste, wastewater). Base ins. = wind + non-wind STR policy for an elevated CBS house; flood by zone on top (~$12.5k AE total). Ground-level pre-FIRM: override ~$20k+. Condos: per-row HO-6 override.
B36: OPERATING PROFILE | C36: Mgmt | D36: Platform | E36: Cleaning | F36: Maint/Supplies | G36: CapEx | H36: Non-mgmt total | I36: Note / source
B37: STR | C37: 0.2 | D37: 0.1 | E37: 0 | F37: 0.08 | G37: 0.05 | H37: =SUM(D37:G37) -> 0.23 | I37: Nightly/weekly. Full-service PM 18-30% locally; Airbnb host-only fee 15.5% (blended 10%); cleaning = 0: passed through to guests as a cleaning fee. Use gross EXCLUDING guest-paid cleaning fees.
B38: Seasonal | C38: 0.12 | D38: 0.02 | E38: 0 | F38: 0.06 | G38: 0.05 | H38: =SUM(D38:G38) -> 0.13 | I38: 30-day+ furnished (snowbird Jan-Apr, travel nurses, insurance displacement). Fewer turns.
B40: FIXED OPERATING COSTS ($/yr) | C40: $/yr | I40: Note / source
B41: Utilities (power, water, internet, streaming) | C41: 6000 | I41: Owner-paid in furnished rentals.
B42: Pool + lawn + pest (with pool) | C42: 3000
B43: Lawn + pest (no pool) | C43: 1200

Sheet Manatee-Sarasota
A1: Manatee + Sarasota County: STR / Seasonal Candidates with Documented Income
A2: Active as of 2026-10-18. Screened ~600 listings across Zillow (14 keyword sweeps), Redfin, brokerages and STR marketplaces. Yellow rows = recommended.
A3: Edit blue cells (Offer Price, Seller Credit %, Down Pmt %, Income, Flood Zone, Ins Override) to rerun. Ins Override (blank = county base + flood) is for condos with master wind/flood policies. Qualify on DSCR (lender haircut) >= 1.00; >= 1.15 preferred. Income is seller-stated until verified with platform payout reports.
A5: Rank | B5: Address | C5: City / ZIP | D5: County | E5: Type | F5: Bd/Ba/SqFt/Yr | G5: List Price | H5: Offer Price | I5: Seller Credit % | J5: Down Pmt % | K5: Stated Gross Income ($/yr) | L5: Income Basis (seller-stated) | M5: Flood Zone | N5: Pool | O5: HOA ($/mo) | P5: Ins Override ($/yr) | Q5: Profile | R5: Loan Amount | S5: Rate | T5: P&I ($/mo) | U5: Taxes ($/mo) | V5: Ins + Flood ($/mo) | W5: PITIA ($/mo) | X5: DSCR (gross) | Y5: DSCR (lender haircut) | Z5: Cash to Close | AA5: Reserves (6 mo) | AB5: Opex excl. Mgmt ($/yr) | AC5: Mgmt ($/yr) | AD5: Cash Flow Self-Managed ($/yr) | AE5: Cash Flow Full PM ($/yr) | AF5: Gross Yield | AG5: Cap Rate (w/ PM) | AH5: Last Sale | AI5: DOM | AJ5: Key Risks / Notes | AK5: Listing Link
A6: 1 | B6: 8404 43rd Ave Terrace W | C6: Bradenton 34209 | D6: Manatee | E6: SFR | F6: 4/2 / 1,430 / 1978 | G6: 584900 | H6: 560000 | I6: 0.03 | J6: =Assumptions!$C$15 -> 0.25 | K6: 85000 | L6: "almost $85,000 in gross revenue over the past 12 months" (T12) | M6: Unknown | N6: Y | O6: 0 | Q6: STR | R6: =H6*(1-J6) -> 420000 | S6: =IF((1-J6)>0.75,Assumptions!$C$11,IF((1-J6)>0.7,Assumptions!$C$12,Assumptions!$C$13)) -> 0.0725 | T6: =PMT(S6/12,Assumptions!$C$14,-R6) -> 2865.1404 | U6: =H6*INDEX(Assumptions!$C$28:$C$34,MATCH(D6,Assumptions!$B$28:$B$34,0))/12 -> 700 | V6: =IF(ISNUMBER(P6),P6,INDEX(Assumptions!$D$28:$D$34,MATCH(D6,Assumptions!$B$28:$B$34,0))+INDEX(Assumptions!$C$22:$C$25,MATCH(M6,Assumptions!$B$22:$B$25,0)))/12 -> 750 | W6: =T6+U6+V6+O6 -> 4315.1404 | X6: =IFERROR(K6/12/W6,0) -> 1.641507 | Y6: =IFERROR(K6*Assumptions!$C$18/12/W6,0) -> 1.3132056 | Z6: =H6*J6+H6*(Assumptions!$C$16-I6) -> 145600 | AA6: =W6*Assumptions!$C$17 -> 25890.842 | AB6: =K6*INDEX(Assumptions!$H$37:$H$38,MATCH(Q6,Assumptions!$B$37:$B$38,0))+Assumptions!$C$41+IF(N6="Y",Assumptions!$C$42,Assumptions!$C$43) -> 28550 | AC6: =K6*INDEX(Assumptions!$C$37:$C$38,MATCH(Q6,Assumptions!$B$37:$B$38,0)) -> 17000 | AD6: =K6-AB6-W6*12 -> 4668.3155 | AE6: =AD6-AC6 -> -12331.685 | AF6: =IFERROR(K6/H6,0) -> 0.15178571 | AG6: =IFERROR((K6-AB6-AC6)/H6,0) -> 0.070446429 | AH6: $595,000 (Aug 2023) | AI6: 21 | AJ6: Heated pool + spa, no HOA, turnkey; full 2021 reno (roof/HVAC/windows/plumbing/electric). First Street flood 7/10; neighbor parcel AE/X: get FEMA zone + elevation cert + CLUE. Featured in national STR newsletter 9/29: move fast. Uninc. Manatee: nightly legal. | AK6: Zillow
A7: 2 | B7: 5318 17th St W (duplex) | C7: Bradenton 34207 | D7: Manatee | E7: Duplex | F7: 2 units / 1,740 / 1971 | G7: 475000 | H7: 460000 | I7: 0 | J7: =Assumptions!$C$15 -> 0.25 | K7: 73000 | L7: Unit B Airbnb "over $53,000 in 2025" + Unit A LTR (est. ~$20k/yr; rent not stated) | M7: Unknown | N7: N | O7: 0 | Q7: STR | R7: =H7*(1-J7) -> 345000 | S7: =IF((1-J7)>0.75,Assumptions!$C$11,IF((1-J7)>0.7,Assumptions!$C$12,Assumptions!$C$13)) -> 0.0725 | T7: =PMT(S7/12,Assumptions!$C$14,-R7) -> 2353.5082 | U7: =H7*INDEX(Assumptions!$C$28:$C$34,MATCH(D7,Assumptions!$B$28:$B$34,0))/12 -> 575 | V7: =IF(ISNUMBER(P7),P7,INDEX(Assumptions!$D$28:$D$34,MATCH(D7,Assumptions!$B$28:$B$34,0))+INDEX(Assumptions!$C$22:$C$25,MATCH(M7,Assumptions!$B$22:$B$25,0)))/12 -> 750 | W7: =T7+U7+V7+O7 -> 3678.5082 | X7: =IFERROR(K7/12/W7,0) -> 1.6537501 | Y7: =IFERROR(K7*Assumptions!$C$18/12/W7,0) -> 1.3230001 | Z7: =H7*J7+H7*(Assumptions!$C$16-I7) -> 133400 | AA7: =W7*Assumptions!$C$17 -> 22071.049 | AB7: =K7*INDEX(Assumptions!$H$37:$H$38,MATCH(Q7,Assumptions!$B$37:$B$38,0))+Assumptions!$C$41+IF(N7="Y",Assumptions!$C$42,Assumptions!$C$43) -> 23990 | AC7: =K7*INDEX(Assumptions!$C$37:$C$38,MATCH(Q7,Assumptions!$B$37:$B$38,0)) -> 14600 | AD7: =K7-AB7-W7*12 -> 4867.902 | AE7: =AD7-AC7 -> -9732.098 | AF7: =IFERROR(K7/H7,0) -> 0.15869565 | AG7: =IFERROR((K7-AB7-AC7)/H7,0) -> 0.074804348 | AH7: $420,000 (Apr 2024) | AI7: 14 | AJ7: Zoned RSF-6 and listed as SFR: confirm legal nonconforming duplex. Confirm lender blends STR + LTR income. Opex model applies STR costs to all income (conservative). | AK7: Zillow
A8: 3 | B8: 2801 23rd Ave W ("Beachin' Escape") | C8: Bradenton 34205 | D8: Manatee | E8: SFR | F8: 4/2 / 1,906 (PR 1,564) / 1968 | G8: 645000 | H8: 600000 | I8: 0.03 | J8: =Assumptions!$C$15 -> 0.25 | K8: 89000 | L8: "$89,000 gross vacation-rental revenue in 2025"; "$91,500 in booked 2026 revenue" | M8: Unknown | N8: Y | O8: 0 | Q8: STR | R8: =H8*(1-J8) -> 450000 | S8: =IF((1-J8)>0.75,Assumptions!$C$11,IF((1-J8)>0.7,Assumptions!$C$12,Assumptions!$C$13)) -> 0.0725 | T8: =PMT(S8/12,Assumptions!$C$14,-R8) -> 3069.7933 | U8: =H8*INDEX(Assumptions!$C$28:$C$34,MATCH(D8,Assumptions!$B$28:$B$34,0))/12 -> 750 | V8: =IF(ISNUMBER(P8),P8,INDEX(Assumptions!$D$28:$D$34,MATCH(D8,Assumptions!$B$28:$B$34,0))+INDEX(Assumptions!$C$22:$C$25,MATCH(M8,Assumptions!$B$22:$B$25,0)))/12 -> 750 | W8: =T8+U8+V8+O8 -> 4569.7933 | X8: =IFERROR(K8/12/W8,0) -> 1.6229764 | Y8: =IFERROR(K8*Assumptions!$C$18/12/W8,0) -> 1.2983811 | Z8: =H8*J8+H8*(Assumptions!$C$16-I8) -> 156000 | AA8: =W8*Assumptions!$C$17 -> 27418.76 | AB8: =K8*INDEX(Assumptions!$H$37:$H$38,MATCH(Q8,Assumptions!$B$37:$B$38,0))+Assumptions!$C$41+IF(N8="Y",Assumptions!$C$42,Assumptions!$C$43) -> 29470 | AC8: =K8*INDEX(Assumptions!$C$37:$C$38,MATCH(Q8,Assumptions!$B$37:$B$38,0)) -> 17800 | AD8: =K8-AB8-W8*12 -> 4692.4809 | AE8: =AD8-AC8 -> -13107.519 | AF8: =IFERROR(K8/H8,0) -> 0.14833333 | AG8: =IFERROR((K8-AB8-AC8)/H8,0) -> 0.06955 | AH8: $474,000 (Mar 2024) | AI8: 23 | AJ8: Strongest track record. Appraisal risk: +36% vs 2024 purchase; public record 1,564 sf vs 1,906 marketed (possible unpermitted space); contract fell through 9/27-9/29: ask why. Listed by Locals Property Mgmt. | AK8: Zillow
A9: 4 | B9: 2245 Bahia Vista St (duplex) | C9: Sarasota 34239 | D9: Sarasota | E9: Duplex | F9: 2/1 + 1/1 / 1,652 / 1936 | G9: 475000 | H9: 455000 | I9: 0 | J9: =Assumptions!$C$15 -> 0.25 | K9: 60000 | L9: "currently generates more than $60,000 annually"; income + expenses available | M9: X | N9: N | O9: 0 | Q9: STR | R9: =H9*(1-J9) -> 341250 | S9: =IF((1-J9)>0.75,Assumptions!$C$11,IF((1-J9)>0.7,Assumptions!$C$12,Assumptions!$C$13)) -> 0.0725 | T9: =PMT(S9/12,Assumptions!$C$14,-R9) -> 2327.9266 | U9: =H9*INDEX(Assumptions!$C$28:$C$34,MATCH(D9,Assumptions!$B$28:$B$34,0))/12 -> 511.875 | V9: =IF(ISNUMBER(P9),P9,INDEX(Assumptions!$D$28:$D$34,MATCH(D9,Assumptions!$B$28:$B$34,0))+INDEX(Assumptions!$C$22:$C$25,MATCH(M9,Assumptions!$B$22:$B$25,0)))/12 -> 666.66667 | W9: =T9+U9+V9+O9 -> 3506.4682 | X9: =IFERROR(K9/12/W9,0) -> 1.4259362 | Y9: =IFERROR(K9*Assumptions!$C$18/12/W9,0) -> 1.140749 | Z9: =H9*J9+H9*(Assumptions!$C$16-I9) -> 131950 | AA9: =W9*Assumptions!$C$17 -> 21038.809 | AB9: =K9*INDEX(Assumptions!$H$37:$H$38,MATCH(Q9,Assumptions!$B$37:$B$38,0))+Assumptions!$C$41+IF(N9="Y",Assumptions!$C$42,Assumptions!$C$43) -> 21000 | AC9: =K9*INDEX(Assumptions!$C$37:$C$38,MATCH(Q9,Assumptions!$B$37:$B$38,0)) -> 12000 | AD9: =K9-AB9-W9*12 -> -3077.6187 | AE9: =AD9-AC9 -> -15077.619 | AF9: =IFERROR(K9/H9,0) -> 0.13186813 | AG9: =IFERROR((K9-AB9-AC9)/H9,0) -> 0.059340659 | AH9: Listed $545k (May 2025) -> $475k | AI9: 78 | AJ9: City of Sarasota 7-night minimum + annual registration/inspection. 1936 build: 4-point/insurance risk. 2025 roof. Land-value upside. | AK9: Zillow
A10: 5 | B10: 1415 36th St W ("Bamboo Lagoon") | C10: Bradenton 34205 | D10: Manatee | E10: SFR | F10: 3/2 / 1,176 / 1972 | G10: 474999 | H10: 474999 | I10: 0 | J10: =Assumptions!$C$15 -> 0.25 | K10: 54000 | L10: "$45,200 gross revenue YTD at 86% occupancy"; 4.99 stars / 82 reviews; bookings convey | M10: X | N10: Y | O10: 0 | Q10: STR | R10: =H10*(1-J10) -> 356249.25 | S10: =IF((1-J10)>0.75,Assumptions!$C$11,IF((1-J10)>0.7,Assumptions!$C$12,Assumptions!$C$13)) -> 0.0725 | T10: =PMT(S10/12,Assumptions!$C$14,-R10) -> 2430.2479 | U10: =H10*INDEX(Assumptions!$C$28:$C$34,MATCH(D10,Assumptions!$B$28:$B$34,0))/12 -> 593.74875 | V10: =IF(ISNUMBER(P10),P10,INDEX(Assumptions!$D$28:$D$34,MATCH(D10,Assumptions!$B$28:$B$34,0))+INDEX(Assumptions!$C$22:$C$25,MATCH(M10,Assumptions!$B$22:$B$25,0)))/12 -> 666.66667 | W10: =T10+U10+V10+O10 -> 3690.6633 | X10: =IFERROR(K10/12/W10,0) -> 1.219293 | Y10: =IFERROR(K10*Assumptions!$C$18/12/W10,0) -> 0.97543442 | Z10: =H10*J10+H10*(Assumptions!$C$16-I10) -> 137749.71 | AA10: =W10*Assumptions!$C$17 -> 22143.98 | AB10: =K10*INDEX(Assumptions!$H$37:$H$38,MATCH(Q10,Assumptions!$B$37:$B$38,0))+Assumptions!$C$41+IF(N10="Y",Assumptions!$C$42,Assumptions!$C$43) -> 21420 | AC10: =K10*INDEX(Assumptions!$C$37:$C$38,MATCH(Q10,Assumptions!$B$37:$B$38,0)) -> 10800 | AD10: =K10-AB10-W10*12 -> -11707.96 | AE10: =AD10-AC10 -> -22507.96 | AF10: =IFERROR(K10/H10,0) -> 0.11368445 | AG10: =IFERROR((K10-AB10-AC10)/H10,0) -> 0.045852728 | AH10: $349,000 (Dec 2024) | AI10: 18 | AJ10: Appraisal risk: +36% vs Dec 2024 purchase. Pool likely added after purchase. | AK10: Zillow
A11: 6 | B11: 3409 18th Avenue Dr W | C11: Bradenton 34205 | D11: Manatee | E11: SFR | F11: 3/2 / 1,644 / 1971 | G11: 529000 | H11: 515000 | I11: 0 | J11: =Assumptions!$C$15 -> 0.25 | K11: 60000 | L11: "over $53,000 in bookings so far this year" | M11: Unknown | N11: Y | O11: 0 | Q11: STR | R11: =H11*(1-J11) -> 386250 | S11: =IF((1-J11)>0.75,Assumptions!$C$11,IF((1-J11)>0.7,Assumptions!$C$12,Assumptions!$C$13)) -> 0.0725 | T11: =PMT(S11/12,Assumptions!$C$14,-R11) -> 2634.9059 | U11: =H11*INDEX(Assumptions!$C$28:$C$34,MATCH(D11,Assumptions!$B$28:$B$34,0))/12 -> 643.75 | V11: =IF(ISNUMBER(P11),P11,INDEX(Assumptions!$D$28:$D$34,MATCH(D11,Assumptions!$B$28:$B$34,0))+INDEX(Assumptions!$C$22:$C$25,MATCH(M11,Assumptions!$B$22:$B$25,0)))/12 -> 750 | W11: =T11+U11+V11+O11 -> 4028.6559 | X11: =IFERROR(K11/12/W11,0) -> 1.2411087 | Y11: =IFERROR(K11*Assumptions!$C$18/12/W11,0) -> 0.99288699 | Z11: =H11*J11+H11*(Assumptions!$C$16-I11) -> 149350 | AA11: =W11*Assumptions!$C$17 -> 24171.935 | AB11: =K11*INDEX(Assumptions!$H$37:$H$38,MATCH(Q11,Assumptions!$B$37:$B$38,0))+Assumptions!$C$41+IF(N11="Y",Assumptions!$C$42,Assumptions!$C$43) -> 22800 | AC11: =K11*INDEX(Assumptions!$C$37:$C$38,MATCH(Q11,Assumptions!$B$37:$B$38,0)) -> 12000 | AD11: =K11-AB11-W11*12 -> -11143.871 | AE11: =AD11-AC11 -> -23143.871 | AF11: =IFERROR(K11/H11,0) -> 0.11650485 | AG11: =IFERROR((K11-AB11-AC11)/H11,0) -> 0.048932039 | AH11: $525,000 (Jun 2024) | AI11: 58 | AJ11: Two price cuts ($550k -> $529k). Roof 2024. City of Bradenton zoning (R1C): STR certificate required. | AK11: Zillow
A12: 7 | B12: 2142 Waldemere St | C12: Sarasota 34239 | D12: Sarasota | E12: SFR | F12: 3/2 / 1,170 / 1952 | G12: 524900 | H12: 505000 | I12: 0 | J12: =Assumptions!$C$15 -> 0.25 | K12: 50157 | L12: "$50,157 gross rental revenue in 2025 and $55,323 in 2024"; Jan-Apr ~$8k/mo | M12: X | N12: N | O12: 0 | Q12: STR | R12: =H12*(1-J12) -> 378750 | S12: =IF((1-J12)>0.75,Assumptions!$C$11,IF((1-J12)>0.7,Assumptions!$C$12,Assumptions!$C$13)) -> 0.0725 | T12: =PMT(S12/12,Assumptions!$C$14,-R12) -> 2583.7427 | U12: =H12*INDEX(Assumptions!$C$28:$C$34,MATCH(D12,Assumptions!$B$28:$B$34,0))/12 -> 568.125 | V12: =IF(ISNUMBER(P12),P12,INDEX(Assumptions!$D$28:$D$34,MATCH(D12,Assumptions!$B$28:$B$34,0))+INDEX(Assumptions!$C$22:$C$25,MATCH(M12,Assumptions!$B$22:$B$25,0)))/12 -> 666.66667 | W12: =T12+U12+V12+O12 -> 3818.5343 | X12: =IFERROR(K12/12/W12,0) -> 1.0945954 | Y12: =IFERROR(K12*Assumptions!$C$18/12/W12,0) -> 0.8756763 | Z12: =H12*J12+H12*(Assumptions!$C$16-I12) -> 146450 | AA12: =W12*Assumptions!$C$17 -> 22911.206 | AB12: =K12*INDEX(Assumptions!$H$37:$H$38,MATCH(Q12,Assumptions!$B$37:$B$38,0))+Assumptions!$C$41+IF(N12="Y",Assumptions!$C$42,Assumptions!$C$43) -> 18736.11 | AC12: =K12*INDEX(Assumptions!$C$37:$C$38,MATCH(Q12,Assumptions!$B$37:$B$38,0)) -> 10031.4 | AD12: =K12-AB12-W12*12 -> -14401.522 | AE12: =AD12-AC12 -> -24432.922 | AF12: =IFERROR(K12/H12,0) -> 0.099320792 | AG12: =IFERROR((K12-AB12-AC12)/H12,0) -> 0.042355426 | AH12: $440,000 (Jun 2023) | AI12: 16 | AJ12: City 7-night min. "Previously operated": confirm still active. Sold as-is; metal roof 2026. | AK12: Zillow
A13: 8 | B13: 7405 12th Ave W | C13: Bradenton 34209 | D13: Manatee | E13: SFR | F13: 2/2 / 1,469 / 1973 | G13: 550000 | H13: 530000 | I13: 0 | J13: =Assumptions!$C$15 -> 0.25 | K13: 48000 | L13: "just under a year... nearly $45,000 in rental income" | M13: Unknown | N13: Y | O13: 8 | Q13: STR | R13: =H13*(1-J13) -> 397500 | S13: =IF((1-J13)>0.75,Assumptions!$C$11,IF((1-J13)>0.7,Assumptions!$C$12,Assumptions!$C$13)) -> 0.0725 | T13: =PMT(S13/12,Assumptions!$C$14,-R13) -> 2711.6507 | U13: =H13*INDEX(Assumptions!$C$28:$C$34,MATCH(D13,Assumptions!$B$28:$B$34,0))/12 -> 662.5 | V13: =IF(ISNUMBER(P13),P13,INDEX(Assumptions!$D$28:$D$34,MATCH(D13,Assumptions!$B$28:$B$34,0))+INDEX(Assumptions!$C$22:$C$25,MATCH(M13,Assumptions!$B$22:$B$25,0)))/12 -> 750 | W13: =T13+U13+V13+O13 -> 4132.1507 | X13: =IFERROR(K13/12/W13,0) -> 0.9680189 | Y13: =IFERROR(K13*Assumptions!$C$18/12/W13,0) -> 0.77441512 | Z13: =H13*J13+H13*(Assumptions!$C$16-I13) -> 153700 | AA13: =W13*Assumptions!$C$17 -> 24792.904 | AB13: =K13*INDEX(Assumptions!$H$37:$H$38,MATCH(Q13,Assumptions!$B$37:$B$38,0))+Assumptions!$C$41+IF(N13="Y",Assumptions!$C$42,Assumptions!$C$43) -> 20040 | AC13: =K13*INDEX(Assumptions!$C$37:$C$38,MATCH(Q13,Assumptions!$B$37:$B$38,0)) -> 9600 | AD13: =K13-AB13-W13*12 -> -21625.809 | AE13: =AD13-AC13 -> -31225.809 | AF13: =IFERROR(K13/H13,0) -> 0.090566038 | AG13: =IFERROR((K13-AB13-AC13)/H13,0) -> 0.034641509 | AH13: $75,000 (2016) | AI13: 12 | AJ13: <12 months history; 2BR. Solar 'majority owned': check lien on remainder. | AK13: Zillow
A14: 9 | B14: 2705 2nd Ave W | C14: Bradenton 34205 | D14: Manatee | E14: SFR | F14: 2/1 / 1,198 / 1925 | G14: 385000 | H14: 360000 | I14: 0 | J14: =Assumptions!$C$15 -> 0.25 | K14: 40000 | L14: "currently brings in $40K/year in gross income" | M14: X | N14: N | O14: 0 | Q14: STR | R14: =H14*(1-J14) -> 270000 | S14: =IF((1-J14)>0.75,Assumptions!$C$11,IF((1-J14)>0.7,Assumptions!$C$12,Assumptions!$C$13)) -> 0.0725 | T14: =PMT(S14/12,Assumptions!$C$14,-R14) -> 1841.876 | U14: =H14*INDEX(Assumptions!$C$28:$C$34,MATCH(D14,Assumptions!$B$28:$B$34,0))/12 -> 450 | V14: =IF(ISNUMBER(P14),P14,INDEX(Assumptions!$D$28:$D$34,MATCH(D14,Assumptions!$B$28:$B$34,0))+INDEX(Assumptions!$C$22:$C$25,MATCH(M14,Assumptions!$B$22:$B$25,0)))/12 -> 666.66667 | W14: =T14+U14+V14+O14 -> 2958.5426 | X14: =IFERROR(K14/12/W14,0) -> 1.1266809 | Y14: =IFERROR(K14*Assumptions!$C$18/12/W14,0) -> 0.90134468 | Z14: =H14*J14+H14*(Assumptions!$C$16-I14) -> 104400 | AA14: =W14*Assumptions!$C$17 -> 17751.256 | AB14: =K14*INDEX(Assumptions!$H$37:$H$38,MATCH(Q14,Assumptions!$B$37:$B$38,0))+Assumptions!$C$41+IF(N14="Y",Assumptions!$C$42,Assumptions!$C$43) -> 16400 | AC14: =K14*INDEX(Assumptions!$C$37:$C$38,MATCH(Q14,Assumptions!$B$37:$B$38,0)) -> 8000 | AD14: =K14-AB14-W14*12 -> -11902.511 | AE14: =AD14-AC14 -> -19902.511 | AF14: =IFERROR(K14/H14,0) -> 0.11111111 | AG14: =IFERROR((K14-AB14-AC14)/H14,0) -> 0.043333333 | AH14: $240,000 (May 2021) | AI14: 214 | AJ14: 377 cumulative DOM: very negotiable. 1BA, 1925: insurance. City of Bradenton certificate. | AK14: Zillow
A15: 10 | B15: 4711 Hollingsworth Ave (3 units) | C15: Sarasota 34233 | D15: Sarasota | E15: Triplex | F15: 3 furnished units / 1,696 / 1981 | G15: 655000 | H15: 655000 | I15: 0 | J15: =Assumptions!$C$15 -> 0.25 | K15: 102000 | L15: "averaging approximately $102,000 in annual revenue during 2024-2025"; OM available | M15: Unknown | N15: N | O15: 0 | Q15: Seasonal | R15: =H15*(1-J15) -> 491250 | S15: =IF((1-J15)>0.75,Assumptions!$C$11,IF((1-J15)>0.7,Assumptions!$C$12,Assumptions!$C$13)) -> 0.0725 | T15: =PMT(S15/12,Assumptions!$C$14,-R15) -> 3351.191 | U15: =H15*INDEX(Assumptions!$C$28:$C$34,MATCH(D15,Assumptions!$B$28:$B$34,0))/12 -> 736.875 | V15: =IF(ISNUMBER(P15),P15,INDEX(Assumptions!$D$28:$D$34,MATCH(D15,Assumptions!$B$28:$B$34,0))+INDEX(Assumptions!$C$22:$C$25,MATCH(M15,Assumptions!$B$22:$B$25,0)))/12 -> 750 | W15: =T15+U15+V15+O15 -> 4838.066 | X15: =IFERROR(K15/12/W15,0) -> 1.7569004 | Y15: =IFERROR(K15*Assumptions!$C$18/12/W15,0) -> 1.4055203 | Z15: =H15*J15+H15*(Assumptions!$C$16-I15) -> 189950 | AA15: =W15*Assumptions!$C$17 -> 29028.396 | AB15: =K15*INDEX(Assumptions!$H$37:$H$38,MATCH(Q15,Assumptions!$B$37:$B$38,0))+Assumptions!$C$41+IF(N15="Y",Assumptions!$C$42,Assumptions!$C$43) -> 20460 | AC15: =K15*INDEX(Assumptions!$C$37:$C$38,MATCH(Q15,Assumptions!$B$37:$B$38,0)) -> 12240 | AD15: =K15-AB15-W15*12 -> 23483.208 | AE15: =AD15-AC15 -> 11243.208 | AF15: =IFERROR(K15/H15,0) -> 0.15572519 | AG15: =IFERROR((K15-AB15-AC15)/H15,0) -> 0.10580153 | AH15: $350,000 (Feb 2022) | AI15: 5 | AJ15: Unincorporated Sarasota County: <30-day banned in this zoning -> 30-day+ model. Zestimate ~$325k: will NOT appraise for DSCR. Seller financing offered: pursue only on seller terms. | AK15: Zillow
A16: 11 | B16: 4440 47th Ave W #102 (Shorewalk condo) | C16: Bradenton 34210 | D16: Manatee | E16: Condo | F16: 2/2 / 1,174 / 1989 | G16: 279000 | H16: 279000 | I16: 0 | J16: =Assumptions!$C$15 -> 0.25 | K16: 44000 | L16: "Gross rental earnings for January-June are $29,300"; 4.96 stars | M16: Unknown | N16: N | O16: 477 | Q16: STR | R16: =H16*(1-J16) -> 209250 | S16: =IF((1-J16)>0.75,Assumptions!$C$11,IF((1-J16)>0.7,Assumptions!$C$12,Assumptions!$C$13)) -> 0.0725 | T16: =PMT(S16/12,Assumptions!$C$14,-R16) -> 1427.4539 | U16: =H16*INDEX(Assumptions!$C$28:$C$34,MATCH(D16,Assumptions!$B$28:$B$34,0))/12 -> 348.75 | V16: =IF(ISNUMBER(P16),P16,INDEX(Assumptions!$D$28:$D$34,MATCH(D16,Assumptions!$B$28:$B$34,0))+INDEX(Assumptions!$C$22:$C$25,MATCH(M16,Assumptions!$B$22:$B$25,0)))/12 -> 750 | W16: =T16+U16+V16+O16 -> 3003.2039 | X16: =IFERROR(K16/12/W16,0) -> 1.2209183 | Y16: =IFERROR(K16*Assumptions!$C$18/12/W16,0) -> 0.97673467 | Z16: =H16*J16+H16*(Assumptions!$C$16-I16) -> 80910 | AA16: =W16*Assumptions!$C$17 -> 18019.223 | AB16: =K16*INDEX(Assumptions!$H$37:$H$38,MATCH(Q16,Assumptions!$B$37:$B$38,0))+Assumptions!$C$41+IF(N16="Y",Assumptions!$C$42,Assumptions!$C$43) -> 17320 | AC16: =K16*INDEX(Assumptions!$C$37:$C$38,MATCH(Q16,Assumptions!$B$37:$B$38,0)) -> 8800 | AD16: =K16-AB16-W16*12 -> -9358.4464 | AE16: =AD16-AC16 -> -18158.446 | AF16: =IFERROR(K16/H16,0) -> 0.15770609 | AG16: =IFERROR((K16-AB16-AC16)/H16,0) -> 0.064086022 | AI16: 55 | AJ16: Cheapest entry. Shorewalk rental pool may be underwritten as condotel/non-warrantable (75% LTV, fewer lenders). | AK16: Zillow
A17: 12 | B17: 539 Forest Way (Cedars East, LBK) | C17: Longboat Key 34228 | D17: Sarasota | E17: Townhome | F17: 2/2.5 / 1,440 / 1990 | G17: 639000 | H17: 639000 | I17: 0 | J17: =Assumptions!$C$15 -> 0.25 | K17: 50000 | L17: "~$50,000 average annual rental payout revenue, after Airbnb and VRBO fees" | M17: AE | N17: N | O17: 945 | Q17: STR | R17: =H17*(1-J17) -> 479250 | S17: =IF((1-J17)>0.75,Assumptions!$C$11,IF((1-J17)>0.7,Assumptions!$C$12,Assumptions!$C$13)) -> 0.0725 | T17: =PMT(S17/12,Assumptions!$C$14,-R17) -> 3269.3298 | U17: =H17*INDEX(Assumptions!$C$28:$C$34,MATCH(D17,Assumptions!$B$28:$B$34,0))/12 -> 718.875 | V17: =IF(ISNUMBER(P17),P17,INDEX(Assumptions!$D$28:$D$34,MATCH(D17,Assumptions!$B$28:$B$34,0))+INDEX(Assumptions!$C$22:$C$25,MATCH(M17,Assumptions!$B$22:$B$25,0)))/12 -> 958.33333 | W17: =T17+U17+V17+O17 -> 5891.5382 | X17: =IFERROR(K17/12/W17,0) -> 0.707229 | Y17: =IFERROR(K17*Assumptions!$C$18/12/W17,0) -> 0.5657832 | Z17: =H17*J17+H17*(Assumptions!$C$16-I17) -> 185310 | AA17: =W17*Assumptions!$C$17 -> 35349.229 | AB17: =K17*INDEX(Assumptions!$H$37:$H$38,MATCH(Q17,Assumptions!$B$37:$B$38,0))+Assumptions!$C$41+IF(N17="Y",Assumptions!$C$42,Assumptions!$C$43) -> 18700 | AC17: =K17*INDEX(Assumptions!$C$37:$C$38,MATCH(Q17,Assumptions!$B$37:$B$38,0)) -> 10000 | AD17: =K17-AB17-W17*12 -> -39398.458 | AE17: =AD17-AC17 -> -49398.458 | AF17: =IFERROR(K17/H17,0) -> 0.078247261 | AG17: =IFERROR((K17-AB17-AC17)/H17,0) -> 0.033333333 | AI17: 27 | AJ17: Shown as a reject example: $945/mo HOA + max 26 rentals/yr kills DSCR. | AK17: Zillow
A20: Operating STRs with no $ in listing: request T12 payouts (could become candidates)
B21: Address | C21: City / ZIP | G21: Price | L21: Evidence (no $ in listing) | AJ21: Ask agent for | AK21: Link
B22: 8403 13th Ave NW | C22: Bradenton 34209 | G22: 619000 | L22: "highly successful, income-generating VRBO"; no rental restrictions; outside flood zone; 147 DOM, 3 cuts | AJ22: T12 payout reports + TDT filings | AK22: Zillow
B23: 926 Plum Tree Ln | C23: Sarasota 34243 (Manatee Co.) | G23: 524900 | L23: "active, successful vacation rental with daily rentals allowed"; no HOA | AJ23: T12 payout reports + TDT filings | AK23: Zillow
B24: 2714 42nd St W | C24: Bradenton 34205 | G24: 499000 | L24: 4BR pool; "currently operating as a successful short-term rental" | AJ24: T12 payout reports + TDT filings | AK24: Zillow
B25: 120 60th St W | C25: Bradenton 34209 | G25: 450000 | L25: "proven rental history available upon request"; 7 price cuts ($549k -> $450k) | AJ25: T12 payout reports + TDT filings | AK25: Zillow
B26: 1214 21st St W | C26: Bradenton 34205 | G26: 625000 | L26: "ESTABLISHED SUCCESSFUL SHORT-TERM RENTAL"; salt pool + spa; impact windows | AJ26: T12 payout reports + TDT filings | AK26: Zillow
B27: 6215 Rodgers Ave | C27: Sarasota 34231 | G27: 419999 | L27: "proven Airbnb performer"; near Siesta; 291 DOM. County 30-day rule applies -> seasonal only | AJ27: T12 payout reports + TDT filings | AK27: Zillow
B28: 1664 Lakeview Pl | C28: Englewood 34223 | G28: 374900 | L28: "proven vacation rental", pool, 1-month minimum (seasonal model) | AJ28: T12 payout reports + TDT filings | AK28: Zillow

Sheet Pinellas
A1: Pinellas County: STR / Seasonal Candidates with Documented Income
A2: Active as of 2026-10-18. Same method: Zillow keyword sweeps with full remarks + jurisdiction rules.
A3: Edit blue cells (Offer Price, Seller Credit %, Down Pmt %, Income, Flood Zone, Ins Override) to rerun. Ins Override (blank = county base + flood) is for condos with master wind/flood policies. Qualify on DSCR (lender haircut) >= 1.00; >= 1.15 preferred. Income is seller-stated until verified with platform payout reports.
A5: Rank | B5: Address | C5: City / ZIP | D5: County | E5: Type | F5: Bd/Ba/SqFt/Yr | G5: List Price | H5: Offer Price | I5: Seller Credit % | J5: Down Pmt % | K5: Stated Gross Income ($/yr) | L5: Income Basis (seller-stated) | M5: Flood Zone | N5: Pool | O5: HOA ($/mo) | P5: Ins Override ($/yr) | Q5: Profile | R5: Loan Amount | S5: Rate | T5: P&I ($/mo) | U5: Taxes ($/mo) | V5: Ins + Flood ($/mo) | W5: PITIA ($/mo) | X5: DSCR (gross) | Y5: DSCR (lender haircut) | Z5: Cash to Close | AA5: Reserves (6 mo) | AB5: Opex excl. Mgmt ($/yr) | AC5: Mgmt ($/yr) | AD5: Cash Flow Self-Managed ($/yr) | AE5: Cash Flow Full PM ($/yr) | AF5: Gross Yield | AG5: Cap Rate (w/ PM) | AH5: Last Sale | AI5: DOM | AJ5: Key Risks / Notes | AK5: Listing Link
A6: 1 | B6: 12565 81st Ave | C6: Seminole 33776 | D6: Pinellas | E6: SFR | F6: 3/2 / 1,306 / 1960 | G6: 499000 | H6: 485000 | I6: 0 | J6: =Assumptions!$C$15 -> 0.25 | K6: 71000 | L6: "approximately $71,000 in estimated annual revenue, 66% average occupancy, $252 ADR"; Airbnb since 2022 | M6: Unknown | N6: Y | O6: 0 | Q6: STR | R6: =H6*(1-J6) -> 363750 | S6: =IF((1-J6)>0.75,Assumptions!$C$11,IF((1-J6)>0.7,Assumptions!$C$12,Assumptions!$C$13)) -> 0.0725 | T6: =PMT(S6/12,Assumptions!$C$14,-R6) -> 2481.4162 | U6: =H6*INDEX(Assumptions!$C$28:$C$34,MATCH(D6,Assumptions!$B$28:$B$34,0))/12 -> 646.66667 | V6: =IF(ISNUMBER(P6),P6,INDEX(Assumptions!$D$28:$D$34,MATCH(D6,Assumptions!$B$28:$B$34,0))+INDEX(Assumptions!$C$22:$C$25,MATCH(M6,Assumptions!$B$22:$B$25,0)))/12 -> 750 | W6: =T6+U6+V6+O6 -> 3878.0829 | X6: =IFERROR(K6/12/W6,0) -> 1.5256679 | Y6: =IFERROR(K6*Assumptions!$C$18/12/W6,0) -> 1.2205343 | Z6: =H6*J6+H6*(Assumptions!$C$16-I6) -> 140650 | AA6: =W6*Assumptions!$C$17 -> 23268.497 | AB6: =K6*INDEX(Assumptions!$H$37:$H$38,MATCH(Q6,Assumptions!$B$37:$B$38,0))+Assumptions!$C$41+IF(N6="Y",Assumptions!$C$42,Assumptions!$C$43) -> 25330 | AC6: =K6*INDEX(Assumptions!$C$37:$C$38,MATCH(Q6,Assumptions!$B$37:$B$38,0)) -> 14200 | AD6: =K6-AB6-W6*12 -> -866.99462 | AE6: =AD6-AC6 -> -15066.995 | AF6: =IFERROR(K6/H6,0) -> 0.14639175 | AG6: =IFERROR((K6-AB6-AC6)/H6,0) -> 0.064886598 | AI6: 29 | AJ6: Heated pool, furnished, 'city-approved STR license' (City of Seminole: confirm rules + transfer). Best Pinellas house found. Inland: ~10-15 min to Madeira/Indian Rocks beaches. | AK6: Zillow
A7: 2 | B7: 4000 46th St N | C7: St Petersburg 33714 | D7: Pinellas | E7: SFR | F7: 4/2 / 1,579 / 1936 | G7: 500000 | H7: 485000 | I7: 0 | J7: =Assumptions!$C$15 -> 0.25 | K7: 85000 | L7: "already on pace to do over $85k of Gross Income in it's first full year as a short term rental" | M7: Unknown | N7: Y | O7: 0 | Q7: STR | R7: =H7*(1-J7) -> 363750 | S7: =IF((1-J7)>0.75,Assumptions!$C$11,IF((1-J7)>0.7,Assumptions!$C$12,Assumptions!$C$13)) -> 0.0725 | T7: =PMT(S7/12,Assumptions!$C$14,-R7) -> 2481.4162 | U7: =H7*INDEX(Assumptions!$C$28:$C$34,MATCH(D7,Assumptions!$B$28:$B$34,0))/12 -> 646.66667 | V7: =IF(ISNUMBER(P7),P7,INDEX(Assumptions!$D$28:$D$34,MATCH(D7,Assumptions!$B$28:$B$34,0))+INDEX(Assumptions!$C$22:$C$25,MATCH(M7,Assumptions!$B$22:$B$25,0)))/12 -> 750 | W7: =T7+U7+V7+O7 -> 3878.0829 | X7: =IFERROR(K7/12/W7,0) -> 1.8265039 | Y7: =IFERROR(K7*Assumptions!$C$18/12/W7,0) -> 1.4612031 | Z7: =H7*J7+H7*(Assumptions!$C$16-I7) -> 140650 | AA7: =W7*Assumptions!$C$17 -> 23268.497 | AB7: =K7*INDEX(Assumptions!$H$37:$H$38,MATCH(Q7,Assumptions!$B$37:$B$38,0))+Assumptions!$C$41+IF(N7="Y",Assumptions!$C$42,Assumptions!$C$43) -> 28550 | AC7: =K7*INDEX(Assumptions!$C$37:$C$38,MATCH(Q7,Assumptions!$B$37:$B$38,0)) -> 17000 | AD7: =K7-AB7-W7*12 -> 9913.0054 | AE7: =AD7-AC7 -> -7086.9946 | AF7: =IFERROR(K7/H7,0) -> 0.17525773 | AG7: =IFERROR((K7-AB7-AC7)/H7,0) -> 0.081340206 | AI7: 18 | AJ7: Heated pool + spa, 4BR. 33714 straddles City of St. Pete (30-day rule) and unincorporated Lealman (legal w/ Certificate of Use): CONFIRM jurisdiction first. 1936 build: insurance. Low current tax will reset. | AK7: Zillow
A8: 3 | B8: 341 Wertz Dr | C8: Largo 33771 | D8: Pinellas | E8: SFR | F8: 3/2 / 1,038 / 1961 | G8: 359000 | H8: 340000 | I8: 0 | J8: =Assumptions!$C$15 -> 0.25 | K8: 51000 | L8: "over $51,000 in revenue in the 12 months leading up to the hurricanes" (pre-Oct 2024) | M8: Unknown | N8: N | O8: 0 | Q8: STR | R8: =H8*(1-J8) -> 255000 | S8: =IF((1-J8)>0.75,Assumptions!$C$11,IF((1-J8)>0.7,Assumptions!$C$12,Assumptions!$C$13)) -> 0.0725 | T8: =PMT(S8/12,Assumptions!$C$14,-R8) -> 1739.5495 | U8: =H8*INDEX(Assumptions!$C$28:$C$34,MATCH(D8,Assumptions!$B$28:$B$34,0))/12 -> 453.33333 | V8: =IF(ISNUMBER(P8),P8,INDEX(Assumptions!$D$28:$D$34,MATCH(D8,Assumptions!$B$28:$B$34,0))+INDEX(Assumptions!$C$22:$C$25,MATCH(M8,Assumptions!$B$22:$B$25,0)))/12 -> 750 | W8: =T8+U8+V8+O8 -> 2942.8828 | X8: =IFERROR(K8/12/W8,0) -> 1.4441621 | Y8: =IFERROR(K8*Assumptions!$C$18/12/W8,0) -> 1.1553297 | Z8: =H8*J8+H8*(Assumptions!$C$16-I8) -> 98600 | AA8: =W8*Assumptions!$C$17 -> 17657.297 | AB8: =K8*INDEX(Assumptions!$H$37:$H$38,MATCH(Q8,Assumptions!$B$37:$B$38,0))+Assumptions!$C$41+IF(N8="Y",Assumptions!$C$42,Assumptions!$C$43) -> 18930 | AC8: =K8*INDEX(Assumptions!$C$37:$C$38,MATCH(Q8,Assumptions!$B$37:$B$38,0)) -> 10200 | AD8: =K8-AB8-W8*12 -> -3244.5942 | AE8: =AD8-AC8 -> -13444.594 | AF8: =IFERROR(K8/H8,0) -> 0.15 | AG8: =IFERROR((K8-AB8-AC8)/H8,0) -> 0.064323529 | AI8: 257 | AJ8: STR paused since 2024 storms (new roof Apr 2025): lender may not accept 2-yr-old history. Largo: STR legal. 257 DOM: negotiable. | AK8: Zillow
A9: 4 | B9: 15305 1st St E #305 (condo) | C9: Madeira Beach 33708 | D9: Pinellas | E9: Condo | F9: 3/3 / 1,440 / 2020 | G9: 659900 | H9: 640000 | I9: 0 | J9: =Assumptions!$C$15 -> 0.25 | K9: 75000 | L9: "$75K in gross rental revenue in 2025 and already over $60K generated year-to-date in 2026" | M9: AE | N9: N | O9: 961 | Q9: STR | R9: =H9*(1-J9) -> 480000 | S9: =IF((1-J9)>0.75,Assumptions!$C$11,IF((1-J9)>0.7,Assumptions!$C$12,Assumptions!$C$13)) -> 0.0725 | T9: =PMT(S9/12,Assumptions!$C$14,-R9) -> 3274.4461 | U9: =H9*INDEX(Assumptions!$C$28:$C$34,MATCH(D9,Assumptions!$B$28:$B$34,0))/12 -> 853.33333 | V9: =IF(ISNUMBER(P9),P9,INDEX(Assumptions!$D$28:$D$34,MATCH(D9,Assumptions!$B$28:$B$34,0))+INDEX(Assumptions!$C$22:$C$25,MATCH(M9,Assumptions!$B$22:$B$25,0)))/12 -> 958.33333 | W9: =T9+U9+V9+O9 -> 6047.1128 | X9: =IFERROR(K9/12/W9,0) -> 1.0335511 | Y9: =IFERROR(K9*Assumptions!$C$18/12/W9,0) -> 0.82684087 | Z9: =H9*J9+H9*(Assumptions!$C$16-I9) -> 185600 | AA9: =W9*Assumptions!$C$17 -> 36282.677 | AB9: =K9*INDEX(Assumptions!$H$37:$H$38,MATCH(Q9,Assumptions!$B$37:$B$38,0))+Assumptions!$C$41+IF(N9="Y",Assumptions!$C$42,Assumptions!$C$43) -> 24450 | AC9: =K9*INDEX(Assumptions!$C$37:$C$38,MATCH(Q9,Assumptions!$B$37:$B$38,0)) -> 15000 | AD9: =K9-AB9-W9*12 -> -22015.354 | AE9: =AD9-AC9 -> -37015.354 | AF9: =IFERROR(K9/H9,0) -> 0.1171875 | AG9: =IFERROR((K9-AB9-AC9)/H9,0) -> 0.055546875 | AI9: 36 | AJ9: Best-documented Pinellas income. 2020 building (lower SB 4-D assessment risk). Confirm Madeira zoning allows <30-day and condo DSCR warrantability. | AK9: Zillow
A10: 5 | B10: 13235 Gulf Blvd #502 (Madeira Bay Resort) | C10: Madeira Beach 33708 | D10: Pinellas | E10: Condo | F10: 2/2 / 734 / 2006 | G10: 575000 | H10: 560000 | I10: 0 | J10: =Assumptions!$C$15 -> 0.25 | K10: 59000 | L10: "Last year's gross rents were $59K" | M10: AE | N10: N | O10: 630 | Q10: STR | R10: =H10*(1-J10) -> 420000 | S10: =IF((1-J10)>0.75,Assumptions!$C$11,IF((1-J10)>0.7,Assumptions!$C$12,Assumptions!$C$13)) -> 0.0725 | T10: =PMT(S10/12,Assumptions!$C$14,-R10) -> 2865.1404 | U10: =H10*INDEX(Assumptions!$C$28:$C$34,MATCH(D10,Assumptions!$B$28:$B$34,0))/12 -> 746.66667 | V10: =IF(ISNUMBER(P10),P10,INDEX(Assumptions!$D$28:$D$34,MATCH(D10,Assumptions!$B$28:$B$34,0))+INDEX(Assumptions!$C$22:$C$25,MATCH(M10,Assumptions!$B$22:$B$25,0)))/12 -> 958.33333 | W10: =T10+U10+V10+O10 -> 5200.1404 | X10: =IFERROR(K10/12/W10,0) -> 0.9454873 | Y10: =IFERROR(K10*Assumptions!$C$18/12/W10,0) -> 0.75638984 | Z10: =H10*J10+H10*(Assumptions!$C$16-I10) -> 162400 | AA10: =W10*Assumptions!$C$17 -> 31200.842 | AB10: =K10*INDEX(Assumptions!$H$37:$H$38,MATCH(Q10,Assumptions!$B$37:$B$38,0))+Assumptions!$C$41+IF(N10="Y",Assumptions!$C$42,Assumptions!$C$43) -> 20770 | AC10: =K10*INDEX(Assumptions!$C$37:$C$38,MATCH(Q10,Assumptions!$B$37:$B$38,0)) -> 11800 | AD10: =K10-AB10-W10*12 -> -24171.685 | AE10: =AD10-AC10 -> -35971.685 | AF10: =IFERROR(K10/H10,0) -> 0.10535714 | AG10: =IFERROR((K10-AB10-AC10)/H10,0) -> 0.047196429 | AI10: 18 | AJ10: Resort with 24/7 guest services = condotel review: most DSCR lenders decline or cap at 60-70% LTV. | AK10: Zillow
A11: 6 | B11: 17960 Gulf Blvd #121 (townhome) | C11: Redington Shores 33708 | D11: Pinellas | E11: Townhome | F11: 2/2.5 / 1,237 / 1989 | G11: 614999 | H11: 590000 | I11: 0 | J11: =Assumptions!$C$15 -> 0.25 | K11: 47890 | L11: "$47,890 IN REVENUE ALREADY BOOKED FOR 2027"; $20k+ Feb-May 2026; 30-day minimum | M11: VE | N11: N | O11: 835 | Q11: Seasonal | R11: =H11*(1-J11) -> 442500 | S11: =IF((1-J11)>0.75,Assumptions!$C$11,IF((1-J11)>0.7,Assumptions!$C$12,Assumptions!$C$13)) -> 0.0725 | T11: =PMT(S11/12,Assumptions!$C$14,-R11) -> 3018.63 | U11: =H11*INDEX(Assumptions!$C$28:$C$34,MATCH(D11,Assumptions!$B$28:$B$34,0))/12 -> 786.66667 | V11: =IF(ISNUMBER(P11),P11,INDEX(Assumptions!$D$28:$D$34,MATCH(D11,Assumptions!$B$28:$B$34,0))+INDEX(Assumptions!$C$22:$C$25,MATCH(M11,Assumptions!$B$22:$B$25,0)))/12 -> 1333.3333 | W11: =T11+U11+V11+O11 -> 5973.63 | X11: =IFERROR(K11/12/W11,0) -> 0.66807507 | Y11: =IFERROR(K11*Assumptions!$C$18/12/W11,0) -> 0.53446006 | Z11: =H11*J11+H11*(Assumptions!$C$16-I11) -> 171100 | AA11: =W11*Assumptions!$C$17 -> 35841.78 | AB11: =K11*INDEX(Assumptions!$H$37:$H$38,MATCH(Q11,Assumptions!$B$37:$B$38,0))+Assumptions!$C$41+IF(N11="Y",Assumptions!$C$42,Assumptions!$C$43) -> 13425.7 | AC11: =K11*INDEX(Assumptions!$C$37:$C$38,MATCH(Q11,Assumptions!$B$37:$B$38,0)) -> 5746.8 | AD11: =K11-AB11-W11*12 -> -37219.26 | AE11: =AD11-AC11 -> -42966.06 | AF11: =IFERROR(K11/H11,0) -> 0.081169492 | AG11: =IFERROR((K11-AB11-AC11)/H11,0) -> 0.048673729 | AI11: 152 | AJ11: Gulf-front, 30-day minimum (seasonal model). VE flood + $835 HOA kill DSCR. | AK11: Zillow
A12: 7 | B12: 1904 Gulf Blvd #D (condo) | C12: Indian Rocks Beach 33785 | D12: Pinellas | E12: Condo | F12: 2/2 / 1,135 / 1997 | G12: 699000 | H12: 699000 | I12: 0 | J12: =Assumptions!$C$15 -> 0.25 | K12: 50000 | L12: "averaged approximately $50,000 annually in gross rental revenue since 2023"; weekly rentals | M12: AE | N12: N | O12: 1325 | Q12: STR | R12: =H12*(1-J12) -> 524250 | S12: =IF((1-J12)>0.75,Assumptions!$C$11,IF((1-J12)>0.7,Assumptions!$C$12,Assumptions!$C$13)) -> 0.0725 | T12: =PMT(S12/12,Assumptions!$C$14,-R12) -> 3576.3091 | U12: =H12*INDEX(Assumptions!$C$28:$C$34,MATCH(D12,Assumptions!$B$28:$B$34,0))/12 -> 932 | V12: =IF(ISNUMBER(P12),P12,INDEX(Assumptions!$D$28:$D$34,MATCH(D12,Assumptions!$B$28:$B$34,0))+INDEX(Assumptions!$C$22:$C$25,MATCH(M12,Assumptions!$B$22:$B$25,0)))/12 -> 958.33333 | W12: =T12+U12+V12+O12 -> 6791.6425 | X12: =IFERROR(K12/12/W12,0) -> 0.61349912 | Y12: =IFERROR(K12*Assumptions!$C$18/12/W12,0) -> 0.49079929 | Z12: =H12*J12+H12*(Assumptions!$C$16-I12) -> 202710 | AA12: =W12*Assumptions!$C$17 -> 40749.855 | AB12: =K12*INDEX(Assumptions!$H$37:$H$38,MATCH(Q12,Assumptions!$B$37:$B$38,0))+Assumptions!$C$41+IF(N12="Y",Assumptions!$C$42,Assumptions!$C$43) -> 18700 | AC12: =K12*INDEX(Assumptions!$C$37:$C$38,MATCH(Q12,Assumptions!$B$37:$B$38,0)) -> 10000 | AD12: =K12-AB12-W12*12 -> -50199.71 | AE12: =AD12-AC12 -> -60199.71 | AF12: =IFERROR(K12/H12,0) -> 0.071530758 | AG12: =IFERROR((K12-AB12-AC12)/H12,0) -> 0.030472103 | AI12: 7 | AJ12: Shown as a reject example: $1,325/mo HOA. | AK12: Zillow
A15: Pinellas operating STRs with history on request (legal zones): request T12 payouts + Certificate of Use
B16: Address | C16: City / ZIP | G16: Price | L16: Evidence (no $ in listing) | AJ16: Ask agent for | AK16: Link
B17: 9542 Oakhurst Rd | C17: Seminole 33776 (unincorporated) | G17: 699000 | L17: 4/3 heated pool; "no length and duration limits"; 3 yrs Airbnb/VRBO history on request; STR insurance quote $4,353 | AJ17: T12 payout reports + TDT filings | AK17: Zillow
B18: 6400 Pelican Dr S | C18: St Petersburg 33707 (outside city limits) | G18: 629000 | L18: 3/2 heated pool; "STR history and revenue information available upon request"; 122 DOM | AJ18: T12 payout reports + TDT filings | AK18: Zillow
B19: 7957 Cottonwoode Dr | C19: Largo 33773 | G19: 575000 | L19: 3/2 pool; "documented Airbnb performance and booking history available" | AJ19: T12 payout reports + TDT filings | AK19: Zillow
B20: 8253 137th Ln | C20: Seminole 33776 (unincorporated) | G20: 599000 | L20: 3/2 pool; Airbnb past year with strong performance | AJ20: T12 payout reports + TDT filings | AK20: Zillow
B21: 4986 Woodland Dr | C21: St Petersburg 33708 | G21: 550000 | L21: 2/2 pool; "ACTIVE Short-Term RENTAL"; "NO RENTAL RESTRICTIONS" (verify jurisdiction) | AJ21: T12 payout reports + TDT filings | AK21: Zillow
B22: 9370 83rd St | C22: Seminole 33777 | G22: 425000 | L22: 3/2 pool; operating furnished Airbnb; furniture extra | AJ22: T12 payout reports + TDT filings | AK22: Zillow
B23: 166 Pinellas Way N | C23: St Petersburg 33710 | G23: 550000 | L23: Pool + spa; history on request. Likely City of St. Pete (30-day rule): verify before pursuing | AJ23: T12 payout reports + TDT filings | AK23: Zillow
B24: 14626 Wildwood Dr | C24: Largo 33774 (unincorporated) | G24: 524900 | L24: 4/2 pool; "Currently operating as an AIRBNB" | AJ24: T12 payout reports + TDT filings | AK24: Zillow
B25: 1600 Loretta Ave NW | C25: Largo 33770 | G25: 490000 | L25: 3/2 heated pool + spa, furnished; "registered with the city of Largo as a short term rental" | AJ25: T12 payout reports + TDT filings | AK25: Zillow
B26: 863 Bay Breeze Ter | C26: Largo 33770 | G26: 585000 | L26: 3/2 pool; "INCOME-PRODUCING VRBO"; "NO RENTAL RESTRICTIONS" | AJ26: T12 payout reports + TDT filings | AK26: Zillow
B27: 8628 Magnolia Dr | C27: Seminole 33777 | G27: 520000 | L27: 4/2 pool; "currently operating as a short-term rental"; verify license transferability | AJ27: T12 payout reports + TDT filings | AK27: Zillow
B28: 839 3rd St N | C28: Safety Harbor 34695 | G28: 499900 | L28: 8-yr vacation rental, hundreds of 5-star reviews; "detailed financials are available on request"; 2/2 small | AJ28: T12 payout reports + TDT filings | AK28: Zillow
... B30: 414 Tampa Rd (Ozona) | C30: Palm Harbor 34683 | G30: 349900 | L30: 2020-2026 rental history + 2027 bookings on request; listing gives $46k projection (not actual) | AJ30: T12 payout reports + TDT filings | AK30: Zillow

Sheet Other SWFL Listings
A1: Lee / Charlotte / Collier: Listings with Stated Rental Income
A2: Active as of 2026-10-18. 3 Zillow sweeps (~257 unique listings) before the Apify usage cap; documented income is thin outside Cape Coral. See 'Other SWFL Markets' for the market ranking.
A3: Edit blue cells (Offer Price, Seller Credit %, Down Pmt %, Income, Flood Zone, Ins Override) to rerun. Ins Override (blank = county base + flood) is for condos with master wind/flood policies. Qualify on DSCR (lender haircut) >= 1.00; >= 1.15 preferred. Income is seller-stated until verified with platform payout reports.
A5: Rank | B5: Address | C5: City / ZIP | D5: County | E5: Type | F5: Bd/Ba/SqFt/Yr | G5: List Price | H5: Offer Price | I5: Seller Credit % | J5: Down Pmt % | K5: Stated Gross Income ($/yr) | L5: Income Basis (seller-stated) | M5: Flood Zone | N5: Pool | O5: HOA ($/mo) | P5: Ins Override ($/yr) | Q5: Profile | R5: Loan Amount | S5: Rate | T5: P&I ($/mo) | U5: Taxes ($/mo) | V5: Ins + Flood ($/mo) | W5: PITIA ($/mo) | X5: DSCR (gross) | Y5: DSCR (lender haircut) | Z5: Cash to Close | AA5: Reserves (6 mo) | AB5: Opex excl. Mgmt ($/yr) | AC5: Mgmt ($/yr) | AD5: Cash Flow Self-Managed ($/yr) | AE5: Cash Flow Full PM ($/yr) | AF5: Gross Yield | AG5: Cap Rate (w/ PM) | AH5: Last Sale | AI5: DOM | AJ5: Key Risks / Notes | AK5: Listing Link
A6: 1 | B6: 326 NW 21st Ter | C6: Cape Coral 33993 | D6: Lee | E6: SFR | F6: 3/2 / 1,734 / 2023 | G6: 475000 | H6: 460000 | I6: 0 | J6: =Assumptions!$C$15 -> 0.25 | K6: 60000 | L6: "generated over $60,000 in annual rental revenue" | M6: Unknown | N6: Y | O6: 0 | Q6: STR | R6: =H6*(1-J6) -> 345000 | S6: =IF((1-J6)>0.75,Assumptions!$C$11,IF((1-J6)>0.7,Assumptions!$C$12,Assumptions!$C$13)) -> 0.0725 | T6: =PMT(S6/12,Assumptions!$C$14,-R6) -> 2353.5082 | U6: =H6*INDEX(Assumptions!$C$28:$C$34,MATCH(D6,Assumptions!$B$28:$B$34,0))/12 -> 651.66667 | V6: =IF(ISNUMBER(P6),P6,INDEX(Assumptions!$D$28:$D$34,MATCH(D6,Assumptions!$B$28:$B$34,0))+INDEX(Assumptions!$C$22:$C$25,MATCH(M6,Assumptions!$B$22:$B$25,0)))/12 -> 750 | W6: =T6+U6+V6+O6 -> 3755.1748 | X6: =IFERROR(K6/12/W6,0) -> 1.3314959 | Y6: =IFERROR(K6*Assumptions!$C$18/12/W6,0) -> 1.0651967 | Z6: =H6*J6+H6*(Assumptions!$C$16-I6) -> 133400 | AA6: =W6*Assumptions!$C$17 -> 22531.049 | AB6: =K6*INDEX(Assumptions!$H$37:$H$38,MATCH(Q6,Assumptions!$B$37:$B$38,0))+Assumptions!$C$41+IF(N6="Y",Assumptions!$C$42,Assumptions!$C$43) -> 22800 | AC6: =K6*INDEX(Assumptions!$C$37:$C$38,MATCH(Q6,Assumptions!$B$37:$B$38,0)) -> 12000 | AD6: =K6-AB6-W6*12 -> -7862.098 | AE6: =AD6-AC6 -> -19862.098 | AF6: =IFERROR(K6/H6,0) -> 0.13043478 | AG6: =IFERROR((K6-AB6-AC6)/H6,0) -> 0.054782609 | AI6: 14 | AJ6: Only SWFL listing clearing DSCR after haircut. NW Cape = inland, ~30+ min to beach. Check North Cape utility assessment (~$32k/lot, ~$3.4k/yr). Cape Coral STR registration $350/yr. | AK6: Zillow
A7: 2 | B7: 370 Townhouse Ln #65 (North Captiva) | C7: Captiva 33924 | D7: Lee | E7: Townhome | F7: 3/2 / 979 / 1985 | G7: 589900 | H7: 589900 | I7: 0 | J7: =Assumptions!$C$15 -> 0.25 | K7: 60000 | L7: "established in a successful vacation rental program with $60,000+ in annual rental income" | M7: AE | N7: N | O7: 583 | Q7: STR | R7: =H7*(1-J7) -> 442425 | S7: =IF((1-J7)>0.75,Assumptions!$C$11,IF((1-J7)>0.7,Assumptions!$C$12,Assumptions!$C$13)) -> 0.0725 | T7: =PMT(S7/12,Assumptions!$C$14,-R7) -> 3018.1184 | U7: =H7*INDEX(Assumptions!$C$28:$C$34,MATCH(D7,Assumptions!$B$28:$B$34,0))/12 -> 835.69167 | V7: =IF(ISNUMBER(P7),P7,INDEX(Assumptions!$D$28:$D$34,MATCH(D7,Assumptions!$B$28:$B$34,0))+INDEX(Assumptions!$C$22:$C$25,MATCH(M7,Assumptions!$B$22:$B$25,0)))/12 -> 958.33333 | W7: =T7+U7+V7+O7 -> 5395.1434 | X7: =IFERROR(K7/12/W7,0) -> 0.92675942 | Y7: =IFERROR(K7*Assumptions!$C$18/12/W7,0) -> 0.74140754 | Z7: =H7*J7+H7*(Assumptions!$C$16-I7) -> 171071 | AA7: =W7*Assumptions!$C$17 -> 32370.86 | AB7: =K7*INDEX(Assumptions!$H$37:$H$38,MATCH(Q7,Assumptions!$B$37:$B$38,0))+Assumptions!$C$41+IF(N7="Y",Assumptions!$C$42,Assumptions!$C$43) -> 21000 | AC7: =K7*INDEX(Assumptions!$C$37:$C$38,MATCH(Q7,Assumptions!$B$37:$B$38,0)) -> 12000 | AD7: =K7-AB7-W7*12 -> -25741.721 | AE7: =AD7-AC7 -> -37741.721 | AF7: =IFERROR(K7/H7,0) -> 0.10171215 | AG7: =IFERROR((K7-AB7-AC7)/H7,0) -> 0.04577047 | AI7: 23 | AJ7: Boat-access-only island: financing/insurance hard. Rental program = condotel-style review. | AK7: Zillow
A8: 3 | B8: 10345 Longshore Rd #31 | C8: Placida 33946 | D8: Charlotte | E8: Townhome | F8: 3/3 / 2,416 / 2020 | G8: 530000 | H8: 530000 | I8: 0 | J8: =Assumptions!$C$15 -> 0.25 | K8: 29250 | L8: "annual short term rental with same family 12/1-4/15 generating rental income of $29,250" | M8: Unknown | N8: N | O8: 520 | Q8: Seasonal | R8: =H8*(1-J8) -> 397500 | S8: =IF((1-J8)>0.75,Assumptions!$C$11,IF((1-J8)>0.7,Assumptions!$C$12,Assumptions!$C$13)) -> 0.0725 | T8: =PMT(S8/12,Assumptions!$C$14,-R8) -> 2711.6507 | U8: =H8*INDEX(Assumptions!$C$28:$C$34,MATCH(D8,Assumptions!$B$28:$B$34,0))/12 -> 728.75 | V8: =IF(ISNUMBER(P8),P8,INDEX(Assumptions!$D$28:$D$34,MATCH(D8,Assumptions!$B$28:$B$34,0))+INDEX(Assumptions!$C$22:$C$25,MATCH(M8,Assumptions!$B$22:$B$25,0)))/12 -> 750 | W8: =T8+U8+V8+O8 -> 4710.4007 | X8: =IFERROR(K8/12/W8,0) -> 0.5174719 | Y8: =IFERROR(K8*Assumptions!$C$18/12/W8,0) -> 0.41397752 | Z8: =H8*J8+H8*(Assumptions!$C$16-I8) -> 153700 | AA8: =W8*Assumptions!$C$17 -> 28262.404 | AB8: =K8*INDEX(Assumptions!$H$37:$H$38,MATCH(Q8,Assumptions!$B$37:$B$38,0))+Assumptions!$C$41+IF(N8="Y",Assumptions!$C$42,Assumptions!$C$43) -> 11002.5 | AC8: =K8*INDEX(Assumptions!$C$37:$C$38,MATCH(Q8,Assumptions!$B$37:$B$38,0)) -> 3510 | AD8: =K8-AB8-W8*12 -> -38277.309 | AE8: =AD8-AC8 -> -41787.309 | AF8: =IFERROR(K8/H8,0) -> 0.055188679 | AG8: =IFERROR((K8-AB8-AC8)/H8,0) -> 0.027806604 | AI8: 126 | AJ8: One seasonal tenant only; rest of year unbooked. Shown as a weak example. | AK8: Zillow
A11: Operating STRs with history on request: Cape Coral Gulf-access + Charlotte Harbor (request T12)
B12: Address | C12: City / ZIP | G12: Price | L12: Evidence (no $ in listing) | AJ12: Ask agent for | AK12: Link
B13: 930 SW 37th Ter (PropertyRadar find) | C13: Cape Coral 33914 | G13: 400000 | L13: 2024 remarks: 'successful vacation rental'; on FL DBPR vacation-rental license list; 3/2 heated pool + spa, 2008, zone X, ~400 DOM. Not Gulf access. Needs ~$49k gross for DSCR 1.00 at list, 25% down. | AJ13: T12 payouts + license status; why it didn't sell at $400k | AK13: Redfin
B14: 2712 SW 4th Pl | C14: Cape Coral 33914 | G14: 599000 | L14: Pool, 2020 build; Feb 1-Mar 31 2027 booking (59 nights) + Nov 2026 booking transfer | AJ14: T12 payout reports + TDT filings | AK14: Zillow
B15: 1433 SE 28th Ter | C15: Cape Coral 33904 | G15: 542500 | L15: Airbnb Guest Favorite 4.93 stars; Gulf access; solar-heated pool | AJ15: T12 payout reports + TDT filings | AK15: Zillow
B16: 4928 SW 1st Ct | C16: Cape Coral 33914 | G16: 599900 | L16: "proven income stream through Airbnb and VRBO"; direct Gulf access; 2BR; 424 DOM | AJ16: T12 payout reports + TDT filings | AK16: Zillow
B17: 2917 SW Santa Barbara Pl (duplex) | C17: Cape Coral 33914 | G17: 659900 | L17: 2024 duplex, 2x 3/2+den, "PROVEN AIRBNB RENTAL HISTORY", Guest Favorite; motivated seller | AJ17: T12 payout reports + TDT filings | AK17: Zillow
B18: 3106 SE 8th Pl | C18: Cape Coral 33904 | G18: 390000 | L18: Pool, furnished, future rentals in place | AJ18: T12 payout reports + TDT filings | AK18: Zillow
B19: 1768 Whiskey Creek Dr | C19: Fort Myers 33919 | G19: 599000 | L19: "rental income information available upon request"; seller offering rate buydown | AJ19: T12 payout reports + TDT filings | AK19: Zillow
B20: 951 Lassino Ct | C20: Punta Gorda 33950 | G20: 659000 | L20: Punta Gorda Isles pool home; ~2 yrs history, reviews and accounts may transfer; check deed restrictions | AJ20: T12 payout reports + TDT filings | AK20: Zillow
B21: 9277 Saint Catherine Ave | C21: Englewood 34224 (Charlotte) | G21: 449900 | L21: Pool, furnished; spring reservations may transfer; ~6 mi to beach | AJ21: T12 payout reports + TDT filings | AK21: Zillow
B22: 59 Wickliffe Dr | C22: Naples 34110 | G22: 665000 | L22: "$29k in future bookings on Airbnb" (forward only); unincorporated Collier | AJ22: T12 payout reports + TDT filings | AK22: Zillow

Sheet Monroe (Keys)
A1: Monroe County (Florida Keys): Licensed Rentals with Stated Income
A2: As of 2026-10-18. Web-search sweep only (Zillow scraper capped): ~85 searches across Zillow/Redfin/brokerage IDX snippets. Under $950k, documented-income inventory is almost entirely condos in a few STR-legal complexes.
A3: Edit blue cells (Offer Price, Seller Credit %, Down Pmt %, Income, Flood Zone, Ins Override) to rerun. Ins Override (blank = county base + flood) is for condos with master wind/flood policies. Qualify on DSCR (lender haircut) >= 1.00; >= 1.15 preferred. Income is seller-stated until verified with platform payout reports.
A5: Rank | B5: Address | C5: City / ZIP | D5: County | E5: Type | F5: Bd/Ba/SqFt/Yr | G5: List Price | H5: Offer Price | I5: Seller Credit % | J5: Down Pmt % | K5: Stated Gross Income ($/yr) | L5: Income Basis (seller-stated) | M5: Flood Zone | N5: Pool | O5: HOA ($/mo) | P5: Ins Override ($/yr) | Q5: Profile | R5: Loan Amount | S5: Rate | T5: P&I ($/mo) | U5: Taxes ($/mo) | V5: Ins + Flood ($/mo) | W5: PITIA ($/mo) | X5: DSCR (gross) | Y5: DSCR (lender haircut) | Z5: Cash to Close | AA5: Reserves (6 mo) | AB5: Opex excl. Mgmt ($/yr) | AC5: Mgmt ($/yr) | AD5: Cash Flow Self-Managed ($/yr) | AE5: Cash Flow Full PM ($/yr) | AF5: Gross Yield | AG5: Cap Rate (w/ PM) | AH5: Last Sale | AI5: DOM | AJ5: Key Risks / Notes | AK5: Listing Link
A6: 1 | B6: 1500 Ocean Bay Dr #E5 (Kawama Yacht Club) | C6: Key Largo 33037 | D6: Monroe | E6: Condo | F6: 2/2 / 766 / n/s | G6: 795000 | H6: 760000 | I6: 0 | J6: =Assumptions!$C$15 -> 0.25 | K6: 98980 | L6: "currently generating rental income of $98,980 yearly"; "can be rented daily-nightly" | M6: AE | N6: N | O6: 1200 | P6: 3000 | Q6: STR | R6: =H6*(1-J6) -> 570000 | S6: =IF((1-J6)>0.75,Assumptions!$C$11,IF((1-J6)>0.7,Assumptions!$C$12,Assumptions!$C$13)) -> 0.0725 | T6: =PMT(S6/12,Assumptions!$C$14,-R6) -> 3888.4048 | U6: =H6*INDEX(Assumptions!$C$28:$C$34,MATCH(D6,Assumptions!$B$28:$B$34,0))/12 -> 601.66667 | V6: =IF(ISNUMBER(P6),P6,INDEX(Assumptions!$D$28:$D$34,MATCH(D6,Assumptions!$B$28:$B$34,0))+INDEX(Assumptions!$C$22:$C$25,MATCH(M6,Assumptions!$B$22:$B$25,0)))/12 -> 250 | W6: =T6+U6+V6+O6 -> 5940.0715 | X6: =IFERROR(K6/12/W6,0) -> 1.3885916 | Y6: =IFERROR(K6*Assumptions!$C$18/12/W6,0) -> 1.1108733 | Z6: =H6*J6+H6*(Assumptions!$C$16-I6) -> 220400 | AA6: =W6*Assumptions!$C$17 -> 35640.429 | AB6: =K6*INDEX(Assumptions!$H$37:$H$38,MATCH(Q6,Assumptions!$B$37:$B$38,0))+Assumptions!$C$41+IF(N6="Y",Assumptions!$C$42,Assumptions!$C$43) -> 29965.4 | AC6: =K6*INDEX(Assumptions!$C$37:$C$38,MATCH(Q6,Assumptions!$B$37:$B$38,0)) -> 19796 | AD6: =K6-AB6-W6*12 -> -2266.2576 | AE6: =AD6-AC6 -> -22062.258 | AF6: =IFERROR(K6/H6,0) -> 0.13023684 | AG6: =IFERROR((K6-AB6-AC6)/H6,0) -> 0.064761316 | AJ6: Best-documented Keys income in range (12.5% gross yield). Stretch price: 25% down = ~$220k cash. Kawama is one of few Key Largo complexes allowing nightly stays. Condo questionnaire + non-warrantable review. | AK6: Zillow
A7: 2 | B7: 500 Burton Dr #2212 (Ocean Pointe) | C7: Tavernier 33070 | D7: Monroe | E7: Condo | F7: 2/2 / ~826 / 1991 | G7: 649900 | H7: 625000 | I7: 0 | J7: =Assumptions!$C$15 -> 0.25 | K7: 100000 | L7: "an impressive average of $100,000 per year in rental income"; "$48,000 net income from Jan-April 2026" | M7: AE | N7: N | O7: 1448 | P7: 3000 | Q7: STR | R7: =H7*(1-J7) -> 468750 | S7: =IF((1-J7)>0.75,Assumptions!$C$11,IF((1-J7)>0.7,Assumptions!$C$12,Assumptions!$C$13)) -> 0.0725 | T7: =PMT(S7/12,Assumptions!$C$14,-R7) -> 3197.7013 | U7: =H7*INDEX(Assumptions!$C$28:$C$34,MATCH(D7,Assumptions!$B$28:$B$34,0))/12 -> 494.79167 | V7: =IF(ISNUMBER(P7),P7,INDEX(Assumptions!$D$28:$D$34,MATCH(D7,Assumptions!$B$28:$B$34,0))+INDEX(Assumptions!$C$22:$C$25,MATCH(M7,Assumptions!$B$22:$B$25,0)))/12 -> 250 | W7: =T7+U7+V7+O7 -> 5390.493 | X7: =IFERROR(K7/12/W7,0) -> 1.5459316 | Y7: =IFERROR(K7*Assumptions!$C$18/12/W7,0) -> 1.2367453 | Z7: =H7*J7+H7*(Assumptions!$C$16-I7) -> 181250 | AA7: =W7*Assumptions!$C$17 -> 32342.958 | AB7: =K7*INDEX(Assumptions!$H$37:$H$38,MATCH(Q7,Assumptions!$B$37:$B$38,0))+Assumptions!$C$41+IF(N7="Y",Assumptions!$C$42,Assumptions!$C$43) -> 30200 | AC7: =K7*INDEX(Assumptions!$C$37:$C$38,MATCH(Q7,Assumptions!$B$37:$B$38,0)) -> 20000 | AD7: =K7-AB7-W7*12 -> 5114.0842 | AE7: =AD7-AC7 -> -14885.916 | AF7: =IFERROR(K7/H7,0) -> 0.16 | AG7: =IFERROR((K7-AB7-AC7)/H7,0) -> 0.07968 | AH7: $560,000 (Nov 2024) | AJ7: Ocean Pointe allows very short-term rentals (rare in the Upper Keys). $46k price drop. Bought for $560k in Nov 2024: appraisal risk at $650k. HOA ~$1,448/mo (quarterly $4,344). | AK7: Zillow
A8: 3 | B8: 500 Burton Dr #3308 (Ocean Pointe) | C8: Tavernier 33070 | D8: Monroe | E8: Condo | F8: 2/2 / 841 / 1991 | G8: 699000 | H8: 670000 | I8: 0 | J8: =Assumptions!$C$15 -> 0.25 | K8: 57988 | L8: "grossed $57,987.66 in 2025, with the owners using it all month in February" | M8: AE | N8: N | O8: 1448 | P8: 3000 | Q8: STR | R8: =H8*(1-J8) -> 502500 | S8: =IF((1-J8)>0.75,Assumptions!$C$11,IF((1-J8)>0.7,Assumptions!$C$12,Assumptions!$C$13)) -> 0.0725 | T8: =PMT(S8/12,Assumptions!$C$14,-R8) -> 3427.9358 | U8: =H8*INDEX(Assumptions!$C$28:$C$34,MATCH(D8,Assumptions!$B$28:$B$34,0))/12 -> 530.41667 | V8: =IF(ISNUMBER(P8),P8,INDEX(Assumptions!$D$28:$D$34,MATCH(D8,Assumptions!$B$28:$B$34,0))+INDEX(Assumptions!$C$22:$C$25,MATCH(M8,Assumptions!$B$22:$B$25,0)))/12 -> 250 | W8: =T8+U8+V8+O8 -> 5656.3525 | X8: =IFERROR(K8/12/W8,0) -> 0.8543197 | Y8: =IFERROR(K8*Assumptions!$C$18/12/W8,0) -> 0.68345576 | Z8: =H8*J8+H8*(Assumptions!$C$16-I8) -> 194300 | AA8: =W8*Assumptions!$C$17 -> 33938.115 | AB8: =K8*INDEX(Assumptions!$H$37:$H$38,MATCH(Q8,Assumptions!$B$37:$B$38,0))+Assumptions!$C$41+IF(N8="Y",Assumptions!$C$42,Assumptions!$C$43) -> 20537.24 | AC8: =K8*INDEX(Assumptions!$C$37:$C$38,MATCH(Q8,Assumptions!$B$37:$B$38,0)) -> 11597.6 | AD8: =K8-AB8-W8*12 -> -30425.47 | AE8: =AD8-AC8 -> -42023.07 | AF8: =IFERROR(K8/H8,0) -> 0.086549254 | AG8: =IFERROR((K8-AB8-AC8)/H8,0) -> 0.038586806 | AJ8: Owner used peak month (Feb): true rental capacity higher. Possibly stale listing: confirm active. | AK8: Zillow
A9: 4 | B9: 500 Burton Dr #4211 (Ocean Pointe, oceanfront) | C9: Tavernier 33070 | D9: Monroe | E9: Condo | F9: 2/2 / n/s / 1991 | G9: 679000 | H9: 650000 | I9: 0 | J9: =Assumptions!$C$15 -> 0.25 | K9: 49000 | L9: "Grossed $29,319.00 in the first 6 months of 2026" | M9: AE | N9: N | O9: 1448 | P9: 3000 | Q9: STR | R9: =H9*(1-J9) -> 487500 | S9: =IF((1-J9)>0.75,Assumptions!$C$11,IF((1-J9)>0.7,Assumptions!$C$12,Assumptions!$C$13)) -> 0.0725 | T9: =PMT(S9/12,Assumptions!$C$14,-R9) -> 3325.6094 | U9: =H9*INDEX(Assumptions!$C$28:$C$34,MATCH(D9,Assumptions!$B$28:$B$34,0))/12 -> 514.58333 | V9: =IF(ISNUMBER(P9),P9,INDEX(Assumptions!$D$28:$D$34,MATCH(D9,Assumptions!$B$28:$B$34,0))+INDEX(Assumptions!$C$22:$C$25,MATCH(M9,Assumptions!$B$22:$B$25,0)))/12 -> 250 | W9: =T9+U9+V9+O9 -> 5538.1927 | X9: =IFERROR(K9/12/W9,0) -> 0.73730431 | Y9: =IFERROR(K9*Assumptions!$C$18/12/W9,0) -> 0.58984345 | Z9: =H9*J9+H9*(Assumptions!$C$16-I9) -> 188500 | AA9: =W9*Assumptions!$C$17 -> 33229.156 | AB9: =K9*INDEX(Assumptions!$H$37:$H$38,MATCH(Q9,Assumptions!$B$37:$B$38,0))+Assumptions!$C$41+IF(N9="Y",Assumptions!$C$42,Assumptions!$C$43) -> 18470 | AC9: =K9*INDEX(Assumptions!$C$37:$C$38,MATCH(Q9,Assumptions!$B$37:$B$38,0)) -> 9800 | AD9: =K9-AB9-W9*12 -> -35928.312 | AE9: =AD9-AC9 -> -45728.312 | AF9: =IFERROR(K9/H9,0) -> 0.075384615 | AG9: =IFERROR((K9-AB9-AC9)/H9,0) -> 0.031892308 | AJ9: Price shown $659k-$699k across sites (midpoint used). | AK9: Zillow
A10: 5 | B10: 8302 Marina Villas Dr (Hawks Cay) | C10: Duck Key 33050 | D10: Monroe | E10: Condo | F10: 3/2 / 1,364 / n/s | G10: 849000 | H10: 800000 | I10: 0 | J10: =Assumptions!$C$15 -> 0.25 | K10: 100000 | L10: "rental income for 2025 was over $100,000 for the year"; listed on VRBO | M10: AE | N10: N | O10: 1404 | P10: 3000 | Q10: STR | R10: =H10*(1-J10) -> 600000 | S10: =IF((1-J10)>0.75,Assumptions!$C$11,IF((1-J10)>0.7,Assumptions!$C$12,Assumptions!$C$13)) -> 0.0725 | T10: =PMT(S10/12,Assumptions!$C$14,-R10) -> 4093.0577 | U10: =H10*INDEX(Assumptions!$C$28:$C$34,MATCH(D10,Assumptions!$B$28:$B$34,0))/12 -> 633.33333 | V10: =IF(ISNUMBER(P10),P10,INDEX(Assumptions!$D$28:$D$34,MATCH(D10,Assumptions!$B$28:$B$34,0))+INDEX(Assumptions!$C$22:$C$25,MATCH(M10,Assumptions!$B$22:$B$25,0)))/12 -> 250 | W10: =T10+U10+V10+O10 -> 6380.391 | X10: =IFERROR(K10/12/W10,0) -> 1.3060851 | Y10: =IFERROR(K10*Assumptions!$C$18/12/W10,0) -> 1.044868 | Z10: =H10*J10+H10*(Assumptions!$C$16-I10) -> 232000 | AA10: =W10*Assumptions!$C$17 -> 38282.346 | AB10: =K10*INDEX(Assumptions!$H$37:$H$38,MATCH(Q10,Assumptions!$B$37:$B$38,0))+Assumptions!$C$41+IF(N10="Y",Assumptions!$C$42,Assumptions!$C$43) -> 30200 | AC10: =K10*INDEX(Assumptions!$C$37:$C$38,MATCH(Q10,Assumptions!$B$37:$B$38,0)) -> 20000 | AD10: =K10-AB10-W10*12 -> -6764.6922 | AE10: =AD10-AC10 -> -26764.692 | AF10: =IFERROR(K10/H10,0) -> 0.125 | AG10: =IFERROR((K10-AB10-AC10)/H10,0) -> 0.06225 | AH10: Listed $1.495M (May 2023) | AJ10: Hawks Cay resort = condotel review (fewer DSCR lenders, 25-35% down). Duck Key is unincorporated county: confirm permit/exemption. Also offered for rent at $8k/mo. | AK10: Zillow
A11: 6 | B11: 500 Burton Dr #1402 (Ocean Pointe) | C11: Tavernier 33070 | D11: Monroe | E11: Condo | F11: 2/2 / 816 / 1991 | G11: 555000 | H11: 535000 | I11: 0 | J11: =Assumptions!$C$15 -> 0.25 | K11: 38000 | L11: "grossed $26,900.07 1/1/2026 through 8/20/2026 with owners and friends using it as well" | M11: AE | N11: N | O11: 1448 | P11: 3000 | Q11: STR | R11: =H11*(1-J11) -> 401250 | S11: =IF((1-J11)>0.75,Assumptions!$C$11,IF((1-J11)>0.7,Assumptions!$C$12,Assumptions!$C$13)) -> 0.0725 | T11: =PMT(S11/12,Assumptions!$C$14,-R11) -> 2737.2323 | U11: =H11*INDEX(Assumptions!$C$28:$C$34,MATCH(D11,Assumptions!$B$28:$B$34,0))/12 -> 423.54167 | V11: =IF(ISNUMBER(P11),P11,INDEX(Assumptions!$D$28:$D$34,MATCH(D11,Assumptions!$B$28:$B$34,0))+INDEX(Assumptions!$C$22:$C$25,MATCH(M11,Assumptions!$B$22:$B$25,0)))/12 -> 250 | W11: =T11+U11+V11+O11 -> 4858.774 | X11: =IFERROR(K11/12/W11,0) -> 0.65174192 | Y11: =IFERROR(K11*Assumptions!$C$18/12/W11,0) -> 0.52139353 | Z11: =H11*J11+H11*(Assumptions!$C$16-I11) -> 155150 | AA11: =W11*Assumptions!$C$17 -> 29152.644 | AB11: =K11*INDEX(Assumptions!$H$37:$H$38,MATCH(Q11,Assumptions!$B$37:$B$38,0))+Assumptions!$C$41+IF(N11="Y",Assumptions!$C$42,Assumptions!$C$43) -> 15940 | AC11: =K11*INDEX(Assumptions!$C$37:$C$38,MATCH(Q11,Assumptions!$B$37:$B$38,0)) -> 7600 | AD11: =K11-AB11-W11*12 -> -36245.288 | AE11: =AD11-AC11 -> -43845.288 | AF11: =IFERROR(K11/H11,0) -> 0.071028037 | AG11: =IFERROR((K11-AB11-AC11)/H11,0) -> 0.027028037 | AI11: 68 | AJ11: Shown as the low end: heavy owner use; HOA load kills DSCR at this income. | AK11: Zillow
A14: Keys: licensed/STR-legal units for sale with history on request (verify license + get T12)
B15: Address | C15: City / ZIP | G15: Price | L15: Evidence (no $ in listing) | AJ15: Ask agent for | AK15: Link
B16: 1500 Ocean Bay Dr #A1 (Kawama) | C16: Key Largo 33037 | G16: 750000 | L16: 2/2, 990 sf; "one of the few properties in Key Largo that allows nightly Rentals" | AJ16: T12 payout reports + TDT filings | AK16: Listing
B17: 104350 Overseas Hwy #A204 (Moon Bay) | C17: Key Largo 33037 | G17: 599888 | L17: "Weekly Rentals ALLOWED"; "Rental history is available upon request"; HOA $959/mo | AJ17: T12 payout reports + TDT filings | AK17: Listing
B18: 500 Burton Dr #2202 (Ocean Pointe) | C18: Tavernier 33070 | G18: 524900 | L18: 2/2, 826 sf; "proven history of successful short-term rentals"; listed 7/22/2026 | AJ18: T12 payout reports + TDT filings | AK18: Listing
B19: 8204 Marina Villas Dr (Hawks Cay) | C19: Duck Key 33050 | G19: 699000 | L19: 2/2, 1,414 sf; "approved as turnkey for the resort rental program"; condotel review | AJ19: T12 payout reports + TDT filings | AK19: Listing
B20: 201 E Ocean Dr #312 (Casa Clara) | C20: Key Colony Beach 33051 | G20: 499000 | L20: 2/2, 1,029 sf; 14-day rentals; listed 10/9/2026; check HOA (shown $2,925 = quarterly?) | AJ20: T12 payout reports + TDT filings | AK20: Listing
B21: 3625 Seaside Dr #25410 (Sunrise Suites) | C21: Key West 33040 | G21: 868000 | L21: 2/2 "Transiently licensed"; HOA ~$905/mo; complex sales $775-860k (2022-25) | AJ21: T12 payout reports + TDT filings | AK21: Listing
B22: 320 Calzada de Bougainvillea | C22: Marathon 33050 | G22: 1049000 | L22: Over cap: 2/2 house, heated pool; "$116,000 in short-rental income in 2025"; $201k price cut | AJ22: T12 payout reports + TDT filings | AK22: Listing
B23: Mariners Club #906 | C23: Key Largo 33037 | G23: 955000 | L23: Just over cap; daily rentals; "5 years of rental history on VRBO"; $45k equity membership | AJ23: T12 payout reports + TDT filings | AK23: Listing

Sheet Down Pmt Scenarios
A1: Down Payment Scenarios: 20% vs 25% vs 30%
A2: Green cells pull offer price, credit, income, flood, pool, HOA and profile from the market tabs; rate tier follows LTV from Assumptions. Change a down % (blue) to test other levels.
A4: Property | B4: Down % | C4: Offer Price | D4: Seller Credit % | E4: Gross ($/yr) | F4: Loan | G4: Rate | H4: P&I ($/mo) | I4: PITIA ($/mo) | J4: DSCR (gross) | K4: DSCR (haircut) | L4: Cash In (down + closing - credit) | M4: Cash Flow Self-Managed ($/yr) | N4: Cash Flow Full PM ($/yr) | O4: Cash-on-Cash (self) | P4: Marginal Return on Extra Cash vs Prior Row
A5: ='Manatee-Sarasota'!$B$6 -> 8404 43rd Ave Terrace W | B5: 0.2 | C5: ='Manatee-Sarasota'!$H$6 -> 560000 | D5: ='Manatee-Sarasota'!$I$6 -> 0.03 | E5: ='Manatee-Sarasota'!$K$6 -> 85000 | F5: =C5*(1-B5) -> 448000 | G5: =IF((1-B5)>0.75,Assumptions!$C$11,IF((1-B5)>0.7,Assumptions!$C$12,Assumptions!$C$13)) -> 0.075 | H5: =PMT(G5/12,Assumptions!$C$14,-F5) -> 3132.481 | I5: =H5+C5*INDEX(Assumptions!$C$28:$C$34,MATCH('Manatee-Sarasota'!$D$6,Assumptions!$B$28:$B$34,0))/12+IF(ISNUMBER('Manatee-Sarasota'!$P$6),'Manatee-Sarasota'!$P$6,INDEX(Assumptions!$D$28:$D$34,MATCH('Manatee-Sarasota'!$D$6,Assumptions!$B$28:$B$34,0))+INDEX(Assumptions!$C$22:$C$25,MATCH('Manatee-Sarasota'!$M$6,Assumptions!$B$22:$B$25,0)))/12+'Manatee-Sarasota'!$O$6 -> 4582.481 | J5: =IFERROR(E5/12/I5,0) -> 1.545742 | K5: =IFERROR(E5*Assumptions!$C$18/12/I5,0) -> 1.2365936 | L5: =C5*B5+C5*(Assumptions!$C$16-D5) -> 117600 | M5: =E5-(E5*INDEX(Assumptions!$H$37:$H$38,MATCH('Manatee-Sarasota'!$Q$6,Assumptions!$B$37:$B$38,0))+Assumptions!$C$41+IF('Manatee-Sarasota'!$N$6="Y",Assumptions!$C$42,Assumptions!$C$43))-I5*12 -> 1460.228 | N5: =M5-E5*INDEX(Assumptions!$C$37:$C$38,MATCH('Manatee-Sarasota'!$Q$6,Assumptions!$B$37:$B$38,0)) -> -15539.772 | O5: =IFERROR(M5/L5,0) -> 0.012416905 | P5: -
A6: ='Manatee-Sarasota'!$B$6 -> 8404 43rd Ave Terrace W | B6: 0.25 | C6: ='Manatee-Sarasota'!$H$6 -> 560000 | D6: ='Manatee-Sarasota'!$I$6 -> 0.03 | E6: ='Manatee-Sarasota'!$K$6 -> 85000 | F6: =C6*(1-B6) -> 420000 | G6: =IF((1-B6)>0.75,Assumptions!$C$11,IF((1-B6)>0.7,Assumptions!$C$12,Assumptions!$C$13)) -> 0.0725 | H6: =PMT(G6/12,Assumptions!$C$14,-F6) -> 2865.1404 | I6: =H6+C6*INDEX(Assumptions!$C$28:$C$34,MATCH('Manatee-Sarasota'!$D$6,Assumptions!$B$28:$B$34,0))/12+IF(ISNUMBER('Manatee-Sarasota'!$P$6),'Manatee-Sarasota'!$P$6,INDEX(Assumptions!$D$28:$D$34,MATCH('Manatee-Sarasota'!$D$6,Assumptions!$B$28:$B$34,0))+INDEX(Assumptions!$C$22:$C$25,MATCH('Manatee-Sarasota'!$M$6,Assumptions!$B$22:$B$25,0)))/12+'Manatee-Sarasota'!$O$6 -> 4315.1404 | J6: =IFERROR(E6/12/I6,0) -> 1.641507 | K6: =IFERROR(E6*Assumptions!$C$18/12/I6,0) -> 1.3132056 | L6: =C6*B6+C6*(Assumptions!$C$16-D6) -> 145600 | M6: =E6-(E6*INDEX(Assumptions!$H$37:$H$38,MATCH('Manatee-Sarasota'!$Q$6,Assumptions!$B$37:$B$38,0))+Assumptions!$C$41+IF('Manatee-Sarasota'!$N$6="Y",Assumptions!$C$42,Assumptions!$C$43))-I6*12 -> 4668.3155 | N6: =M6-E6*INDEX(Assumptions!$C$37:$C$38,MATCH('Manatee-Sarasota'!$Q$6,Assumptions!$B$37:$B$38,0)) -> -12331.685 | O6: =IFERROR(M6/L6,0) -> 0.032062606 | P6: =IFERROR((M6-M5)/(L6-L5),0) -> 0.11457455
A7: ='Manatee-Sarasota'!$B$6 -> 8404 43rd Ave Terrace W | B7: 0.3 | C7: ='Manatee-Sarasota'!$H$6 -> 560000 | D7: ='Manatee-Sarasota'!$I$6 -> 0.03 | E7: ='Manatee-Sarasota'!$K$6 -> 85000 | F7: =C7*(1-B7) -> 392000 | G7: =IF((1-B7)>0.75,Assumptions!$C$11,IF((1-B7)>0.7,Assumptions!$C$12,Assumptions!$C$13)) -> 0.07125 | H7: =PMT(G7/12,Assumptions!$C$14,-F7) -> 2640.9766 | I7: =H7+C7*INDEX(Assumptions!$C$28:$C$34,MATCH('Manatee-Sarasota'!$D$6,Assumptions!$B$28:$B$34,0))/12+IF(ISNUMBER('Manatee-Sarasota'!$P$6),'Manatee-Sarasota'!$P$6,INDEX(Assumptions!$D$28:$D$34,MATCH('Manatee-Sarasota'!$D$6,Assumptions!$B$28:$B$34,0))+INDEX(Assumptions!$C$22:$C$25,MATCH('Manatee-Sarasota'!$M$6,Assumptions!$B$22:$B$25,0)))/12+'Manatee-Sarasota'!$O$6 -> 4090.9766 | J7: =IFERROR(E7/12/I7,0) -> 1.7314529 | K7: =IFERROR(E7*Assumptions!$C$18/12/I7,0) -> 1.3851623 | L7: =C7*B7+C7*(Assumptions!$C$16-D7) -> 173600 | M7: =E7-(E7*INDEX(Assumptions!$H$37:$H$38,MATCH('Manatee-Sarasota'!$Q$6,Assumptions!$B$37:$B$38,0))+Assumptions!$C$41+IF('Manatee-Sarasota'!$N$6="Y",Assumptions!$C$42,Assumptions!$C$43))-I7*12 -> 7358.2807 | N7: =M7-E7*INDEX(Assumptions!$C$37:$C$38,MATCH('Manatee-Sarasota'!$Q$6,Assumptions!$B$37:$B$38,0)) -> -9641.7193 | O7: =IFERROR(M7/L7,0) -> 0.042386409 | P7: =IFERROR((M7-M6)/(L7-L6),0) -> 0.096070185
A9: ='Manatee-Sarasota'!$B$7 -> 5318 17th St W (duplex) | B9: 0.2 | C9: ='Manatee-Sarasota'!$H$7 -> 460000 | D9: ='Manatee-Sarasota'!$I$7 -> 0 | E9: ='Manatee-Sarasota'!$K$7 -> 73000 | F9: =C9*(1-B9) -> 368000 | G9: =IF((1-B9)>0.75,Assumptions!$C$11,IF((1-B9)>0.7,Assumptions!$C$12,Assumptions!$C$13)) -> 0.075 | H9: =PMT(G9/12,Assumptions!$C$14,-F9) -> 2573.1094 | I9: =H9+C9*INDEX(Assumptions!$C$28:$C$34,MATCH('Manatee-Sarasota'!$D$7,Assumptions!$B$28:$B$34,0))/12+IF(ISNUMBER('Manatee-Sarasota'!$P$7),'Manatee-Sarasota'!$P$7,INDEX(Assumptions!$D$28:$D$34,MATCH('Manatee-Sarasota'!$D$7,Assumptions!$B$28:$B$34,0))+INDEX(Assumptions!$C$22:$C$25,MATCH('Manatee-Sarasota'!$M$7,Assumptions!$B$22:$B$25,0)))/12+'Manatee-Sarasota'!$O$7 -> 3898.1094 | J9: =IFERROR(E9/12/I9,0) -> 1.5605856 | K9: =IFERROR(E9*Assumptions!$C$18/12/I9,0) -> 1.2484685 | L9: =C9*B9+C9*(Assumptions!$C$16-D9) -> 110400 | M9: =E9-(E9*INDEX(Assumptions!$H$37:$H$38,MATCH('Manatee-Sarasota'!$Q$7,Assumptions!$B$37:$B$38,0))+Assumptions!$C$41+IF('Manatee-Sarasota'!$N$7="Y",Assumptions!$C$42,Assumptions!$C$43))-I9*12 -> 2232.6873 | N9: =M9-E9*INDEX(Assumptions!$C$37:$C$38,MATCH('Manatee-Sarasota'!$Q$7,Assumptions!$B$37:$B$38,0)) -> -12367.313 | O9: =IFERROR(M9/L9,0) -> 0.020223617 | P9: -
A10: ='Manatee-Sarasota'!$B$7 -> 5318 17th St W (duplex) | B10: 0.25 | C10: ='Manatee-Sarasota'!$H$7 -> 460000 | D10: ='Manatee-Sarasota'!$I$7 -> 0 | E10: ='Manatee-Sarasota'!$K$7 -> 73000 | F10: =C10*(1-B10) -> 345000 | G10: =IF((1-B10)>0.75,Assumptions!$C$11,IF((1-B10)>0.7,Assumptions!$C$12,Assumptions!$C$13)) -> 0.0725 | H10: =PMT(G10/12,Assumptions!$C$14,-F10) -> 2353.5082 | I10: =H10+C10*INDEX(Assumptions!$C$28:$C$34,MATCH('Manatee-Sarasota'!$D$7,Assumptions!$B$28:$B$34,0))/12+IF(ISNUMBER('Manatee-Sarasota'!$P$7),'Manatee-Sarasota'!$P$7,INDEX(Assumptions!$D$28:$D$34,MATCH('Manatee-Sarasota'!$D$7,Assumptions!$B$28:$B$34,0))+INDEX(Assumptions!$C$22:$C$25,MATCH('Manatee-Sarasota'!$M$7,Assumptions!$B$22:$B$25,0)))/12+'Manatee-Sarasota'!$O$7 -> 3678.5082 | J10: =IFERROR(E10/12/I10,0) -> 1.6537501 | K10: =IFERROR(E10*Assumptions!$C$18/12/I10,0) -> 1.3230001 | L10: =C10*B10+C10*(Assumptions!$C$16-D10) -> 133400 | M10: =E10-(E10*INDEX(Assumptions!$H$37:$H$38,MATCH('Manatee-Sarasota'!$Q$7,Assumptions!$B$37:$B$38,0))+Assumptions!$C$41+IF('Manatee-Sarasota'!$N$7="Y",Assumptions!$C$42,Assumptions!$C$43))-I10*12 -> 4867.902 | N10: =M10-E10*INDEX(Assumptions!$C$37:$C$38,MATCH('Manatee-Sarasota'!$Q$7,Assumptions!$B$37:$B$38,0)) -> -9732.098 | O10: =IFERROR(M10/L10,0) -> 0.03649102 | P10: =IFERROR((M10-M9)/(L10-L9),0) -> 0.11457455
A11: ='Manatee-Sarasota'!$B$7 -> 5318 17th St W (duplex) | B11: 0.3 | C11: ='Manatee-Sarasota'!$H$7 -> 460000 | D11: ='Manatee-Sarasota'!$I$7 -> 0 | E11: ='Manatee-Sarasota'!$K$7 -> 73000 | F11: =C11*(1-B11) -> 322000 | G11: =IF((1-B11)>0.75,Assumptions!$C$11,IF((1-B11)>0.7,Assumptions!$C$12,Assumptions!$C$13)) -> 0.07125 | H11: =PMT(G11/12,Assumptions!$C$14,-F11) -> 2169.3736 | I11: =H11+C11*INDEX(Assumptions!$C$28:$C$34,MATCH('Manatee-Sarasota'!$D$7,Assumptions!$B$28:$B$34,0))/12+IF(ISNUMBER('Manatee-Sarasota'!$P$7),'Manatee-Sarasota'!$P$7,INDEX(Assumptions!$D$28:$D$34,MATCH('Manatee-Sarasota'!$D$7,Assumptions!$B$28:$B$34,0))+INDEX(Assumptions!$C$22:$C$25,MATCH('Manatee-Sarasota'!$M$7,Assumptions!$B$22:$B$25,0)))/12+'Manatee-Sarasota'!$O$7 -> 3494.3736 | J11: =IFERROR(E11/12/I11,0) -> 1.7408938 | K11: =IFERROR(E11*Assumptions!$C$18/12/I11,0) -> 1.392715 | L11: =C11*B11+C11*(Assumptions!$C$16-D11) -> 156400 | M11: =E11-(E11*INDEX(Assumptions!$H$37:$H$38,MATCH('Manatee-Sarasota'!$Q$7,Assumptions!$B$37:$B$38,0))+Assumptions!$C$41+IF('Manatee-Sarasota'!$N$7="Y",Assumptions!$C$42,Assumptions!$C$43))-I11*12 -> 7077.5163 | N11: =M11-E11*INDEX(Assumptions!$C$37:$C$38,MATCH('Manatee-Sarasota'!$Q$7,Assumptions!$B$37:$B$38,0)) -> -7522.4837 | O11: =IFERROR(M11/L11,0) -> 0.045252662 | P11: =IFERROR((M11-M10)/(L11-L10),0) -> 0.096070185
A13: ='Manatee-Sarasota'!$B$8 -> 2801 23rd Ave W ("Beachin' Escape") | B13: 0.2 | C13: ='Manatee-Sarasota'!$H$8 -> 600000 | D13: ='Manatee-Sarasota'!$I$8 -> 0.03 | E13: ='Manatee-Sarasota'!$K$8 -> 89000 | F13: =C13*(1-B13) -> 480000 | G13: =IF((1-B13)>0.75,Assumptions!$C$11,IF((1-B13)>0.7,Assumptions!$C$12,Assumptions!$C$13)) -> 0.075 | H13: =PMT(G13/12,Assumptions!$C$14,-F13) -> 3356.2296 | I13: =H13+C13*INDEX(Assumptions!$C$28:$C$34,MATCH('Manatee-Sarasota'!$D$8,Assumptions!$B$28:$B$34,0))/12+IF(ISNUMBER('Manatee-Sarasota'!$P$8),'Manatee-Sarasota'!$P$8,INDEX(Assumptions!$D$28:$D$34,MATCH('Manatee-Sarasota'!$D$8,Assumptions!$B$28:$B$34,0))+INDEX(Assumptions!$C$22:$C$25,MATCH('Manatee-Sarasota'!$M$8,Assumptions!$B$22:$B$25,0)))/12+'Manatee-Sarasota'!$O$8 -> 4856.2296 | J13: =IFERROR(E13/12/I13,0) -> 1.5272479 | K13: =IFERROR(E13*Assumptions!$C$18/12/I13,0) -> 1.2217983 | L13: =C13*B13+C13*(Assumptions!$C$16-D13) -> 126000 | M13: =E13-(E13*INDEX(Assumptions!$H$37:$H$38,MATCH('Manatee-Sarasota'!$Q$8,Assumptions!$B$37:$B$38,0))+Assumptions!$C$41+IF('Manatee-Sarasota'!$N$8="Y",Assumptions!$C$42,Assumptions!$C$43))-I13*12 -> 1255.2443 | N13: =M13-E13*INDEX(Assumptions!$C$37:$C$38,MATCH('Manatee-Sarasota'!$Q$8,Assumptions!$B$37:$B$38,0)) -> -16544.756 | O13: =IFERROR(M13/L13,0) -> 0.0099622564 | P13: -
A14: ='Manatee-Sarasota'!$B$8 -> 2801 23rd Ave W ("Beachin' Escape") | B14: 0.25 | C14: ='Manatee-Sarasota'!$H$8 -> 600000 | D14: ='Manatee-Sarasota'!$I$8 -> 0.03 | E14: ='Manatee-Sarasota'!$K$8 -> 89000 | F14: =C14*(1-B14) -> 450000 | G14: =IF((1-B14)>0.75,Assumptions!$C$11,IF((1-B14)>0.7,Assumptions!$C$12,Assumptions!$C$13)) -> 0.0725 | H14: =PMT(G14/12,Assumptions!$C$14,-F14) -> 3069.7933 | I14: =H14+C14*INDEX(Assumptions!$C$28:$C$34,MATCH('Manatee-Sarasota'!$D$8,Assumptions!$B$28:$B$34,0))/12+IF(ISNUMBER('Manatee-Sarasota'!$P$8),'Manatee-Sarasota'!$P$8,INDEX(Assumptions!$D$28:$D$34,MATCH('Manatee-Sarasota'!$D$8,Assumptions!$B$28:$B$34,0))+INDEX(Assumptions!$C$22:$C$25,MATCH('Manatee-Sarasota'!$M$8,Assumptions!$B$22:$B$25,0)))/12+'Manatee-Sarasota'!$O$8 -> 4569.7933 | J14: =IFERROR(E14/12/I14,0) -> 1.6229764 | K14: =IFERROR(E14*Assumptions!$C$18/12/I14,0) -> 1.2983811 | L14: =C14*B14+C14*(Assumptions!$C$16-D14) -> 156000 | M14: =E14-(E14*INDEX(Assumptions!$H$37:$H$38,MATCH('Manatee-Sarasota'!$Q$8,Assumptions!$B$37:$B$38,0))+Assumptions!$C$41+IF('Manatee-Sarasota'!$N$8="Y",Assumptions!$C$42,Assumptions!$C$43))-I14*12 -> 4692.4809 | N14: =M14-E14*INDEX(Assumptions!$C$37:$C$38,MATCH('Manatee-Sarasota'!$Q$8,Assumptions!$B$37:$B$38,0)) -> -13107.519 | O14: =IFERROR(M14/L14,0) -> 0.030080006 | P14: =IFERROR((M14-M13)/(L14-L13),0) -> 0.11457455
A15: ='Manatee-Sarasota'!$B$8 -> 2801 23rd Ave W ("Beachin' Escape") | B15: 0.3 | C15: ='Manatee-Sarasota'!$H$8 -> 600000 | D15: ='Manatee-Sarasota'!$I$8 -> 0.03 | E15: ='Manatee-Sarasota'!$K$8 -> 89000 | F15: =C15*(1-B15) -> 420000 | G15: =IF((1-B15)>0.75,Assumptions!$C$11,IF((1-B15)>0.7,Assumptions!$C$12,Assumptions!$C$13)) -> 0.07125 | H15: =PMT(G15/12,Assumptions!$C$14,-F15) -> 2829.6178 | I15: =H15+C15*INDEX(Assumptions!$C$28:$C$34,MATCH('Manatee-Sarasota'!$D$8,Assumptions!$B$28:$B$34,0))/12+IF(ISNUMBER('Manatee-Sarasota'!$P$8),'Manatee-Sarasota'!$P$8,INDEX(Assumptions!$D$28:$D$34,MATCH('Manatee-Sarasota'!$D$8,Assumptions!$B$28:$B$34,0))+INDEX(Assumptions!$C$22:$C$25,MATCH('Manatee-Sarasota'!$M$8,Assumptions!$B$22:$B$25,0)))/12+'Manatee-Sarasota'!$O$8 -> 4329.6178 | J15: =IFERROR(E15/12/I15,0) -> 1.7130072 | K15: =IFERROR(E15*Assumptions!$C$18/12/I15,0) -> 1.3704058 | L15: =C15*B15+C15*(Assumptions!$C$16-D15) -> 186000 | M15: =E15-(E15*INDEX(Assumptions!$H$37:$H$38,MATCH('Manatee-Sarasota'!$Q$8,Assumptions!$B$37:$B$38,0))+Assumptions!$C$41+IF('Manatee-Sarasota'!$N$8="Y",Assumptions!$C$42,Assumptions!$C$43))-I15*12 -> 7574.5864 | N15: =M15-E15*INDEX(Assumptions!$C$37:$C$38,MATCH('Manatee-Sarasota'!$Q$8,Assumptions!$B$37:$B$38,0)) -> -10225.414 | O15: =IFERROR(M15/L15,0) -> 0.040723583 | P15: =IFERROR((M15-M14)/(L15-L14),0) -> 0.096070185
A17: =Pinellas!$B$6 -> 12565 81st Ave | B17: 0.2 | C17: =Pinellas!$H$6 -> 485000 | D17: =Pinellas!$I$6 -> 0 | E17: =Pinellas!$K$6 -> 71000 | F17: =C17*(1-B17) -> 388000 | G17: =IF((1-B17)>0.75,Assumptions!$C$11,IF((1-B17)>0.7,Assumptions!$C$12,Assumptions!$C$13)) -> 0.075 | H17: =PMT(G17/12,Assumptions!$C$14,-F17) -> 2712.9523 | I17: =H17+C17*INDEX(Assumptions!$C$28:$C$34,MATCH(Pinellas!$D$6,Assumptions!$B$28:$B$34,0))/12+IF(ISNUMBER(Pinellas!$P$6),Pinellas!$P$6,INDEX(Assumptions!$D$28:$D$34,MATCH(Pinellas!$D$6,Assumptions!$B$28:$B$34,0))+INDEX(Assumptions!$C$22:$C$25,MATCH(Pinellas!$M$6,Assumptions!$B$22:$B$25,0)))/12+Pinellas!$O$6 -> 4109.619 | J17: =IFERROR(E17/12/I17,0) -> 1.4397117 | K17: =IFERROR(E17*Assumptions!$C$18/12/I17,0) -> 1.1517694 | L17: =C17*B17+C17*(Assumptions!$C$16-D17) -> 116400 | M17: =E17-(E17*INDEX(Assumptions!$H$37:$H$38,MATCH(Pinellas!$Q$6,Assumptions!$B$37:$B$38,0))+Assumptions!$C$41+IF(Pinellas!$N$6="Y",Assumptions!$C$42,Assumptions!$C$43))-I17*12 -> -3645.4275 | N17: =M17-E17*INDEX(Assumptions!$C$37:$C$38,MATCH(Pinellas!$Q$6,Assumptions!$B$37:$B$38,0)) -> -17845.428 | O17: =IFERROR(M17/L17,0) -> -0.031318106 | P17: -
A18: =Pinellas!$B$6 -> 12565 81st Ave | B18: 0.25 | C18: =Pinellas!$H$6 -> 485000 | D18: =Pinellas!$I$6 -> 0 | E18: =Pinellas!$K$6 -> 71000 | F18: =C18*(1-B18) -> 363750 | G18: =IF((1-B18)>0.75,Assumptions!$C$11,IF((1-B18)>0.7,Assumptions!$C$12,Assumptions!$C$13)) -> 0.0725 | H18: =PMT(G18/12,Assumptions!$C$14,-F18) -> 2481.4162 | I18: =H18+C18*INDEX(Assumptions!$C$28:$C$34,MATCH(Pinellas!$D$6,Assumptions!$B$28:$B$34,0))/12+IF(ISNUMBER(Pinellas!$P$6),Pinellas!$P$6,INDEX(Assumptions!$D$28:$D$34,MATCH(Pinellas!$D$6,Assumptions!$B$28:$B$34,0))+INDEX(Assumptions!$C$22:$C$25,MATCH(Pinellas!$M$6,Assumptions!$B$22:$B$25,0)))/12+Pinellas!$O$6 -> 3878.0829 | J18: =IFERROR(E18/12/I18,0) -> 1.5256679 | K18: =IFERROR(E18*Assumptions!$C$18/12/I18,0) -> 1.2205343 | L18: =C18*B18+C18*(Assumptions!$C$16-D18) -> 140650 | M18: =E18-(E18*INDEX(Assumptions!$H$37:$H$38,MATCH(Pinellas!$Q$6,Assumptions!$B$37:$B$38,0))+Assumptions!$C$41+IF(Pinellas!$N$6="Y",Assumptions!$C$42,Assumptions!$C$43))-I18*12 -> -866.99462 | N18: =M18-E18*INDEX(Assumptions!$C$37:$C$38,MATCH(Pinellas!$Q$6,Assumptions!$B$37:$B$38,0)) -> -15066.995 | O18: =IFERROR(M18/L18,0) -> -0.0061641992 | P18: =IFERROR((M18-M17)/(L18-L17),0) -> 0.11457455
A19: =Pinellas!$B$6 -> 12565 81st Ave | B19: 0.3 | C19: =Pinellas!$H$6 -> 485000 | D19: =Pinellas!$I$6 -> 0 | E19: =Pinellas!$K$6 -> 71000 | F19: =C19*(1-B19) -> 339500 | G19: =IF((1-B19)>0.75,Assumptions!$C$11,IF((1-B19)>0.7,Assumptions!$C$12,Assumptions!$C$13)) -> 0.07125 | H19: =PMT(G19/12,Assumptions!$C$14,-F19) -> 2287.2744 | I19: =H19+C19*INDEX(Assumptions!$C$28:$C$34,MATCH(Pinellas!$D$6,Assumptions!$B$28:$B$34,0))/12+IF(ISNUMBER(Pinellas!$P$6),Pinellas!$P$6,INDEX(Assumptions!$D$28:$D$34,MATCH(Pinellas!$D$6,Assumptions!$B$28:$B$34,0))+INDEX(Assumptions!$C$22:$C$25,MATCH(Pinellas!$M$6,Assumptions!$B$22:$B$25,0)))/12+Pinellas!$O$6 -> 3683.9411 | J19: =IFERROR(E19/12/I19,0) -> 1.6060699 | K19: =IFERROR(E19*Assumptions!$C$18/12/I19,0) -> 1.2848559 | L19: =C19*B19+C19*(Assumptions!$C$16-D19) -> 164900 | M19: =E19-(E19*INDEX(Assumptions!$H$37:$H$38,MATCH(Pinellas!$Q$6,Assumptions!$B$37:$B$38,0))+Assumptions!$C$41+IF(Pinellas!$N$6="Y",Assumptions!$C$42,Assumptions!$C$43))-I19*12 -> 1462.7074 | N19: =M19-E19*INDEX(Assumptions!$C$37:$C$38,MATCH(Pinellas!$Q$6,Assumptions!$B$37:$B$38,0)) -> -12737.293 | O19: =IFERROR(M19/L19,0) -> 0.008870269 | P19: =IFERROR((M19-M18)/(L19-L18),0) -> 0.096070185
A21: =Pinellas!$B$7 -> 4000 46th St N | B21: 0.2 | C21: =Pinellas!$H$7 -> 485000 | D21: =Pinellas!$I$7 -> 0 | E21: =Pinellas!$K$7 -> 85000 | F21: =C21*(1-B21) -> 388000 | G21: =IF((1-B21)>0.75,Assumptions!$C$11,IF((1-B21)>0.7,Assumptions!$C$12,Assumptions!$C$13)) -> 0.075 | H21: =PMT(G21/12,Assumptions!$C$14,-F21) -> 2712.9523 | I21: =H21+C21*INDEX(Assumptions!$C$28:$C$34,MATCH(Pinellas!$D$7,Assumptions!$B$28:$B$34,0))/12+IF(ISNUMBER(Pinellas!$P$7),Pinellas!$P$7,INDEX(Assumptions!$D$28:$D$34,MATCH(Pinellas!$D$7,Assumptions!$B$28:$B$34,0))+INDEX(Assumptions!$C$22:$C$25,MATCH(Pinellas!$M$7,Assumptions!$B$22:$B$25,0)))/12+Pinellas!$O$7 -> 4109.619 | J21: =IFERROR(E21/12/I21,0) -> 1.7235986 | K21: =IFERROR(E21*Assumptions!$C$18/12/I21,0) -> 1.3788789 | L21: =C21*B21+C21*(Assumptions!$C$16-D21) -> 116400 | M21: =E21-(E21*INDEX(Assumptions!$H$37:$H$38,MATCH(Pinellas!$Q$7,Assumptions!$B$37:$B$38,0))+Assumptions!$C$41+IF(Pinellas!$N$7="Y",Assumptions!$C$42,Assumptions!$C$43))-I21*12 -> 7134.5725 | N21: =M21-E21*INDEX(Assumptions!$C$37:$C$38,MATCH(Pinellas!$Q$7,Assumptions!$B$37:$B$38,0)) -> -9865.4275 | O21: =IFERROR(M21/L21,0) -> 0.061293578 | P21: -
A22: =Pinellas!$B$7 -> 4000 46th St N | B22: 0.25 | C22: =Pinellas!$H$7 -> 485000 | D22: =Pinellas!$I$7 -> 0 | E22: =Pinellas!$K$7 -> 85000 | F22: =C22*(1-B22) -> 363750 | G22: =IF((1-B22)>0.75,Assumptions!$C$11,IF((1-B22)>0.7,Assumptions!$C$12,Assumptions!$C$13)) -> 0.0725 | H22: =PMT(G22/12,Assumptions!$C$14,-F22) -> 2481.4162 | I22: =H22+C22*INDEX(Assumptions!$C$28:$C$34,MATCH(Pinellas!$D$7,Assumptions!$B$28:$B$34,0))/12+IF(ISNUMBER(Pinellas!$P$7),Pinellas!$P$7,INDEX(Assumptions!$D$28:$D$34,MATCH(Pinellas!$D$7,Assumptions!$B$28:$B$34,0))+INDEX(Assumptions!$C$22:$C$25,MATCH(Pinellas!$M$7,Assumptions!$B$22:$B$25,0)))/12+Pinellas!$O$7 -> 3878.0829 | J22: =IFERROR(E22/12/I22,0) -> 1.8265039 | K22: =IFERROR(E22*Assumptions!$C$18/12/I22,0) -> 1.4612031 | L22: =C22*B22+C22*(Assumptions!$C$16-D22) -> 140650 | M22: =E22-(E22*INDEX(Assumptions!$H$37:$H$38,MATCH(Pinellas!$Q$7,Assumptions!$B$37:$B$38,0))+Assumptions!$C$41+IF(Pinellas!$N$7="Y",Assumptions!$C$42,Assumptions!$C$43))-I22*12 -> 9913.0054 | N22: =M22-E22*INDEX(Assumptions!$C$37:$C$38,MATCH(Pinellas!$Q$7,Assumptions!$B$37:$B$38,0)) -> -7086.9946 | O22: =IFERROR(M22/L22,0) -> 0.070479953 | P22: =IFERROR((M22-M21)/(L22-L21),0) -> 0.11457455
A23: =Pinellas!$B$7 -> 4000 46th St N | B23: 0.3 | C23: =Pinellas!$H$7 -> 485000 | D23: =Pinellas!$I$7 -> 0 | E23: =Pinellas!$K$7 -> 85000 | F23: =C23*(1-B23) -> 339500 | G23: =IF((1-B23)>0.75,Assumptions!$C$11,IF((1-B23)>0.7,Assumptions!$C$12,Assumptions!$C$13)) -> 0.07125 | H23: =PMT(G23/12,Assumptions!$C$14,-F23) -> 2287.2744 | I23: =H23+C23*INDEX(Assumptions!$C$28:$C$34,MATCH(Pinellas!$D$7,Assumptions!$B$28:$B$34,0))/12+IF(ISNUMBER(Pinellas!$P$7),Pinellas!$P$7,INDEX(Assumptions!$D$28:$D$34,MATCH(Pinellas!$D$7,Assumptions!$B$28:$B$34,0))+INDEX(Assumptions!$C$22:$C$25,MATCH(Pinellas!$M$7,Assumptions!$B$22:$B$25,0)))/12+Pinellas!$O$7 -> 3683.9411 | J23: =IFERROR(E23/12/I23,0) -> 1.9227597 | K23: =IFERROR(E23*Assumptions!$C$18/12/I23,0) -> 1.5382077 | L23: =C23*B23+C23*(Assumptions!$C$16-D23) -> 164900 | M23: =E23-(E23*INDEX(Assumptions!$H$37:$H$38,MATCH(Pinellas!$Q$7,Assumptions!$B$37:$B$38,0))+Assumptions!$C$41+IF(Pinellas!$N$7="Y",Assumptions!$C$42,Assumptions!$C$43))-I23*12 -> 12242.707 | N23: =M23-E23*INDEX(Assumptions!$C$37:$C$38,MATCH(Pinellas!$Q$7,Assumptions!$B$37:$B$38,0)) -> -4757.2926 | O23: =IFERROR(M23/L23,0) -> 0.074243222 | P23: =IFERROR((M23-M22)/(L23-L22),0) -> 0.096070185
A25: ='Monroe (Keys)'!$B$6 -> 1500 Ocean Bay Dr #E5 (Kawama Yacht Club) | B25: 0.2 | C25: ='Monroe (Keys)'!$H$6 -> 760000 | D25: ='Monroe (Keys)'!$I$6 -> 0 | E25: ='Monroe (Keys)'!$K$6 -> 98980 | F25: =C25*(1-B25) -> 608000 | G25: =IF((1-B25)>0.75,Assumptions!$C$11,IF((1-B25)>0.7,Assumptions!$C$12,Assumptions!$C$13)) -> 0.075 | H25: =PMT(G25/12,Assumptions!$C$14,-F25) -> 4251.2242 | I25: =H25+C25*INDEX(Assumptions!$C$28:$C$34,MATCH('Monroe (Keys)'!$D$6,Assumptions!$B$28:$B$34,0))/12+IF(ISNUMBER('Monroe (Keys)'!$P$6),'Monroe (Keys)'!$P$6,INDEX(Assumptions!$D$28:$D$34,MATCH('Monroe (Keys)'!$D$6,Assumptions!$B$28:$B$34,0))+INDEX(Assumptions!$C$22:$C$25,MATCH('Monroe (Keys)'!$M$6,Assumptions!$B$22:$B$25,0)))/12+'Monroe (Keys)'!$O$6 -> 6302.8909 | J25: =IFERROR(E25/12/I25,0) -> 1.3086588 | K25: =IFERROR(E25*Assumptions!$C$18/12/I25,0) -> 1.046927 | L25: =C25*B25+C25*(Assumptions!$C$16-D25) -> 182400 | M25: =E25-(E25*INDEX(Assumptions!$H$37:$H$38,MATCH('Monroe (Keys)'!$Q$6,Assumptions!$B$37:$B$38,0))+Assumptions!$C$41+IF('Monroe (Keys)'!$N$6="Y",Assumptions!$C$42,Assumptions!$C$43))-I25*12 -> -6620.0905 | N25: =M25-E25*INDEX(Assumptions!$C$37:$C$38,MATCH('Monroe (Keys)'!$Q$6,Assumptions!$B$37:$B$38,0)) -> -26416.091 | O25: =IFERROR(M25/L25,0) -> -0.036294356 | P25: -
A26: ='Monroe (Keys)'!$B$6 -> 1500 Ocean Bay Dr #E5 (Kawama Yacht Club) | B26: 0.25 | C26: ='Monroe (Keys)'!$H$6 -> 760000 | D26: ='Monroe (Keys)'!$I$6 -> 0 | E26: ='Monroe (Keys)'!$K$6 -> 98980 | F26: =C26*(1-B26) -> 570000 | G26: =IF((1-B26)>0.75,Assumptions!$C$11,IF((1-B26)>0.7,Assumptions!$C$12,Assumptions!$C$13)) -> 0.0725 | H26: =PMT(G26/12,Assumptions!$C$14,-F26) -> 3888.4048 | I26: =H26+C26*INDEX(Assumptions!$C$28:$C$34,MATCH('Monroe (Keys)'!$D$6,Assumptions!$B$28:$B$34,0))/12+IF(ISNUMBER('Monroe (Keys)'!$P$6),'Monroe (Keys)'!$P$6,INDEX(Assumptions!$D$28:$D$34,MATCH('Monroe (Keys)'!$D$6,Assumptions!$B$28:$B$34,0))+INDEX(Assumptions!$C$22:$C$25,MATCH('Monroe (Keys)'!$M$6,Assumptions!$B$22:$B$25,0)))/12+'Monroe (Keys)'!$O$6 -> 5940.0715 | J26: =IFERROR(E26/12/I26,0) -> 1.3885916 | K26: =IFERROR(E26*Assumptions!$C$18/12/I26,0) -> 1.1108733 | L26: =C26*B26+C26*(Assumptions!$C$16-D26) -> 220400 | M26: =E26-(E26*INDEX(Assumptions!$H$37:$H$38,MATCH('Monroe (Keys)'!$Q$6,Assumptions!$B$37:$B$38,0))+Assumptions!$C$41+IF('Monroe (Keys)'!$N$6="Y",Assumptions!$C$42,Assumptions!$C$43))-I26*12 -> -2266.2576 | N26: =M26-E26*INDEX(Assumptions!$C$37:$C$38,MATCH('Monroe (Keys)'!$Q$6,Assumptions!$B$37:$B$38,0)) -> -22062.258 | O26: =IFERROR(M26/L26,0) -> -0.010282475 | P26: =IFERROR((M26-M25)/(L26-L25),0) -> 0.11457455
A27: ='Monroe (Keys)'!$B$6 -> 1500 Ocean Bay Dr #E5 (Kawama Yacht Club) | B27: 0.3 | C27: ='Monroe (Keys)'!$H$6 -> 760000 | D27: ='Monroe (Keys)'!$I$6 -> 0 | E27: ='Monroe (Keys)'!$K$6 -> 98980 | F27: =C27*(1-B27) -> 532000 | G27: =IF((1-B27)>0.75,Assumptions!$C$11,IF((1-B27)>0.7,Assumptions!$C$12,Assumptions!$C$13)) -> 0.07125 | H27: =PMT(G27/12,Assumptions!$C$14,-F27) -> 3584.1825 | I27: =H27+C27*INDEX(Assumptions!$C$28:$C$34,MATCH('Monroe (Keys)'!$D$6,Assumptions!$B$28:$B$34,0))/12+IF(ISNUMBER('Monroe (Keys)'!$P$6),'Monroe (Keys)'!$P$6,INDEX(Assumptions!$D$28:$D$34,MATCH('Monroe (Keys)'!$D$6,Assumptions!$B$28:$B$34,0))+INDEX(Assumptions!$C$22:$C$25,MATCH('Monroe (Keys)'!$M$6,Assumptions!$B$22:$B$25,0)))/12+'Monroe (Keys)'!$O$6 -> 5635.8492 | J27: =IFERROR(E27/12/I27,0) -> 1.4635476 | K27: =IFERROR(E27*Assumptions!$C$18/12/I27,0) -> 1.170838 | L27: =C27*B27+C27*(Assumptions!$C$16-D27) -> 258400 | M27: =E27-(E27*INDEX(Assumptions!$H$37:$H$38,MATCH('Monroe (Keys)'!$Q$6,Assumptions!$B$37:$B$38,0))+Assumptions!$C$41+IF('Monroe (Keys)'!$N$6="Y",Assumptions!$C$42,Assumptions!$C$43))-I27*12 -> 1384.4095 | N27: =M27-E27*INDEX(Assumptions!$C$37:$C$38,MATCH('Monroe (Keys)'!$Q$6,Assumptions!$B$37:$B$38,0)) -> -18411.591 | O27: =IFERROR(M27/L27,0) -> 0.0053576218 | P27: =IFERROR((M27-M26)/(L27-L26),0) -> 0.096070185

Sheet PropertyRadar
A1: PropertyRadar Pull: Listed Absentee-Owned Homes, Required-Rent Screen
A2: As of 2026-10-19. PropertyRadar has no rental income, so the screen asks: what gross rent does this house need to hit DSCR 1.00 / 1.25 after the lender haircut, at list price and the default down payment? Required gross = PITIA x 12 x target / haircut. Compare to the market benchmark (blue, editable).
A3: Credits | B3: 193 records purchased = 193 credits (1 record = 1 credit, confirmed on a 1-record test: the API's free-record counter fell 10,000 -> 9,999; totalCost reported $0 because purchases draw from the account allowance). Session cap 250, so 57 left in reserve. Counts/previews (Purchase=0) are free. No owner contact add-ons bought.
A4: Criteria | B4: All tiers: active MLS listing (isListedForSale), list price $375k-$650k, PropertyRadar type SFR, 3+ beds (Pinellas: 1,200+ sf instead, because its public record has no bed counts), absentee owner (isSameMailingOrExempt = 0: mailing differs and no homestead), owned 18+ months (no recorded transfer in the last 548 days). Mobile homes flagged and excluded.
A5: T1 Manatee + Sarasota (108) | B5: Manatee beach ZIPs 34205/07/09/10/16/17/28 (13), plus 34203/34221/34243 (24); Sarasota beach list 34231/33/36/39/42/29/75/85/93 (49), plus 34232/34235/34237 (22). Inland Lakewood Ranch/Parrish/North Port ZIPs skipped.
A6: T2 Pinellas (57) | B6: Focus ZIPs 33772/33776/33777/34683/34684/33714 (36), plus Largo/mid-county 33770/33774/33778/33762/33764 and Palm Harbor 34685 (21).
A7: T3 Lee / Charlotte (28) | B7: Cape Coral 33904/33914 with pool and list price <= $550k (24); Fort Myers Beach 33931 + Englewood 34224 (4). 33990/33991/33993 counted only (94 more absentee listings).
A8: Monroe (counts only) | B8: 26 listed SFR 3+ bd $375k-$650k countywide, 9 absentee. Not bought.
A10: Summary pick | B10: Owner type | C10: Mail = property | D10: Exemption? | E10: Last sale | F10: Last sale $ | G10: Loan balance | H10: AVM | I10: Equity % | J10: List price | K10: DOM | L10: Listed | M10: Finding
A11: 8404 43rd Ave Ter W, Bradenton 34209 | B11: Individual (married) | C11: N | D11: Likely | E11: 2023-08-14 | F11: 595000 | G11: 516458 | H11: 532465 | I11: 0.03 | J11: 584900 | K11: 26 | L11: Y | M11: RED FLAGS: exemption flag on a claimed $85k STR (homestead would contradict rental use); ~3% equity. At $560k with a 3% credit and ~5.5% seller costs, seller nets ~$512k vs ~$516k payoff, so they would have to bring cash. Expect pushback; consider ~$570k with a smaller credit.
A12: 5318 17th St W, Bradenton 34207 | B12: LLC/Corp | C12: N | D12: Flag set (corporate, so not homestead) | E12: 2024-04-09 | F12: 420000 | G12: 325183 | H12: 379031 | I12: 0.14 | J12: 475000 | K12: 18 | L12: Y | M12: PropertyRadar types it MFR (supports the duplex story; still confirm legal nonconforming use). $460k offer clears the payoff.
A13: 2801 23rd Ave W, Bradenton 34205 | B13: Individual | C13: N | D13: No (absentee) | E13: 2024-03-04 | F13: 474000 | H13: 430669 | J13: 645000 | K13: 24 | L13: Y | M13: Absentee, consistent with STR use. AVM $431k vs $645k ask: appraisal risk confirmed.
A14: 12565 81st Ave, Seminole 33776 | B14: Individual (multi) | C14: Y | D14: Unknown | E14: 2021-04-16 | F14: 235000 | G14: 287873 | H14: 356997 | I14: 0.19 | J14: 499000 | K14: 29 | L14: Y | M14: Owner mails to the property: may be owner-occupied/homesteaded. Check before trusting 'Airbnb since 2022'. AVM $357k vs $499k ask.
A15: 4000 46th St N, St Petersburg 33714 | B15: Individual (multi) | C15: N | D15: Likely | E15: 2025-02-19 | F15: 330000 | G15: 287578 | H15: 329488 | I15: 0.13 | J15: 500000 | K15: 18 | L15: Y | M15: Bought 2/2025 at $330k; ask $500k and AVM $329k: big appraisal gap. Exemption flag set; confirm homestead status.
A17: SCREEN TARGETS | B17: Value | D17: BENCHMARK GROSS ($/yr) BY MARKET | E17: 3BR no pool | F17: 3BR pool | G17: 4BR+ no pool | H17: 4BR+ pool | I17: Basis
A18: DSCR target (floor) | B18: 1 | D18: Manatee W Bradenton (STR) | E18: 45000 | F18: 58000 | G18: 52000 | H18: 68000 | I18: Analyst estimates anchored to seller-stated incomes already in this workbook (West Bradenton 4BR pool $63-89k; Seminole $71k; Largo $51k; Cape Coral $60k). Sarasota County and Siesta Key rows are 30-day+ seasonal (county 30-day minimum). Overwrite with AirDNA/PriceLabs comps.
A19: DSCR target (preferred) | B19: 1.25 | D19: Manatee inland (STR) | E19: 36000 | F19: 46000 | G19: 42000 | H19: 54000
D20: Sarasota City (7-night) | E20: 42000 | F20: 55000 | G20: 48000 | H20: 62000
D21: Sarasota County (30-day) | E21: 34000 | F21: 46000 | G21: 40000 | H21: 54000
D22: Siesta Key (30-day) | E22: 50000 | F22: 65000 | G22: 58000 | H22: 75000
D23: Pinellas uninc/Largo (STR) | E23: 45000 | F23: 60000 | G23: 52000 | H23: 70000
D24: Cape Coral pool (STR) | E24: 45000 | F24: 55000 | G24: 52000 | H24: 65000
D25: FMB / Englewood | E25: 42000 | F25: 52000 | G25: 48000 | H25: 60000
A27: Address | B27: City / ZIP | C27: County | D27: Market (benchmark) | E27: Type | F27: Beds | G27: Baths | H27: SqFt | I27: Year | J27: List Price | K27: DOM | L27: Last Sale Date | M27: Last Sale Price | N27: Est. Equity | O27: Owner Type | P27: Absentee | Q27: Pool | R27: Flood Zone | S27: Tier | T27: Down % | U27: Loan | V27: Rate | W27: PITIA ($/mo) | X27: Req. Gross DSCR 1.00 ($/yr) | Y27: Req. Gross DSCR 1.25 ($/yr) | Z27: Cash to Close | AA27: Beds (screen) | AB27: Benchmark Gross ($/yr) | AC27: Benchmark / Req. 1.00 | AD27: DSCR Screen | AE27: Notes
A28: 216 SW 29th St | B28: Cape Coral 33914 | C28: Lee | D28: Cape Coral pool (STR) | E28: Single Family Residence | F28: 4 | G28: 2 | H28: 1828 | I28: 2016 | J28: 424900 | K28: 109 | L28: 2022-04-08 | M28: 357000 | N28: 412052 | O28: Individual | P28: N | Q28: Y | R28: X | S28: T3 Cape Coral pool | T28: =Assumptions!$C$15 -> 0.25 | U28: =J28*(1-T28) -> 318675 | V28: =IF((1-T28)>0.75,Assumptions!$C$11,IF((1-T28)>0.7,Assumptions!$C$12,Assumptions!$C$13)) -> 0.0725 | W28: =PMT(V28/12,Assumptions!$C$14,-U28)+J28*INDEX(Assumptions!$C$28:$C$34,MATCH(C28,Assumptions!$B$28:$B$34,0))/12+(INDEX(Assumptions!$D$28:$D$34,MATCH(C28,Assumptions!$B$28:$B$34,0))+INDEX(Assumptions!$C$22:$C$25,MATCH(R28,Assumptions!$B$22:$B$25,0)))/12 -> 3442.5336 | X28: =W28*12*$B$18/Assumptions!$C$18 -> 51638.004 | Y28: =W28*12*$B$19/Assumptions!$C$18 -> 64547.505 | Z28: =J28*(T28+Assumptions!$C$16) -> 123221 | AA28: =IF(ISNUMBER(F28),F28,IF(H28>=2000,4,3)) -> 4 | AB28: =IFERROR(INDEX($E$18:$H$25,MATCH(D28,$D$18:$D$25,0),1+IF(AA28>=4,2,0)+IF(Q28="Y",1,0)),0) -> 65000 | AC28: =IFERROR(AB28/X28,0) -> 1.2587628 | AD28: =IF(ISNUMBER(SEARCH("Mobile",E28)),"EXCLUDED",IF(AB28>=Y28,"PASS",IF(AB28>=X28,"MARGINAL","FAIL"))) -> PASS | AE28: WEB: 4/2 2016 heated saltwater pool, corner lot, zone X, no HOA. Cut from $450k; on/off market since 2025 ($479.9k). No canal or rental claims seen: dry lot likely. Best screen in the pull, but no income history.
A29: 634 SE 32nd St | B29: Cape Coral 33904 | C29: Lee | D29: Cape Coral pool (STR) | E29: Single Family Residence | F29: 4 | G29: 2 | H29: 2051 | I29: 1989 | J29: 429900 | K29: 3 | L29: 2013-02-26 | M29: 134900 | N29: 415242 | O29: Individual | P29: N | Q29: Y | R29: X | S29: T3 Cape Coral pool | T29: =Assumptions!$C$15 -> 0.25 | U29: =J29*(1-T29) -> 322425 | V29: =IF((1-T29)>0.75,Assumptions!$C$11,IF((1-T29)>0.7,Assumptions!$C$12,Assumptions!$C$13)) -> 0.0725 | W29: =PMT(V29/12,Assumptions!$C$14,-U29)+J29*INDEX(Assumptions!$C$28:$C$34,MATCH(C29,Assumptions!$B$28:$B$34,0))/12+(INDEX(Assumptions!$D$28:$D$34,MATCH(C29,Assumptions!$B$28:$B$34,0))+INDEX(Assumptions!$C$22:$C$25,MATCH(R29,Assumptions!$B$22:$B$25,0)))/12 -> 3475.1985 | X29: =W29*12*$B$18/Assumptions!$C$18 -> 52127.978 | Y29: =W29*12*$B$19/Assumptions!$C$18 -> 65159.973 | Z29: =J29*(T29+Assumptions!$C$16) -> 124671 | AA29: =IF(ISNUMBER(F29),F29,IF(H29>=2000,4,3)) -> 4 | AB29: =IFERROR(INDEX($E$18:$H$25,MATCH(D29,$D$18:$D$25,0),1+IF(AA29>=4,2,0)+IF(Q29="Y",1,0)),0) -> 65000 | AC29: =IFERROR(AB29/X29,0) -> 1.2469312 | AD29: =IF(ISNUMBER(SEARCH("Mobile",E29)),"EXCLUDED",IF(AB29>=Y29,"PASS",IF(AB29>=X29,"MARGINAL","FAIL"))) -> MARGINAL | AE29: WEB: currently/recently a long-term rental ($2,700/mo; $3,200 in 2023); same MLS also shows for rent. Metal roof, outside flood zone. No canal, no STR history.
A30: 3010 Hatton St | B30: Sarasota 34237 | C30: Sarasota | D30: Sarasota City (7-night) | E30: Single Family Residence | F30: 3 | G30: 2 | H30: 1657 | I30: 1957 | J30: 375000 | K30: 37 | N30: 371347 | O30: Trust | P30: N | Q30: N | R30: X | S30: T1 Sarasota city | T30: =Assumptions!$C$15 -> 0.25 | U30: =J30*(1-T30) -> 281250 | V30: =IF((1-T30)>0.75,Assumptions!$C$11,IF((1-T30)>0.7,Assumptions!$C$12,Assumptions!$C$13)) -> 0.0725 | W30: =PMT(V30/12,Assumptions!$C$14,-U30)+J30*INDEX(Assumptions!$C$28:$C$34,MATCH(C30,Assumptions!$B$28:$B$34,0))/12+(INDEX(Assumptions!$D$28:$D$34,MATCH(C30,Assumptions!$B$28:$B$34,0))+INDEX(Assumptions!$C$22:$C$25,MATCH(R30,Assumptions!$B$22:$B$25,0)))/12 -> 3007.1625 | X30: =W30*12*$B$18/Assumptions!$C$18 -> 45107.437 | Y30: =W30*12*$B$19/Assumptions!$C$18 -> 56384.296 | Z30: =J30*(T30+Assumptions!$C$16) -> 108750 | AA30: =IF(ISNUMBER(F30),F30,IF(H30>=2000,4,3)) -> 3 | AB30: =IFERROR(INDEX($E$18:$H$25,MATCH(D30,$D$18:$D$25,0),1+IF(AA30>=4,2,0)+IF(Q30="Y",1,0)),0) -> 42000 | AC30: =IFERROR(AB30/X30,0) -> 0.93111032 | AD30: =IF(ISNUMBER(SEARCH("Mobile",E30)),"EXCLUDED",IF(AB30>=Y30,"PASS",IF(AB30>=X30,"MARGINAL","FAIL"))) -> FAIL | AE30: WEB: Opendoor resale; remarks say 'room for a pool', so likely NO pool (PropertyRadar shows pool; set to N). Nearby parcels show City Limits (7-night min). No rental claims.
A31: 209 15th St | B31: Palm Harbor 34683 | C31: Pinellas | D31: Pinellas uninc/Largo (STR) | E31: Single Family Residence | G31: 2 | H31: 2411 | I31: 1976 | J31: 499000 | K31: 104 | L31: 1975-01-01 | M31: 9500 | N31: 520043 | O31: LLC/Corp | P31: N | Q31: Y | R31: X | S31: T2 Pinellas focus | T31: =Assumptions!$C$15 -> 0.25 | U31: =J31*(1-T31) -> 374250 | V31: =IF((1-T31)>0.75,Assumptions!$C$11,IF((1-T31)>0.7,Assumptions!$C$12,Assumptions!$C$13)) -> 0.0725 | W31: =PMT(V31/12,Assumptions!$C$14,-U31)+J31*INDEX(Assumptions!$C$28:$C$34,MATCH(C31,Assumptions!$B$28:$B$34,0))/12+(INDEX(Assumptions!$D$28:$D$34,MATCH(C31,Assumptions!$B$28:$B$34,0))+INDEX(Assumptions!$C$22:$C$25,MATCH(R31,Assumptions!$B$22:$B$25,0)))/12 -> 3885.0447 | X31: =W31*12*$B$18/Assumptions!$C$18 -> 58275.671 | Y31: =W31*12*$B$19/Assumptions!$C$18 -> 72844.589 | Z31: =J31*(T31+Assumptions!$C$16) -> 144710 | AA31: =IF(ISNUMBER(F31),F31,IF(H31>=2000,4,3)) -> 4 | AB31: =IFERROR(INDEX($E$18:$H$25,MATCH(D31,$D$18:$D$25,0),1+IF(AA31>=4,2,0)+IF(Q31="Y",1,0)),0) -> 70000 | AC31: =IFERROR(AB31/X31,0) -> 1.2011874 | AD31: =IF(ISNUMBER(SEARCH("Mobile",E31)),"EXCLUDED",IF(AB31>=Y31,"PASS",IF(AB31>=X31,"MARGINAL","FAIL"))) -> MARGINAL | AE31: Beds not in Pinellas public record; screen assumes 3BR <2,000 sf, 4BR >=2,000 sf. WEB: 3/2 pool, unincorporated Palm Harbor (nightly STR legal w/ Certificate of Use). Cut $555k -> $499k since July. No rental history. Cleanest STR-legal Pinellas pool house in the pull.
A32: 8665 Mockingbird Ln | B32: Seminole 33777 | C32: Pinellas | D32: Pinellas uninc/Largo (STR) | E32: Single Family Residence | G32: 2 | H32: 1970 | I32: 1971 | J32: 424900 | K32: 803 | L32: 1972-01-01 | M32: 18100 | N32: 420474 | O32: Individual | P32: N | Q32: Y | R32: X | S32: T2 Pinellas focus | T32: =Assumptions!$C$15 -> 0.25 | U32: =J32*(1-T32) -> 318675 | V32: =IF((1-T32)>0.75,Assumptions!$C$11,IF((1-T32)>0.7,Assumptions!$C$12,Assumptions!$C$13)) -> 0.0725 | W32: =PMT(V32/12,Assumptions!$C$14,-U32)+J32*INDEX(Assumptions!$C$28:$C$34,MATCH(C32,Assumptions!$B$28:$B$34,0))/12+(INDEX(Assumptions!$D$28:$D$34,MATCH(C32,Assumptions!$B$28:$B$34,0))+INDEX(Assumptions!$C$22:$C$25,MATCH(R32,Assumptions!$B$22:$B$25,0)))/12 -> 3407.1253 | X32: =W32*12*$B$18/Assumptions!$C$18 -> 51106.879 | Y32: =W32*12*$B$19/Assumptions!$C$18 -> 63883.599 | Z32: =J32*(T32+Assumptions!$C$16) -> 123221 | AA32: =IF(ISNUMBER(F32),F32,IF(H32>=2000,4,3)) -> 3 | AB32: =IFERROR(INDEX($E$18:$H$25,MATCH(D32,$D$18:$D$25,0),1+IF(AA32>=4,2,0)+IF(Q32="Y",1,0)),0) -> 60000 | AC32: =IFERROR(AB32/X32,0) -> 1.1740103 | AD32: =IF(ISNUMBER(SEARCH("Mobile",E32)),"EXCLUDED",IF(AB32>=Y32,"PASS",IF(AB32>=X32,"MARGINAL","FAIL"))) -> MARGINAL | AE32: Beds not in Pinellas public record; screen assumes 3BR <2,000 sf, 4BR >=2,000 sf. WEB: 3/2 fixer, sold as-is, ~830 DOM (same MLS since 2024), last seen $429.9k. Homestead taxes $1.2k will reset. Likely unincorporated (Bardmoor).
A33: 4207 21st Ave W | B33: Bradenton 34205 | C33: Manatee | D33: Manatee W Bradenton (STR) | E33: Single Family Residence | F33: 3 | G33: 2 | H33: 1796 | I33: 1973 | J33: 424900 | K33: 82 | L33: 2017-03-22 | M33: 290000 | N33: 415182 | O33: Trust | P33: N | Q33: Y | R33: X | S33: T1 Manatee beach | T33: =Assumptions!$C$15 -> 0.25 | U33: =J33*(1-T33) -> 318675 | V33: =IF((1-T33)>0.75,Assumptions!$C$11,IF((1-T33)>0.7,Assumptions!$C$12,Assumptions!$C$13)) -> 0.0725 | W33: =PMT(V33/12,Assumptions!$C$14,-U33)+J33*INDEX(Assumptions!$C$28:$C$34,MATCH(C33,Assumptions!$B$28:$B$34,0))/12+(INDEX(Assumptions!$D$28:$D$34,MATCH(C33,Assumptions!$B$28:$B$34,0))+INDEX(Assumptions!$C$22:$C$25,MATCH(R33,Assumptions!$B$22:$B$25,0)))/12 -> 3371.7169 | X33: =W33*12*$B$18/Assumptions!$C$18 -> 50575.754 | Y33: =W33*12*$B$19/Assumptions!$C$18 -> 63219.692 | Z33: =J33*(T33+Assumptions!$C$16) -> 123221 | AA33: =IF(ISNUMBER(F33),F33,IF(H33>=2000,4,3)) -> 3 | AB33: =IFERROR(INDEX($E$18:$H$25,MATCH(D33,$D$18:$D$25,0),1+IF(AA33>=4,2,0)+IF(Q33="Y",1,0)),0) -> 58000 | AC33: =IFERROR(AB33/X33,0) -> 1.1467946 | AD33: =IF(ISNUMBER(SEARCH("Mobile",E33)),"EXCLUDED",IF(AB33>=Y33,"PASS",IF(AB33>=X33,"MARGINAL","FAIL"))) -> MARGINAL | AE33: WEB: REO/foreclosure resale (Feb 2026 auction). Zoning R1B suggests City of Bradenton (certificate required). One site shows a cut to $374.9k. No rental history.
A34: 11440 130th Ave | B34: Largo 33778 | C34: Pinellas | D34: Pinellas uninc/Largo (STR) | E34: Single Family Residence | G34: 2 | H34: 1446 | I34: 1972 | J34: 450000 | K34: 174 | L34: 2012-10-19 | M34: 135000 | N34: 391862 | O34: Individual (married) | P34: N | Q34: Y | R34: X | S34: T2 Pinellas Largo/mid | T34: =Assumptions!$C$15 -> 0.25 | U34: =J34*(1-T34) -> 337500 | V34: =IF((1-T34)>0.75,Assumptions!$C$11,IF((1-T34)>0.7,Assumptions!$C$12,Assumptions!$C$13)) -> 0.0725 | W34: =PMT(V34/12,Assumptions!$C$14,-U34)+J34*INDEX(Assumptions!$C$28:$C$34,MATCH(C34,Assumptions!$B$28:$B$34,0))/12+(INDEX(Assumptions!$D$28:$D$34,MATCH(C34,Assumptions!$B$28:$B$34,0))+INDEX(Assumptions!$C$22:$C$25,MATCH(R34,Assumptions!$B$22:$B$25,0)))/12 -> 3569.0116 | X34: =W34*12*$B$18/Assumptions!$C$18 -> 53535.174 | Y34: =W34*12*$B$19/Assumptions!$C$18 -> 66918.968 | Z34: =J34*(T34+Assumptions!$C$16) -> 130500 | AA34: =IF(ISNUMBER(F34),F34,IF(H34>=2000,4,3)) -> 3 | AB34: =IFERROR(INDEX($E$18:$H$25,MATCH(D34,$D$18:$D$25,0),1+IF(AA34>=4,2,0)+IF(Q34="Y",1,0)),0) -> 60000 | AC34: =IFERROR(AB34/X34,0) -> 1.1207585 | AD34: =IF(ISNUMBER(SEARCH("Mobile",E34)),"EXCLUDED",IF(AB34>=Y34,"PASS",IF(AB34>=X34,"MARGINAL","FAIL"))) -> MARGINAL | AE34: Beds not in Pinellas public record; screen assumes 3BR <2,000 sf, 4BR >=2,000 sf. WEB: 3/2, cut $494.7k -> $450k; pool unconfirmed. Jurisdiction (uninc vs City of Largo) unconfirmed; STR legal either way.
A35: 1115 SE 30th Ter | B35: Cape Coral 33904 | C35: Lee | D35: Cape Coral pool (STR) | E35: Single Family Residence | F35: 3 | G35: 3 | H35: 1659 | I35: 1983 | J35: 399900 | K35: 26 | N35: 452024 | O35: LLC/Corp | P35: N | Q35: Y | R35: X | S35: T3 Cape Coral pool | T35: =Assumptions!$C$15 -> 0.25 | U35: =J35*(1-T35) -> 299925 | V35: =IF((1-T35)>0.75,Assumptions!$C$11,IF((1-T35)>0.7,Assumptions!$C$12,Assumptions!$C$13)) -> 0.0725 | W35: =PMT(V35/12,Assumptions!$C$14,-U35)+J35*INDEX(Assumptions!$C$28:$C$34,MATCH(C35,Assumptions!$B$28:$B$34,0))/12+(INDEX(Assumptions!$D$28:$D$34,MATCH(C35,Assumptions!$B$28:$B$34,0))+INDEX(Assumptions!$C$22:$C$25,MATCH(R35,Assumptions!$B$22:$B$25,0)))/12 -> 3279.2089 | X35: =W35*12*$B$18/Assumptions!$C$18 -> 49188.133 | Y35: =W35*12*$B$19/Assumptions!$C$18 -> 61485.166 | Z35: =J35*(T35+Assumptions!$C$16) -> 115971 | AA35: =IF(ISNUMBER(F35),F35,IF(H35>=2000,4,3)) -> 3 | AB35: =IFERROR(INDEX($E$18:$H$25,MATCH(D35,$D$18:$D$25,0),1+IF(AA35>=4,2,0)+IF(Q35="Y",1,0)),0) -> 55000 | AC35: =IFERROR(AB35/X35,0) -> 1.1181559 | AD35: =IF(ISNUMBER(SEARCH("Mobile",E35)),"EXCLUDED",IF(AB35>=Y35,"PASS",IF(AB35>=X35,"MARGINAL","FAIL"))) -> MARGINAL | AE35: WEB: renovated, triple lot, city assessments paid, zone X; tenant-occupied long-term rental (sale subject to lease). Bought 3/2024 for $389k. No canal.
A36: 930 SW 37th Ter | B36: Cape Coral 33914 | C36: Lee | D36: Cape Coral pool (STR) | E36: Single Family Residence | F36: 3 | G36: 2 | H36: 1818 | I36: 2008 | J36: 400000 | K36: 407 | L36: 2011-02-24 | M36: 172500 | N36: 395026 | O36: Individual (married) | P36: N | Q36: Y | R36: X | S36: T3 Cape Coral pool | T36: =Assumptions!$C$15 -> 0.25 | U36: =J36*(1-T36) -> 300000 | V36: =IF((1-T36)>0.75,Assumptions!$C$11,IF((1-T36)>0.7,Assumptions!$C$12,Assumptions!$C$13)) -> 0.0725 | W36: =PMT(V36/12,Assumptions!$C$14,-U36)+J36*INDEX(Assumptions!$C$28:$C$34,MATCH(C36,Assumptions!$B$28:$B$34,0))/12+(INDEX(Assumptions!$D$28:$D$34,MATCH(C36,Assumptions!$B$28:$B$34,0))+INDEX(Assumptions!$C$22:$C$25,MATCH(R36,Assumptions!$B$22:$B$25,0)))/12 -> 3279.8622 | X36: =W36*12*$B$18/Assumptions!$C$18 -> 49197.933 | Y36: =W36*12*$B$19/Assumptions!$C$18 -> 61497.416 | Z36: =J36*(T36+Assumptions!$C$16) -> 116000 | AA36: =IF(ISNUMBER(F36),F36,IF(H36>=2000,4,3)) -> 3 | AB36: =IFERROR(INDEX($E$18:$H$25,MATCH(D36,$D$18:$D$25,0),1+IF(AA36>=4,2,0)+IF(Q36="Y",1,0)),0) -> 55000 | AC36: =IFERROR(AB36/X36,0) -> 1.1179332 | AD36: =IF(ISNUMBER(SEARCH("Mobile",E36)),"EXCLUDED",IF(AB36>=Y36,"PASS",IF(AB36>=X36,"MARGINAL","FAIL"))) -> MARGINAL | AE36: WEB: 2024 remarks said 'successful vacation rental'; address is on the FL DBPR vacation-rental license list. No $ figures. Sold 10/2024 $390k; ~400 DOM at $400k. Ask for payouts. Added to SWFL watch list.
A37: 2225 Jaffa Pl | B37: Clearwater 33764 | C37: Pinellas | D37: Pinellas uninc/Largo (STR) | E37: Single Family Residence | G37: 2 | H37: 2320 | I37: 1971 | J37: 545000 | K37: 26 | L37: 2007-03-13 | M37: 335000 | N37: 562331 | O37: Individual | P37: N | Q37: Y | R37: X | S37: T2 Pinellas Largo/mid | T37: =Assumptions!$C$15 -> 0.25 | U37: =J37*(1-T37) -> 408750 | V37: =IF((1-T37)>0.75,Assumptions!$C$11,IF((1-T37)>0.7,Assumptions!$C$12,Assumptions!$C$13)) -> 0.0725 | W37: =PMT(V37/12,Assumptions!$C$14,-U37)+J37*INDEX(Assumptions!$C$28:$C$34,MATCH(C37,Assumptions!$B$28:$B$34,0))/12+(INDEX(Assumptions!$D$28:$D$34,MATCH(C37,Assumptions!$B$28:$B$34,0))+INDEX(Assumptions!$C$22:$C$25,MATCH(R37,Assumptions!$B$22:$B$25,0)))/12 -> 4181.7289 | X37: =W37*12*$B$18/Assumptions!$C$18 -> 62725.933 | Y37: =W37*12*$B$19/Assumptions!$C$18 -> 78407.416 | Z37: =J37*(T37+Assumptions!$C$16) -> 158050 | AA37: =IF(ISNUMBER(F37),F37,IF(H37>=2000,4,3)) -> 4 | AB37: =IFERROR(INDEX($E$18:$H$25,MATCH(D37,$D$18:$D$25,0),1+IF(AA37>=4,2,0)+IF(Q37="Y",1,0)),0) -> 70000 | AC37: =IFERROR(AB37/X37,0) -> 1.1159659 | AD37: =IF(ISNUMBER(SEARCH("Mobile",E37)),"EXCLUDED",IF(AB37>=Y37,"PASS",IF(AB37>=X37,"MARGINAL","FAIL"))) -> MARGINAL | AE37: Beds not in Pinellas public record; screen assumes 3BR <2,000 sf, 4BR >=2,000 sf. WEB: 3/2 pool, HOA ~$60, Grovewood. If inside Clearwater city limits, 30-day minimum kills nightly STR: check PCPAO tax district.
A38: 3141 N Canal Dr | B38: Palm Harbor 34684 | C38: Pinellas | D38: Pinellas uninc/Largo (STR) | E38: Single Family Residence | G38: 2 | H38: 1456 | I38: 1984 | J38: 475000 | K38: 103 | L38: 2006-05-02 | M38: 404000 | N38: 328744 | O38: LLC/Corp | P38: N | Q38: Y | R38: X | S38: T2 Pinellas focus | T38: =Assumptions!$C$15 -> 0.25 | U38: =J38*(1-T38) -> 356250 | V38: =IF((1-T38)>0.75,Assumptions!$C$11,IF((1-T38)>0.7,Assumptions!$C$12,Assumptions!$C$13)) -> 0.0725 | W38: =PMT(V38/12,Assumptions!$C$14,-U38)+J38*INDEX(Assumptions!$C$28:$C$34,MATCH(C38,Assumptions!$B$28:$B$34,0))/12+(INDEX(Assumptions!$D$28:$D$34,MATCH(C38,Assumptions!$B$28:$B$34,0))+INDEX(Assumptions!$C$22:$C$25,MATCH(R38,Assumptions!$B$22:$B$25,0)))/12 -> 3730.253 | X38: =W38*12*$B$18/Assumptions!$C$18 -> 55953.795 | Y38: =W38*12*$B$19/Assumptions!$C$18 -> 69942.244 | Z38: =J38*(T38+Assumptions!$C$16) -> 137750 | AA38: =IF(ISNUMBER(F38),F38,IF(H38>=2000,4,3)) -> 3 | AB38: =IFERROR(INDEX($E$18:$H$25,MATCH(D38,$D$18:$D$25,0),1+IF(AA38>=4,2,0)+IF(Q38="Y",1,0)),0) -> 60000 | AC38: =IFERROR(AB38/X38,0) -> 1.0723133 | AD38: =IF(ISNUMBER(SEARCH("Mobile",E38)),"EXCLUDED",IF(AB38>=Y38,"PASS",IF(AB38>=X38,"MARGINAL","FAIL"))) -> MARGINAL | AE38: Beds not in Pinellas public record; screen assumes 3BR <2,000 sf, 4BR >=2,000 sf.
A39: 10293 Satsuma Rd | B39: Seminole 33772 | C39: Pinellas | D39: Pinellas uninc/Largo (STR) | E39: Single Family Residence | G39: 2 | H39: 1596 | I39: 1961 | J39: 475300 | K39: 51 | L39: 2021-10-11 | M39: 403500 | N39: 447712 | O39: LLC/Corp | P39: N | Q39: Y | R39: X | S39: T2 Pinellas focus | T39: =Assumptions!$C$15 -> 0.25 | U39: =J39*(1-T39) -> 356475 | V39: =IF((1-T39)>0.75,Assumptions!$C$11,IF((1-T39)>0.7,Assumptions!$C$12,Assumptions!$C$13)) -> 0.0725 | W39: =PMT(V39/12,Assumptions!$C$14,-U39)+J39*INDEX(Assumptions!$C$28:$C$34,MATCH(C39,Assumptions!$B$28:$B$34,0))/12+(INDEX(Assumptions!$D$28:$D$34,MATCH(C39,Assumptions!$B$28:$B$34,0))+INDEX(Assumptions!$C$22:$C$25,MATCH(R39,Assumptions!$B$22:$B$25,0)))/12 -> 3732.1879 | X39: =W39*12*$B$18/Assumptions!$C$18 -> 55982.818 | Y39: =W39*12*$B$19/Assumptions!$C$18 -> 69978.523 | Z39: =J39*(T39+Assumptions!$C$16) -> 137837 | AA39: =IF(ISNUMBER(F39),F39,IF(H39>=2000,4,3)) -> 3 | AB39: =IFERROR(INDEX($E$18:$H$25,MATCH(D39,$D$18:$D$25,0),1+IF(AA39>=4,2,0)+IF(Q39="Y",1,0)),0) -> 60000 | AC39: =IFERROR(AB39/X39,0) -> 1.0717574 | AD39: =IF(ISNUMBER(SEARCH("Mobile",E39)),"EXCLUDED",IF(AB39>=Y39,"PASS",IF(AB39>=X39,"MARGINAL","FAIL"))) -> MARGINAL | AE39: Beds not in Pinellas public record; screen assumes 3BR <2,000 sf, 4BR >=2,000 sf. WEB: 3/2 pool, former long-term rental at $2,750/mo (LLC owner). City of Seminole vs unincorporated unconfirmed.
A40: 14883 Seminole Trl # 130 | B40: Seminole 33776 | C40: Pinellas | D40: Pinellas uninc/Largo (STR) | E40: PUD | H40: 2174 | I40: 1999 | J40: 399900 | K40: 102 | L40: 2010-12-22 | M40: 215000 | N40: 415036 | O40: Trust | P40: N | Q40: N | R40: X | S40: T2 Pinellas focus | T40: =Assumptions!$C$15 -> 0.25 | U40: =J40*(1-T40) -> 299925 | V40: =IF((1-T40)>0.75,Assumptions!$C$11,IF((1-T40)>0.7,Assumptions!$C$12,Assumptions!$C$13)) -> 0.0725 | W40: =PMT(V40/12,Assumptions!$C$14,-U40)+J40*INDEX(Assumptions!$C$28:$C$34,MATCH(C40,Assumptions!$B$28:$B$34,0))/12+(INDEX(Assumptions!$D$28:$D$34,MATCH(C40,Assumptions!$B$28:$B$34,0))+INDEX(Assumptions!$C$22:$C$25,MATCH(R40,Assumptions!$B$22:$B$25,0)))/12 -> 3245.8839 | X40: =W40*12*$B$18/Assumptions!$C$18 -> 48688.258 | Y40: =W40*12*$B$19/Assumptions!$C$18 -> 60860.323 | Z40: =J40*(T40+Assumptions!$C$16) -> 115971 | AA40: =IF(ISNUMBER(F40),F40,IF(H40>=2000,4,3)) -> 4 | AB40: =IFERROR(INDEX($E$18:$H$25,MATCH(D40,$D$18:$D$25,0),1+IF(AA40>=4,2,0)+IF(Q40="Y",1,0)),0) -> 52000 | AC40: =IFERROR(AB40/X40,0) -> 1.0680193 | AD40: =IF(ISNUMBER(SEARCH("Mobile",E40)),"EXCLUDED",IF(AB40>=Y40,"PASS",IF(AB40>=X40,"MARGINAL","FAIL"))) -> MARGINAL | AE40: Beds not in Pinellas public record; screen assumes 3BR <2,000 sf, 4BR >=2,000 sf.
A41: 1039 Madison St | B41: Largo 33770 | C41: Pinellas | D41: Pinellas uninc/Largo (STR) | E41: Single Family Residence | G41: 2 | H41: 1600 | I41: 1958 | J41: 478000 | K41: 6 | L41: 1975-01-01 | M41: 35000 | N41: 342910 | O41: Trust | P41: N | Q41: Y | R41: X | S41: T2 Pinellas Largo/mid | T41: =Assumptions!$C$15 -> 0.25 | U41: =J41*(1-T41) -> 358500 | V41: =IF((1-T41)>0.75,Assumptions!$C$11,IF((1-T41)>0.7,Assumptions!$C$12,Assumptions!$C$13)) -> 0.0725 | W41: =PMT(V41/12,Assumptions!$C$14,-U41)+J41*INDEX(Assumptions!$C$28:$C$34,MATCH(C41,Assumptions!$B$28:$B$34,0))/12+(INDEX(Assumptions!$D$28:$D$34,MATCH(C41,Assumptions!$B$28:$B$34,0))+INDEX(Assumptions!$C$22:$C$25,MATCH(R41,Assumptions!$B$22:$B$25,0)))/12 -> 3749.602 | X41: =W41*12*$B$18/Assumptions!$C$18 -> 56244.029 | Y41: =W41*12*$B$19/Assumptions!$C$18 -> 70305.037 | Z41: =J41*(T41+Assumptions!$C$16) -> 138620 | AA41: =IF(ISNUMBER(F41),F41,IF(H41>=2000,4,3)) -> 3 | AB41: =IFERROR(INDEX($E$18:$H$25,MATCH(D41,$D$18:$D$25,0),1+IF(AA41>=4,2,0)+IF(Q41="Y",1,0)),0) -> 60000 | AC41: =IFERROR(AB41/X41,0) -> 1.0667799 | AD41: =IF(ISNUMBER(SEARCH("Mobile",E41)),"EXCLUDED",IF(AB41>=Y41,"PASS",IF(AB41>=X41,"MARGINAL","FAIL"))) -> MARGINAL | AE41: Beds not in Pinellas public record; screen assumes 3BR <2,000 sf, 4BR >=2,000 sf. WEB: actually 2/2 (not 3BR), pool + tiki hut; advertised as a long-term rental at $2,950/mo. 2BR fails the 3+ bed brief.
A42: 5535 Bates St | B42: Seminole 33772 | C42: Pinellas | D42: Pinellas uninc/Largo (STR) | E42: Single Family Residence | G42: 3 | H42: 2624 | I42: 1990 | J42: 574900 | K42: 54 | L42: 1997-12-17 | M42: 209000 | N42: 700711 | O42: LLC/Corp | P42: N | Q42: Y | R42: X | S42: T2 Pinellas focus | T42: =Assumptions!$C$15 -> 0.25 | U42: =J42*(1-T42) -> 431175 | V42: =IF((1-T42)>0.75,Assumptions!$C$11,IF((1-T42)>0.7,Assumptions!$C$12,Assumptions!$C$13)) -> 0.0725 | W42: =PMT(V42/12,Assumptions!$C$14,-U42)+J42*INDEX(Assumptions!$C$28:$C$34,MATCH(C42,Assumptions!$B$28:$B$34,0))/12+(INDEX(Assumptions!$D$28:$D$34,MATCH(C42,Assumptions!$B$28:$B$34,0))+INDEX(Assumptions!$C$22:$C$25,MATCH(R42,Assumptions!$B$22:$B$25,0)))/12 -> 4374.5736 | X42: =W42*12*$B$18/Assumptions!$C$18 -> 65618.604 | Y42: =W42*12*$B$19/Assumptions!$C$18 -> 82023.255 | Z42: =J42*(T42+Assumptions!$C$16) -> 166721 | AA42: =IF(ISNUMBER(F42),F42,IF(H42>=2000,4,3)) -> 4 | AB42: =IFERROR(INDEX($E$18:$H$25,MATCH(D42,$D$18:$D$25,0),1+IF(AA42>=4,2,0)+IF(Q42="Y",1,0)),0) -> 70000 | AC42: =IFERROR(AB42/X42,0) -> 1.0667706 | AD42: =IF(ISNUMBER(SEARCH("Mobile",E42)),"EXCLUDED",IF(AB42>=Y42,"PASS",IF(AB42>=X42,"MARGINAL","FAIL"))) -> MARGINAL | AE42: Beds not in Pinellas public record; screen assumes 3BR <2,000 sf, 4BR >=2,000 sf. WEB: 3/2.5, 2,624 sf; cut $649.9k -> $574.9k; institutional SFR owner (past LTR). Likely unincorporated (R-3). Pool vs spa unconfirmed.
A43: 310 SE 47th St | B43: Cape Coral 33904 | C43: Lee | D43: Cape Coral pool (STR) | E43: Single Family Residence | F43: 3 | G43: 2 | H43: 1427 | I43: 2003 | J43: 385000 | K43: 250 | L43: 2022-02-02 | M43: 430000 | N43: 104519 | O43: Individual | P43: N | Q43: Y | R43: AE | S43: T3 Cape Coral pool | T43: =Assumptions!$C$15 -> 0.25 | U43: =J43*(1-T43) -> 288750 | V43: =IF((1-T43)>0.75,Assumptions!$C$11,IF((1-T43)>0.7,Assumptions!$C$12,Assumptions!$C$13)) -> 0.0725 | W43: =PMT(V43/12,Assumptions!$C$14,-U43)+J43*INDEX(Assumptions!$C$28:$C$34,MATCH(C43,Assumptions!$B$28:$B$34,0))/12+(INDEX(Assumptions!$D$28:$D$34,MATCH(C43,Assumptions!$B$28:$B$34,0))+INDEX(Assumptions!$C$22:$C$25,MATCH(R43,Assumptions!$B$22:$B$25,0)))/12 -> 3473.534 | X43: =W43*12*$B$18/Assumptions!$C$18 -> 52103.01 | Y43: =W43*12*$B$19/Assumptions!$C$18 -> 65128.763 | Z43: =J43*(T43+Assumptions!$C$16) -> 111650 | AA43: =IF(ISNUMBER(F43),F43,IF(H43>=2000,4,3)) -> 3 | AB43: =IFERROR(INDEX($E$18:$H$25,MATCH(D43,$D$18:$D$25,0),1+IF(AA43>=4,2,0)+IF(Q43="Y",1,0)),0) -> 55000 | AC43: =IFERROR(AB43/X43,0) -> 1.0556012 | AD43: =IF(ISNUMBER(SEARCH("Mobile",E43)),"EXCLUDED",IF(AB43>=Y43,"PASS",IF(AB43>=X43,"MARGINAL","FAIL"))) -> MARGINAL
A44: 1432 SE 29th Ter | B44: Cape Coral 33904 | C44: Lee | D44: Cape Coral pool (STR) | E44: Single Family Residence | F44: 3 | G44: 2 | H44: 2269 | I44: 2005 | J44: 430000 | K44: 51 | L44: 2010-12-20 | M44: 203000 | N44: 536273 | O44: Individual | P44: N | Q44: Y | R44: X | S44: T3 Cape Coral pool | T44: =Assumptions!$C$15 -> 0.25 | U44: =J44*(1-T44) -> 322500 | V44: =IF((1-T44)>0.75,Assumptions!$C$11,IF((1-T44)>0.7,Assumptions!$C$12,Assumptions!$C$13)) -> 0.0725 | W44: =PMT(V44/12,Assumptions!$C$14,-U44)+J44*INDEX(Assumptions!$C$28:$C$34,MATCH(C44,Assumptions!$B$28:$B$34,0))/12+(INDEX(Assumptions!$D$28:$D$34,MATCH(C44,Assumptions!$B$28:$B$34,0))+INDEX(Assumptions!$C$22:$C$25,MATCH(R44,Assumptions!$B$22:$B$25,0)))/12 -> 3475.8518 | X44: =W44*12*$B$18/Assumptions!$C$18 -> 52137.778 | Y44: =W44*12*$B$19/Assumptions!$C$18 -> 65172.222 | Z44: =J44*(T44+Assumptions!$C$16) -> 124700 | AA44: =IF(ISNUMBER(F44),F44,IF(H44>=2000,4,3)) -> 3 | AB44: =IFERROR(INDEX($E$18:$H$25,MATCH(D44,$D$18:$D$25,0),1+IF(AA44>=4,2,0)+IF(Q44="Y",1,0)),0) -> 55000 | AC44: =IFERROR(AB44/X44,0) -> 1.0548973 | AD44: =IF(ISNUMBER(SEARCH("Mobile",E44)),"EXCLUDED",IF(AB44>=Y44,"PASS",IF(AB44>=X44,"MARGINAL","FAIL"))) -> MARGINAL
A45: 3318 SW 8th Pl | B45: Cape Coral 33914 | C45: Lee | D45: Cape Coral pool (STR) | E45: Single Family Residence | F45: 4 | G45: 2 | H45: 1870 | I45: 2022 | J45: 529000 | K45: 289 | L45: 2023-06-01 | M45: 610000 | N45: 85159 | O45: LLC/Corp | P45: N | Q45: Y | R45: X | S45: T3 Cape Coral pool | T45: =Assumptions!$C$15 -> 0.25 | U45: =J45*(1-T45) -> 396750 | V45: =IF((1-T45)>0.75,Assumptions!$C$11,IF((1-T45)>0.7,Assumptions!$C$12,Assumptions!$C$13)) -> 0.0725 | W45: =PMT(V45/12,Assumptions!$C$14,-U45)+J45*INDEX(Assumptions!$C$28:$C$34,MATCH(C45,Assumptions!$B$28:$B$34,0))/12+(INDEX(Assumptions!$D$28:$D$34,MATCH(C45,Assumptions!$B$28:$B$34,0))+INDEX(Assumptions!$C$22:$C$25,MATCH(R45,Assumptions!$B$22:$B$25,0)))/12 -> 4122.6177 | X45: =W45*12*$B$18/Assumptions!$C$18 -> 61839.266 | Y45: =W45*12*$B$19/Assumptions!$C$18 -> 77299.082 | Z45: =J45*(T45+Assumptions!$C$16) -> 153410 | AA45: =IF(ISNUMBER(F45),F45,IF(H45>=2000,4,3)) -> 4 | AB45: =IFERROR(INDEX($E$18:$H$25,MATCH(D45,$D$18:$D$25,0),1+IF(AA45>=4,2,0)+IF(Q45="Y",1,0)),0) -> 65000 | AC45: =IFERROR(AB45/X45,0) -> 1.0511121 | AD45: =IF(ISNUMBER(SEARCH("Mobile",E45)),"EXCLUDED",IF(AB45>=Y45,"PASS",IF(AB45>=X45,"MARGINAL","FAIL"))) -> MARGINAL
A46: 1538 SW 49th St | B46: Cape Coral 33914 | C46: Lee | D46: Cape Coral pool (STR) | E46: Single Family Residence | F46: 3 | G46: 2 | H46: 1556 | I46: 1987 | J46: 389000 | K46: 56 | L46: 2016-09-26 | M46: 250000 | N46: 237547 | O46: Individual | P46: N | Q46: Y | R46: AE | S46: T3 Cape Coral pool | T46: =Assumptions!$C$15 -> 0.25 | U46: =J46*(1-T46) -> 291750 | V46: =IF((1-T46)>0.75,Assumptions!$C$11,IF((1-T46)>0.7,Assumptions!$C$12,Assumptions!$C$13)) -> 0.0725 | W46: =PMT(V46/12,Assumptions!$C$14,-U46)+J46*INDEX(Assumptions!$C$28:$C$34,MATCH(C46,Assumptions!$B$28:$B$34,0))/12+(INDEX(Assumptions!$D$28:$D$34,MATCH(C46,Assumptions!$B$28:$B$34,0))+INDEX(Assumptions!$C$22:$C$25,MATCH(R46,Assumptions!$B$22:$B$25,0)))/12 -> 3499.666 | X46: =W46*12*$B$18/Assumptions!$C$18 -> 52494.989 | Y46: =W46*12*$B$19/Assumptions!$C$18 -> 65618.737 | Z46: =J46*(T46+Assumptions!$C$16) -> 112810 | AA46: =IF(ISNUMBER(F46),F46,IF(H46>=2000,4,3)) -> 3 | AB46: =IFERROR(INDEX($E$18:$H$25,MATCH(D46,$D$18:$D$25,0),1+IF(AA46>=4,2,0)+IF(Q46="Y",1,0)),0) -> 55000 | AC46: =IFERROR(AB46/X46,0) -> 1.047719 | AD46: =IF(ISNUMBER(SEARCH("Mobile",E46)),"EXCLUDED",IF(AB46>=Y46,"PASS",IF(AB46>=X46,"MARGINAL","FAIL"))) -> MARGINAL
A47: 2090 Sandpiper Dr | B47: Palm Harbor 34683 | C47: Pinellas | D47: Pinellas uninc/Largo (STR) | E47: Single Family Residence | G47: 2 | H47: 1664 | I47: 1987 | J47: 489000 | K47: 30 | L47: 2005-05-24 | M47: 263000 | N47: 389696 | O47: Individual (married) | P47: N | Q47: Y | R47: X | S47: T2 Pinellas focus | T47: =Assumptions!$C$15 -> 0.25 | U47: =J47*(1-T47) -> 366750 | V47: =IF((1-T47)>0.75,Assumptions!$C$11,IF((1-T47)>0.7,Assumptions!$C$12,Assumptions!$C$13)) -> 0.0725 | W47: =PMT(V47/12,Assumptions!$C$14,-U47)+J47*INDEX(Assumptions!$C$28:$C$34,MATCH(C47,Assumptions!$B$28:$B$34,0))/12+(INDEX(Assumptions!$D$28:$D$34,MATCH(C47,Assumptions!$B$28:$B$34,0))+INDEX(Assumptions!$C$22:$C$25,MATCH(R47,Assumptions!$B$22:$B$25,0)))/12 -> 3820.5482 | X47: =W47*12*$B$18/Assumptions!$C$18 -> 57308.223 | Y47: =W47*12*$B$19/Assumptions!$C$18 -> 71635.278 | Z47: =J47*(T47+Assumptions!$C$16) -> 141810 | AA47: =IF(ISNUMBER(F47),F47,IF(H47>=2000,4,3)) -> 3 | AB47: =IFERROR(INDEX($E$18:$H$25,MATCH(D47,$D$18:$D$25,0),1+IF(AA47>=4,2,0)+IF(Q47="Y",1,0)),0) -> 60000 | AC47: =IFERROR(AB47/X47,0) -> 1.0469702 | AD47: =IF(ISNUMBER(SEARCH("Mobile",E47)),"EXCLUDED",IF(AB47>=Y47,"PASS",IF(AB47>=X47,"MARGINAL","FAIL"))) -> MARGINAL | AE47: Beds not in Pinellas public record; screen assumes 3BR <2,000 sf, 4BR >=2,000 sf.
A48: 2006 8th Ave SW | B48: Largo 33770 | C48: Pinellas | D48: Pinellas uninc/Largo (STR) | E48: Single Family Residence | G48: 3 | H48: 1792 | I48: 1956 | J48: 489900 | K48: 11 | L48: 2016-02-18 | M48: 213500 | N48: 402862 | O48: Individual (married) | P48: N | Q48: Y | R48: X | S48: T2 Pinellas Largo/mid | T48: =Assumptions!$C$15 -> 0.25 | U48: =J48*(1-T48) -> 367425 | V48: =IF((1-T48)>0.75,Assumptions!$C$11,IF((1-T48)>0.7,Assumptions!$C$12,Assumptions!$C$13)) -> 0.0725 | W48: =PMT(V48/12,Assumptions!$C$14,-U48)+J48*INDEX(Assumptions!$C$28:$C$34,MATCH(C48,Assumptions!$B$28:$B$34,0))/12+(INDEX(Assumptions!$D$28:$D$34,MATCH(C48,Assumptions!$B$28:$B$34,0))+INDEX(Assumptions!$C$22:$C$25,MATCH(R48,Assumptions!$B$22:$B$25,0)))/12 -> 3826.3529 | X48: =W48*12*$B$18/Assumptions!$C$18 -> 57395.293 | Y48: =W48*12*$B$19/Assumptions!$C$18 -> 71744.116 | Z48: =J48*(T48+Assumptions!$C$16) -> 142071 | AA48: =IF(ISNUMBER(F48),F48,IF(H48>=2000,4,3)) -> 3 | AB48: =IFERROR(INDEX($E$18:$H$25,MATCH(D48,$D$18:$D$25,0),1+IF(AA48>=4,2,0)+IF(Q48="Y",1,0)),0) -> 60000 | AC48: =IFERROR(AB48/X48,0) -> 1.0453819 | AD48: =IF(ISNUMBER(SEARCH("Mobile",E48)),"EXCLUDED",IF(AB48>=Y48,"PASS",IF(AB48>=X48,"MARGINAL","FAIL"))) -> MARGINAL | AE48: Beds not in Pinellas public record; screen assumes 3BR <2,000 sf, 4BR >=2,000 sf. WEB: remodeled 4/3 pool, new roof; cut from $575k. Likely City of Largo (STR allowed). No rental history.
A49: 2228 SW 26th Ter | B49: Cape Coral 33914 | C49: Lee | D49: Cape Coral pool (STR) | E49: Single Family Residence | F49: 4 | G49: 3 | H49: 2118 | I49: 2007 | J49: 499000 | K49: 164 | L49: 2019-08-09 | M49: 300000 | N49: 221031 | O49: Individual (married) | P49: N | Q49: Y | R49: AE | S49: T3 Cape Coral pool | T49: =Assumptions!$C$15 -> 0.25 | U49: =J49*(1-T49) -> 374250 | V49: =IF((1-T49)>0.75,Assumptions!$C$11,IF((1-T49)>0.7,Assumptions!$C$12,Assumptions!$C$13)) -> 0.0725 | W49: =PMT(V49/12,Assumptions!$C$14,-U49)+J49*INDEX(Assumptions!$C$28:$C$34,MATCH(C49,Assumptions!$B$28:$B$34,0))/12+(INDEX(Assumptions!$D$28:$D$34,MATCH(C49,Assumptions!$B$28:$B$34,0))+INDEX(Assumptions!$C$22:$C$25,MATCH(R49,Assumptions!$B$22:$B$25,0)))/12 -> 4218.2947 | X49: =W49*12*$B$18/Assumptions!$C$18 -> 63274.421 | Y49: =W49*12*$B$19/Assumptions!$C$18 -> 79093.026 | Z49: =J49*(T49+Assumptions!$C$16) -> 144710 | AA49: =IF(ISNUMBER(F49),F49,IF(H49>=2000,4,3)) -> 4 | AB49: =IFERROR(INDEX($E$18:$H$25,MATCH(D49,$D$18:$D$25,0),1+IF(AA49>=4,2,0)+IF(Q49="Y",1,0)),0) -> 65000 | AC49: =IFERROR(AB49/X49,0) -> 1.0272714 | AD49: =IF(ISNUMBER(SEARCH("Mobile",E49)),"EXCLUDED",IF(AB49>=Y49,"PASS",IF(AB49>=X49,"MARGINAL","FAIL"))) -> MARGINAL
A50: 1704 Palaco Grande Pkwy | B50: Cape Coral 33904 | C50: Lee | D50: Cape Coral pool (STR) | E50: Single Family Residence | F50: 4 | G50: 2 | H50: 2243 | I50: 1983 | J50: 549000 | K50: 234 | L50: 2023-03-31 | M50: 600000 | N50: 324529 | O50: Individual | P50: N | Q50: Y | R50: X | S50: T3 Cape Coral pool | T50: =Assumptions!$C$15 -> 0.25 | U50: =J50*(1-T50) -> 411750 | V50: =IF((1-T50)>0.75,Assumptions!$C$11,IF((1-T50)>0.7,Assumptions!$C$12,Assumptions!$C$13)) -> 0.0725 | W50: =PMT(V50/12,Assumptions!$C$14,-U50)+J50*INDEX(Assumptions!$C$28:$C$34,MATCH(C50,Assumptions!$B$28:$B$34,0))/12+(INDEX(Assumptions!$D$28:$D$34,MATCH(C50,Assumptions!$B$28:$B$34,0))+INDEX(Assumptions!$C$22:$C$25,MATCH(R50,Assumptions!$B$22:$B$25,0)))/12 -> 4253.2775 | X50: =W50*12*$B$18/Assumptions!$C$18 -> 63799.162 | Y50: =W50*12*$B$19/Assumptions!$C$18 -> 79748.953 | Z50: =J50*(T50+Assumptions!$C$16) -> 159210 | AA50: =IF(ISNUMBER(F50),F50,IF(H50>=2000,4,3)) -> 4 | AB50: =IFERROR(INDEX($E$18:$H$25,MATCH(D50,$D$18:$D$25,0),1+IF(AA50>=4,2,0)+IF(Q50="Y",1,0)),0) -> 65000 | AC50: =IFERROR(AB50/X50,0) -> 1.0188222 | AD50: =IF(ISNUMBER(SEARCH("Mobile",E50)),"EXCLUDED",IF(AB50>=Y50,"PASS",IF(AB50>=X50,"MARGINAL","FAIL"))) -> MARGINAL
A51: 1724 SW 51st Ter | B51: Cape Coral 33914 | C51: Lee | D51: Cape Coral pool (STR) | E51: Single Family Residence | F51: 3 | G51: 2 | H51: 1537 | I51: 2000 | J51: 405000 | K51: 11 | L51: 2011-01-20 | M51: 136000 | N51: 284331 | O51: Individual (married) | P51: N | Q51: Y | R51: AE | S51: T3 Cape Coral pool | T51: =Assumptions!$C$15 -> 0.25 | U51: =J51*(1-T51) -> 303750 | V51: =IF((1-T51)>0.75,Assumptions!$C$11,IF((1-T51)>0.7,Assumptions!$C$12,Assumptions!$C$13)) -> 0.0725 | W51: =PMT(V51/12,Assumptions!$C$14,-U51)+J51*INDEX(Assumptions!$C$28:$C$34,MATCH(C51,Assumptions!$B$28:$B$34,0))/12+(INDEX(Assumptions!$D$28:$D$34,MATCH(C51,Assumptions!$B$28:$B$34,0))+INDEX(Assumptions!$C$22:$C$25,MATCH(R51,Assumptions!$B$22:$B$25,0)))/12 -> 3604.1938 | X51: =W51*12*$B$18/Assumptions!$C$18 -> 54062.907 | Y51: =W51*12*$B$19/Assumptions!$C$18 -> 67578.633 | Z51: =J51*(T51+Assumptions!$C$16) -> 117450 | AA51: =IF(ISNUMBER(F51),F51,IF(H51>=2000,4,3)) -> 3 | AB51: =IFERROR(INDEX($E$18:$H$25,MATCH(D51,$D$18:$D$25,0),1+IF(AA51>=4,2,0)+IF(Q51="Y",1,0)),0) -> 55000 | AC51: =IFERROR(AB51/X51,0) -> 1.0173334 | AD51: =IF(ISNUMBER(SEARCH("Mobile",E51)),"EXCLUDED",IF(AB51>=Y51,"PASS",IF(AB51>=X51,"MARGINAL","FAIL"))) -> MARGINAL
A52: 1720 Arabian Ln | B52: Palm Harbor 34685 | C52: Pinellas | D52: Pinellas uninc/Largo (STR) | E52: PUD | H52: 3160 | I52: 1993 | J52: 430000 | K52: 188 | L52: 2011-10-12 | M52: 136500 | N52: 425637 | O52: Individual | P52: N | Q52: N | R52: X | S52: T2 Pinellas Largo/mid | T52: =Assumptions!$C$15 -> 0.25 | U52: =J52*(1-T52) -> 322500 | V52: =IF((1-T52)>0.75,Assumptions!$C$11,IF((1-T52)>0.7,Assumptions!$C$12,Assumptions!$C$13)) -> 0.0725 | W52: =PMT(V52/12,Assumptions!$C$14,-U52)+J52*INDEX(Assumptions!$C$28:$C$34,MATCH(C52,Assumptions!$B$28:$B$34,0))/12+(INDEX(Assumptions!$D$28:$D$34,MATCH(C52,Assumptions!$B$28:$B$34,0))+INDEX(Assumptions!$C$22:$C$25,MATCH(R52,Assumptions!$B$22:$B$25,0)))/12 -> 3440.0185 | X52: =W52*12*$B$18/Assumptions!$C$18 -> 51600.278 | Y52: =W52*12*$B$19/Assumptions!$C$18 -> 64500.347 | Z52: =J52*(T52+Assumptions!$C$16) -> 124700 | AA52: =IF(ISNUMBER(F52),F52,IF(H52>=2000,4,3)) -> 4 | AB52: =IFERROR(INDEX($E$18:$H$25,MATCH(D52,$D$18:$D$25,0),1+IF(AA52>=4,2,0)+IF(Q52="Y",1,0)),0) -> 52000 | AC52: =IFERROR(AB52/X52,0) -> 1.0077465 | AD52: =IF(ISNUMBER(SEARCH("Mobile",E52)),"EXCLUDED",IF(AB52>=Y52,"PASS",IF(AB52>=X52,"MARGINAL","FAIL"))) -> MARGINAL | AE52: Beds not in Pinellas public record; screen assumes 3BR <2,000 sf, 4BR >=2,000 sf.
A53: 622 SW 31st St | B53: Cape Coral 33914 | C53: Lee | D53: Cape Coral pool (STR) | E53: Single Family Residence | F53: 3 | G53: 2.5 | H53: 2251 | I53: 2006 | J53: 454999 | K53: 46 | L53: 2005-02-17 | M53: 64900 | N53: 527195 | O53: Trust | P53: N | Q53: Y | R53: X | S53: T3 Cape Coral pool | T53: =Assumptions!$C$15 -> 0.25 | U53: =J53*(1-T53) -> 341249.25 | V53: =IF((1-T53)>0.75,Assumptions!$C$11,IF((1-T53)>0.7,Assumptions!$C$12,Assumptions!$C$13)) -> 0.0725 | W53: =PMT(V53/12,Assumptions!$C$14,-U53)+J53*INDEX(Assumptions!$C$28:$C$34,MATCH(C53,Assumptions!$B$28:$B$34,0))/12+(INDEX(Assumptions!$D$28:$D$34,MATCH(C53,Assumptions!$B$28:$B$34,0))+INDEX(Assumptions!$C$22:$C$25,MATCH(R53,Assumptions!$B$22:$B$25,0)))/12 -> 3639.17 | X53: =W53*12*$B$18/Assumptions!$C$18 -> 54587.55 | Y53: =W53*12*$B$19/Assumptions!$C$18 -> 68234.438 | Z53: =J53*(T53+Assumptions!$C$16) -> 131949.71 | AA53: =IF(ISNUMBER(F53),F53,IF(H53>=2000,4,3)) -> 3 | AB53: =IFERROR(INDEX($E$18:$H$25,MATCH(D53,$D$18:$D$25,0),1+IF(AA53>=4,2,0)+IF(Q53="Y",1,0)),0) -> 55000 | AC53: =IFERROR(AB53/X53,0) -> 1.0075557 | AD53: =IF(ISNUMBER(SEARCH("Mobile",E53)),"EXCLUDED",IF(AB53>=Y53,"PASS",IF(AB53>=X53,"MARGINAL","FAIL"))) -> MARGINAL
A54: 6513 29th Ave W | B54: Bradenton 34209 | C54: Manatee | D54: Manatee W Bradenton (STR) | E54: Single Family Residence | F54: 3 | G54: 3 | H54: 1973 | I54: 1983 | J54: 499999 | K54: 174 | L54: 2022-01-10 | M54: 340000 | N54: 485932 | O54: Individual (married) | P54: N | Q54: Y | R54: X | S54: T1 Manatee beach | T54: =Assumptions!$C$15 -> 0.25 | U54: =J54*(1-T54) -> 374999.25 | V54: =IF((1-T54)>0.75,Assumptions!$C$11,IF((1-T54)>0.7,Assumptions!$C$12,Assumptions!$C$13)) -> 0.0725 | W54: =PMT(V54/12,Assumptions!$C$14,-U54)+J54*INDEX(Assumptions!$C$28:$C$34,MATCH(C54,Assumptions!$B$28:$B$34,0))/12+(INDEX(Assumptions!$D$28:$D$34,MATCH(C54,Assumptions!$B$28:$B$34,0))+INDEX(Assumptions!$C$22:$C$25,MATCH(R54,Assumptions!$B$22:$B$25,0)))/12 -> 3849.8214 | X54: =W54*12*$B$18/Assumptions!$C$18 -> 57747.32 | Y54: =W54*12*$B$19/Assumptions!$C$18 -> 72184.15 | Z54: =J54*(T54+Assumptions!$C$16) -> 144999.71 | AA54: =IF(ISNUMBER(F54),F54,IF(H54>=2000,4,3)) -> 3 | AB54: =IFERROR(INDEX($E$18:$H$25,MATCH(D54,$D$18:$D$25,0),1+IF(AA54>=4,2,0)+IF(Q54="Y",1,0)),0) -> 58000 | AC54: =IFERROR(AB54/X54,0) -> 1.0043756 | AD54: =IF(ISNUMBER(SEARCH("Mobile",E54)),"EXCLUDED",IF(AB54>=Y54,"PASS",IF(AB54>=X54,"MARGINAL","FAIL"))) -> MARGINAL | AE54: WEB: snippets say 3/2 and no pool mentioned; unfurnished; two cuts $549.9k -> $499,999; likely unincorporated Manatee. No rental claims.
A55: 3603 SE 18th Pl | B55: Cape Coral 33904 | C55: Lee | D55: Cape Coral pool (STR) | E55: Single Family Residence | F55: 3 | G55: 3 | H55: 2042 | I55: 1979 | J55: 430000 | K55: 52 | L55: 2020-07-08 | M55: 280000 | N55: 178695 | O55: Individual | P55: N | Q55: Y | R55: AE | S55: T3 Cape Coral pool | T55: =Assumptions!$C$15 -> 0.25 | U55: =J55*(1-T55) -> 322500 | V55: =IF((1-T55)>0.75,Assumptions!$C$11,IF((1-T55)>0.7,Assumptions!$C$12,Assumptions!$C$13)) -> 0.0725 | W55: =PMT(V55/12,Assumptions!$C$14,-U55)+J55*INDEX(Assumptions!$C$28:$C$34,MATCH(C55,Assumptions!$B$28:$B$34,0))/12+(INDEX(Assumptions!$D$28:$D$34,MATCH(C55,Assumptions!$B$28:$B$34,0))+INDEX(Assumptions!$C$22:$C$25,MATCH(R55,Assumptions!$B$22:$B$25,0)))/12 -> 3767.5185 | X55: =W55*12*$B$18/Assumptions!$C$18 -> 56512.778 | Y55: =W55*12*$B$19/Assumptions!$C$18 -> 70640.972 | Z55: =J55*(T55+Assumptions!$C$16) -> 124700 | AA55: =IF(ISNUMBER(F55),F55,IF(H55>=2000,4,3)) -> 3 | AB55: =IFERROR(INDEX($E$18:$H$25,MATCH(D55,$D$18:$D$25,0),1+IF(AA55>=4,2,0)+IF(Q55="Y",1,0)),0) -> 55000 | AC55: =IFERROR(AB55/X55,0) -> 0.97323123 | AD55: =IF(ISNUMBER(SEARCH("Mobile",E55)),"EXCLUDED",IF(AB55>=Y55,"PASS",IF(AB55>=X55,"MARGINAL","FAIL"))) -> FAIL
A56: 2077 Druid Rd E | B56: Clearwater 33764 | C56: Pinellas | D56: Pinellas uninc/Largo (STR) | E56: Single Family Residence | G56: 2 | H56: 1253 | I56: 1957 | J56: 375000 | K56: 89 | L56: 2002-01-03 | M56: 105000 | N56: 365047 | O56: Individual (married) | P56: N | Q56: N | R56: X | S56: T2 Pinellas Largo/mid | T56: =Assumptions!$C$15 -> 0.25 | U56: =J56*(1-T56) -> 281250 | V56: =IF((1-T56)>0.75,Assumptions!$C$11,IF((1-T56)>0.7,Assumptions!$C$12,Assumptions!$C$13)) -> 0.0725 | W56: =PMT(V56/12,Assumptions!$C$14,-U56)+J56*INDEX(Assumptions!$C$28:$C$34,MATCH(C56,Assumptions!$B$28:$B$34,0))/12+(INDEX(Assumptions!$D$28:$D$34,MATCH(C56,Assumptions!$B$28:$B$34,0))+INDEX(Assumptions!$C$22:$C$25,MATCH(R56,Assumptions!$B$22:$B$25,0)))/12 -> 3085.2875 | X56: =W56*12*$B$18/Assumptions!$C$18 -> 46279.312 | Y56: =W56*12*$B$19/Assumptions!$C$18 -> 57849.14 | Z56: =J56*(T56+Assumptions!$C$16) -> 108750 | AA56: =IF(ISNUMBER(F56),F56,IF(H56>=2000,4,3)) -> 3 | AB56: =IFERROR(INDEX($E$18:$H$25,MATCH(D56,$D$18:$D$25,0),1+IF(AA56>=4,2,0)+IF(Q56="Y",1,0)),0) -> 45000 | AC56: =IFERROR(AB56/X56,0) -> 0.97235672 | AD56: =IF(ISNUMBER(SEARCH("Mobile",E56)),"EXCLUDED",IF(AB56>=Y56,"PASS",IF(AB56>=X56,"MARGINAL","FAIL"))) -> FAIL | AE56: Beds not in Pinellas public record; screen assumes 3BR <2,000 sf, 4BR >=2,000 sf.
A57: 2122 SW 25th St | B57: Cape Coral 33914 | C57: Lee | D57: Cape Coral pool (STR) | E57: Single Family Residence | F57: 4 | G57: 2 | H57: 1711 | I57: 2004 | J57: 539000 | K57: 152 | L57: 2022-05-25 | M57: 512000 | N57: 170897 | O57: Individual (married) | P57: N | Q57: Y | R57: AE | S57: T3 Cape Coral pool | T57: =Assumptions!$C$15 -> 0.25 | U57: =J57*(1-T57) -> 404250 | V57: =IF((1-T57)>0.75,Assumptions!$C$11,IF((1-T57)>0.7,Assumptions!$C$12,Assumptions!$C$13)) -> 0.0725 | W57: =PMT(V57/12,Assumptions!$C$14,-U57)+J57*INDEX(Assumptions!$C$28:$C$34,MATCH(C57,Assumptions!$B$28:$B$34,0))/12+(INDEX(Assumptions!$D$28:$D$34,MATCH(C57,Assumptions!$B$28:$B$34,0))+INDEX(Assumptions!$C$22:$C$25,MATCH(R57,Assumptions!$B$22:$B$25,0)))/12 -> 4479.6143 | X57: =W57*12*$B$18/Assumptions!$C$18 -> 67194.214 | Y57: =W57*12*$B$19/Assumptions!$C$18 -> 83992.768 | Z57: =J57*(T57+Assumptions!$C$16) -> 156310 | AA57: =IF(ISNUMBER(F57),F57,IF(H57>=2000,4,3)) -> 4 | AB57: =IFERROR(INDEX($E$18:$H$25,MATCH(D57,$D$18:$D$25,0),1+IF(AA57>=4,2,0)+IF(Q57="Y",1,0)),0) -> 65000 | AC57: =IFERROR(AB57/X57,0) -> 0.96734519 | AD57: =IF(ISNUMBER(SEARCH("Mobile",E57)),"EXCLUDED",IF(AB57>=Y57,"PASS",IF(AB57>=X57,"MARGINAL","FAIL"))) -> FAIL
A58: 3100 Lake Ridge Dr | B58: Sarasota 34237 | C58: Sarasota | D58: Sarasota City (7-night) | E58: Single Family Residence | F58: 4 | G58: 2 | H58: 1818 | I58: 1971 | J58: 425000 | K58: 37 | L58: 2022-11-18 | M58: 395000 | N58: 95500 | O58: Individual | P58: N | Q58: N | R58: X | S58: T1 Sarasota city | T58: =Assumptions!$C$15 -> 0.25 | U58: =J58*(1-T58) -> 318750 | V58: =IF((1-T58)>0.75,Assumptions!$C$11,IF((1-T58)>0.7,Assumptions!$C$12,Assumptions!$C$13)) -> 0.0725 | W58: =PMT(V58/12,Assumptions!$C$14,-U58)+J58*INDEX(Assumptions!$C$28:$C$34,MATCH(C58,Assumptions!$B$28:$B$34,0))/12+(INDEX(Assumptions!$D$28:$D$34,MATCH(C58,Assumptions!$B$28:$B$34,0))+INDEX(Assumptions!$C$22:$C$25,MATCH(R58,Assumptions!$B$22:$B$25,0)))/12 -> 3319.2286 | X58: =W58*12*$B$18/Assumptions!$C$18 -> 49788.428 | Y58: =W58*12*$B$19/Assumptions!$C$18 -> 62235.535 | Z58: =J58*(T58+Assumptions!$C$16) -> 123250 | AA58: =IF(ISNUMBER(F58),F58,IF(H58>=2000,4,3)) -> 4 | AB58: =IFERROR(INDEX($E$18:$H$25,MATCH(D58,$D$18:$D$25,0),1+IF(AA58>=4,2,0)+IF(Q58="Y",1,0)),0) -> 48000 | AC58: =IFERROR(AB58/X58,0) -> 0.96407944 | AD58: =IF(ISNUMBER(SEARCH("Mobile",E58)),"EXCLUDED",IF(AB58>=Y58,"PASS",IF(AB58>=X58,"MARGINAL","FAIL"))) -> FAIL
A59: 5017 80th Avenue Cir E | B59: Sarasota 34243 | C59: Manatee | D59: Manatee inland (STR) | E59: Single Family Residence | F59: 3 | G59: 2 | H59: 1640 | I59: 1986 | J59: 395000 | K59: 230 | L59: 2011-02-28 | M59: 135000 | N59: 422192 | O59: Individual (married) | P59: N | Q59: Y | R59: X | S59: T1 Manatee other | T59: =Assumptions!$C$15 -> 0.25 | U59: =J59*(1-T59) -> 296250 | V59: =IF((1-T59)>0.75,Assumptions!$C$11,IF((1-T59)>0.7,Assumptions!$C$12,Assumptions!$C$13)) -> 0.0725 | W59: =PMT(V59/12,Assumptions!$C$14,-U59)+J59*INDEX(Assumptions!$C$28:$C$34,MATCH(C59,Assumptions!$B$28:$B$34,0))/12+(INDEX(Assumptions!$D$28:$D$34,MATCH(C59,Assumptions!$B$28:$B$34,0))+INDEX(Assumptions!$C$22:$C$25,MATCH(R59,Assumptions!$B$22:$B$25,0)))/12 -> 3181.3639 | X59: =W59*12*$B$18/Assumptions!$C$18 -> 47720.458 | Y59: =W59*12*$B$19/Assumptions!$C$18 -> 59650.573 | Z59: =J59*(T59+Assumptions!$C$16) -> 114550 | AA59: =IF(ISNUMBER(F59),F59,IF(H59>=2000,4,3)) -> 3 | AB59: =IFERROR(INDEX($E$18:$H$25,MATCH(D59,$D$18:$D$25,0),1+IF(AA59>=4,2,0)+IF(Q59="Y",1,0)),0) -> 46000 | AC59: =IFERROR(AB59/X59,0) -> 0.96394715 | AD59: =IF(ISNUMBER(SEARCH("Mobile",E59)),"EXCLUDED",IF(AB59>=Y59,"PASS",IF(AB59>=X59,"MARGINAL","FAIL"))) -> FAIL
A60: 4831 SW 18th Ave | B60: Cape Coral 33914 | C60: Lee | D60: Cape Coral pool (STR) | E60: Single Family Residence | F60: 4 | G60: 2 | H60: 2090 | I60: 2019 | J60: 541900 | K60: 65 | L60: 2020-01-07 | M60: 257760 | N60: 265376 | O60: Individual | P60: N | Q60: Y | R60: AE | S60: T3 Cape Coral pool | T60: =Assumptions!$C$15 -> 0.25 | U60: =J60*(1-T60) -> 406425 | V60: =IF((1-T60)>0.75,Assumptions!$C$11,IF((1-T60)>0.7,Assumptions!$C$12,Assumptions!$C$13)) -> 0.0725 | W60: =PMT(V60/12,Assumptions!$C$14,-U60)+J60*INDEX(Assumptions!$C$28:$C$34,MATCH(C60,Assumptions!$B$28:$B$34,0))/12+(INDEX(Assumptions!$D$28:$D$34,MATCH(C60,Assumptions!$B$28:$B$34,0))+INDEX(Assumptions!$C$22:$C$25,MATCH(R60,Assumptions!$B$22:$B$25,0)))/12 -> 4498.5599 | X60: =W60*12*$B$18/Assumptions!$C$18 -> 67478.399 | Y60: =W60*12*$B$19/Assumptions!$C$18 -> 84347.999 | Z60: =J60*(T60+Assumptions!$C$16) -> 157151 | AA60: =IF(ISNUMBER(F60),F60,IF(H60>=2000,4,3)) -> 4 | AB60: =IFERROR(INDEX($E$18:$H$25,MATCH(D60,$D$18:$D$25,0),1+IF(AA60>=4,2,0)+IF(Q60="Y",1,0)),0) -> 65000 | AC60: =IFERROR(AB60/X60,0) -> 0.96327122 | AD60: =IF(ISNUMBER(SEARCH("Mobile",E60)),"EXCLUDED",IF(AB60>=Y60,"PASS",IF(AB60>=X60,"MARGINAL","FAIL"))) -> FAIL
A61: 102 Stafford Dr | B61: Palm Harbor 34684 | C61: Pinellas | D61: Pinellas uninc/Largo (STR) | E61: Single Family Residence | G61: 2 | H61: 1264 | I61: 1979 | J61: 379900 | K61: 244 | L61: 2001-04-17 | M61: 90000 | N61: 368929 | O61: Trust | P61: N | Q61: N | R61: X | S61: T2 Pinellas focus | T61: =Assumptions!$C$15 -> 0.25 | U61: =J61*(1-T61) -> 284925 | V61: =IF((1-T61)>0.75,Assumptions!$C$11,IF((1-T61)>0.7,Assumptions!$C$12,Assumptions!$C$13)) -> 0.0725 | W61: =PMT(V61/12,Assumptions!$C$14,-U61)+J61*INDEX(Assumptions!$C$28:$C$34,MATCH(C61,Assumptions!$B$28:$B$34,0))/12+(INDEX(Assumptions!$D$28:$D$34,MATCH(C61,Assumptions!$B$28:$B$34,0))+INDEX(Assumptions!$C$22:$C$25,MATCH(R61,Assumptions!$B$22:$B$25,0)))/12 -> 3116.8908 | X61: =W61*12*$B$18/Assumptions!$C$18 -> 46753.361 | Y61: =W61*12*$B$19/Assumptions!$C$18 -> 58441.702 | Z61: =J61*(T61+Assumptions!$C$16) -> 110171 | AA61: =IF(ISNUMBER(F61),F61,IF(H61>=2000,4,3)) -> 3 | AB61: =IFERROR(INDEX($E$18:$H$25,MATCH(D61,$D$18:$D$25,0),1+IF(AA61>=4,2,0)+IF(Q61="Y",1,0)),0) -> 45000 | AC61: =IFERROR(AB61/X61,0) -> 0.96249764 | AD61: =IF(ISNUMBER(SEARCH("Mobile",E61)),"EXCLUDED",IF(AB61>=Y61,"PASS",IF(AB61>=X61,"MARGINAL","FAIL"))) -> FAIL | AE61: Beds not in Pinellas public record; screen assumes 3BR <2,000 sf, 4BR >=2,000 sf.
A62: 707 65th Avenue Dr W | B62: Bradenton 34207 | C62: Manatee | D62: Manatee W Bradenton (STR) | E62: Single Family Residence | F62: 3 | G62: 2 | H62: 1182 | I62: 1973 | J62: 384900 | K62: 74 | L62: 2023-06-21 | M62: 181000 | N62: 279379 | O62: LLC/Corp | P62: N | Q62: N | R62: X | S62: T1 Manatee beach | T62: =Assumptions!$C$15 -> 0.25 | U62: =J62*(1-T62) -> 288675 | V62: =IF((1-T62)>0.75,Assumptions!$C$11,IF((1-T62)>0.7,Assumptions!$C$12,Assumptions!$C$13)) -> 0.0725 | W62: =PMT(V62/12,Assumptions!$C$14,-U62)+J62*INDEX(Assumptions!$C$28:$C$34,MATCH(C62,Assumptions!$B$28:$B$34,0))/12+(INDEX(Assumptions!$D$28:$D$34,MATCH(C62,Assumptions!$B$28:$B$34,0))+INDEX(Assumptions!$C$22:$C$25,MATCH(R62,Assumptions!$B$22:$B$25,0)))/12 -> 3117.064 | X62: =W62*12*$B$18/Assumptions!$C$18 -> 46755.961 | Y62: =W62*12*$B$19/Assumptions!$C$18 -> 58444.951 | Z62: =J62*(T62+Assumptions!$C$16) -> 111621 | AA62: =IF(ISNUMBER(F62),F62,IF(H62>=2000,4,3)) -> 3 | AB62: =IFERROR(INDEX($E$18:$H$25,MATCH(D62,$D$18:$D$25,0),1+IF(AA62>=4,2,0)+IF(Q62="Y",1,0)),0) -> 45000 | AC62: =IFERROR(AB62/X62,0) -> 0.96244413 | AD62: =IF(ISNUMBER(SEARCH("Mobile",E62)),"EXCLUDED",IF(AB62>=Y62,"PASS",IF(AB62>=X62,"MARGINAL","FAIL"))) -> FAIL
A63: 3409 18th Avenue Dr W | B63: Bradenton 34205 | C63: Manatee | D63: Manatee W Bradenton (STR) | E63: Single Family Residence | F63: 3 | G63: 2 | H63: 1644 | I63: 1971 | J63: 529000 | K63: 65 | L63: 2024-07-01 | M63: 525000 | N63: 109950 | O63: Individual (married) | P63: N | Q63: Y | R63: X | S63: T1 Manatee beach | T63: =Assumptions!$C$15 -> 0.25 | U63: =J63*(1-T63) -> 396750 | V63: =IF((1-T63)>0.75,Assumptions!$C$11,IF((1-T63)>0.7,Assumptions!$C$12,Assumptions!$C$13)) -> 0.0725 | W63: =PMT(V63/12,Assumptions!$C$14,-U63)+J63*INDEX(Assumptions!$C$28:$C$34,MATCH(C63,Assumptions!$B$28:$B$34,0))/12+(INDEX(Assumptions!$D$28:$D$34,MATCH(C63,Assumptions!$B$28:$B$34,0))+INDEX(Assumptions!$C$22:$C$25,MATCH(R63,Assumptions!$B$22:$B$25,0)))/12 -> 4034.4511 | X63: =W63*12*$B$18/Assumptions!$C$18 -> 60516.766 | Y63: =W63*12*$B$19/Assumptions!$C$18 -> 75645.957 | Z63: =J63*(T63+Assumptions!$C$16) -> 153410 | AA63: =IF(ISNUMBER(F63),F63,IF(H63>=2000,4,3)) -> 3 | AB63: =IFERROR(INDEX($E$18:$H$25,MATCH(D63,$D$18:$D$25,0),1+IF(AA63>=4,2,0)+IF(Q63="Y",1,0)),0) -> 58000 | AC63: =IFERROR(AB63/X63,0) -> 0.95841209 | AD63: =IF(ISNUMBER(SEARCH("Mobile",E63)),"EXCLUDED",IF(AB63>=Y63,"PASS",IF(AB63>=X63,"MARGINAL","FAIL"))) -> FAIL | AE63: Already in workbook (see market tab).
A64: 4623 Sanibel Way | B64: Bradenton 34203 | C64: Manatee | D64: Manatee inland (STR) | E64: Single Family Residence | F64: 3 | G64: 2 | H64: 1856 | I64: 2001 | J64: 399900 | K64: 61 | L64: 2015-06-16 | M64: 243000 | N64: 425229 | O64: Individual | P64: N | Q64: Y | R64: X | S64: T1 Manatee other | T64: =Assumptions!$C$15 -> 0.25 | U64: =J64*(1-T64) -> 299925 | V64: =IF((1-T64)>0.75,Assumptions!$C$11,IF((1-T64)>0.7,Assumptions!$C$12,Assumptions!$C$13)) -> 0.0725 | W64: =PMT(V64/12,Assumptions!$C$14,-U64)+J64*INDEX(Assumptions!$C$28:$C$34,MATCH(C64,Assumptions!$B$28:$B$34,0))/12+(INDEX(Assumptions!$D$28:$D$34,MATCH(C64,Assumptions!$B$28:$B$34,0))+INDEX(Assumptions!$C$22:$C$25,MATCH(R64,Assumptions!$B$22:$B$25,0)))/12 -> 3212.5589 | X64: =W64*12*$B$18/Assumptions!$C$18 -> 48188.383 | Y64: =W64*12*$B$19/Assumptions!$C$18 -> 60235.479 | Z64: =J64*(T64+Assumptions!$C$16) -> 115971 | AA64: =IF(ISNUMBER(F64),F64,IF(H64>=2000,4,3)) -> 3 | AB64: =IFERROR(INDEX($E$18:$H$25,MATCH(D64,$D$18:$D$25,0),1+IF(AA64>=4,2,0)+IF(Q64="Y",1,0)),0) -> 46000 | AC64: =IFERROR(AB64/X64,0) -> 0.95458692 | AD64: =IF(ISNUMBER(SEARCH("Mobile",E64)),"EXCLUDED",IF(AB64>=Y64,"PASS",IF(AB64>=X64,"MARGINAL","FAIL"))) -> FAIL
A65: 2801 23rd Ave W | B65: Bradenton 34205 | C65: Manatee | D65: Manatee W Bradenton (STR) | E65: Single Family Residence | F65: 4 | G65: 2 | H65: 1564 | I65: 1968 | J65: 645000 | K65: 24 | L65: 2024-03-04 | M65: 474000 | N65: 17778 | O65: Individual | P65: N | Q65: Y | R65: X | S65: T1 Manatee beach | T65: =Assumptions!$C$15 -> 0.25 | U65: =J65*(1-T65) -> 483750 | V65: =IF((1-T65)>0.75,Assumptions!$C$11,IF((1-T65)>0.7,Assumptions!$C$12,Assumptions!$C$13)) -> 0.0725 | W65: =PMT(V65/12,Assumptions!$C$14,-U65)+J65*INDEX(Assumptions!$C$28:$C$34,MATCH(C65,Assumptions!$B$28:$B$34,0))/12+(INDEX(Assumptions!$D$28:$D$34,MATCH(C65,Assumptions!$B$28:$B$34,0))+INDEX(Assumptions!$C$22:$C$25,MATCH(R65,Assumptions!$B$22:$B$25,0)))/12 -> 4772.9444 | X65: =W65*12*$B$18/Assumptions!$C$18 -> 71594.166 | Y65: =W65*12*$B$19/Assumptions!$C$18 -> 89492.708 | Z65: =J65*(T65+Assumptions!$C$16) -> 187050 | AA65: =IF(ISNUMBER(F65),F65,IF(H65>=2000,4,3)) -> 4 | AB65: =IFERROR(INDEX($E$18:$H$25,MATCH(D65,$D$18:$D$25,0),1+IF(AA65>=4,2,0)+IF(Q65="Y",1,0)),0) -> 68000 | AC65: =IFERROR(AB65/X65,0) -> 0.94979806 | AD65: =IF(ISNUMBER(SEARCH("Mobile",E65)),"EXCLUDED",IF(AB65>=Y65,"PASS",IF(AB65>=X65,"MARGINAL","FAIL"))) -> FAIL | AE65: Already in workbook (see market tab).
A66: 318 SW 28th St | B66: Cape Coral 33914 | C66: Lee | D66: Cape Coral pool (STR) | E66: Single Family Residence | F66: 3 | G66: 2 | H66: 1752 | I66: 1991 | J66: 490000 | K66: 94 | L66: 2025-03-18 | M66: 440000 | N66: 126078 | O66: Individual | P66: N | Q66: Y | R66: X | S66: T3 Cape Coral pool | T66: =Assumptions!$C$15 -> 0.25 | U66: =J66*(1-T66) -> 367500 | V66: =IF((1-T66)>0.75,Assumptions!$C$11,IF((1-T66)>0.7,Assumptions!$C$12,Assumptions!$C$13)) -> 0.0725 | W66: =PMT(V66/12,Assumptions!$C$14,-U66)+J66*INDEX(Assumptions!$C$28:$C$34,MATCH(C66,Assumptions!$B$28:$B$34,0))/12+(INDEX(Assumptions!$D$28:$D$34,MATCH(C66,Assumptions!$B$28:$B$34,0))+INDEX(Assumptions!$C$22:$C$25,MATCH(R66,Assumptions!$B$22:$B$25,0)))/12 -> 3867.8312 | X66: =W66*12*$B$18/Assumptions!$C$18 -> 58017.467 | Y66: =W66*12*$B$19/Assumptions!$C$18 -> 72521.834 | Z66: =J66*(T66+Assumptions!$C$16) -> 142100 | AA66: =IF(ISNUMBER(F66),F66,IF(H66>=2000,4,3)) -> 3 | AB66: =IFERROR(INDEX($E$18:$H$25,MATCH(D66,$D$18:$D$25,0),1+IF(AA66>=4,2,0)+IF(Q66="Y",1,0)),0) -> 55000 | AC66: =IFERROR(AB66/X66,0) -> 0.94799036 | AD66: =IF(ISNUMBER(SEARCH("Mobile",E66)),"EXCLUDED",IF(AB66>=Y66,"PASS",IF(AB66>=X66,"MARGINAL","FAIL"))) -> FAIL
A67: 4205 4th Ave W | B67: Bradenton 34209 | C67: Manatee | D67: Manatee W Bradenton (STR) | E67: Single Family Residence | F67: 3 | G67: 2 | H67: 1635 | I67: 1988 | J67: 392500 | K67: 11 | L67: 2011-02-07 | M67: 120000 | N67: 467886 | O67: LLC/Corp | P67: N | Q67: N | R67: X | S67: T1 Manatee beach | T67: =Assumptions!$C$15 -> 0.25 | U67: =J67*(1-T67) -> 294375 | V67: =IF((1-T67)>0.75,Assumptions!$C$11,IF((1-T67)>0.7,Assumptions!$C$12,Assumptions!$C$13)) -> 0.0725 | W67: =PMT(V67/12,Assumptions!$C$14,-U67)+J67*INDEX(Assumptions!$C$28:$C$34,MATCH(C67,Assumptions!$B$28:$B$34,0))/12+(INDEX(Assumptions!$D$28:$D$34,MATCH(C67,Assumptions!$B$28:$B$34,0))+INDEX(Assumptions!$C$22:$C$25,MATCH(R67,Assumptions!$B$22:$B$25,0)))/12 -> 3165.4481 | X67: =W67*12*$B$18/Assumptions!$C$18 -> 47481.721 | Y67: =W67*12*$B$19/Assumptions!$C$18 -> 59352.152 | Z67: =J67*(T67+Assumptions!$C$16) -> 113825 | AA67: =IF(ISNUMBER(F67),F67,IF(H67>=2000,4,3)) -> 3 | AB67: =IFERROR(INDEX($E$18:$H$25,MATCH(D67,$D$18:$D$25,0),1+IF(AA67>=4,2,0)+IF(Q67="Y",1,0)),0) -> 45000 | AC67: =IFERROR(AB67/X67,0) -> 0.94773312 | AD67: =IF(ISNUMBER(SEARCH("Mobile",E67)),"EXCLUDED",IF(AB67>=Y67,"PASS",IF(AB67>=X67,"MARGINAL","FAIL"))) -> FAIL
A68: 368 Harbor Ridge Dr | B68: Palm Harbor 34683 | C68: Pinellas | D68: Pinellas uninc/Largo (STR) | E68: PUD | H68: 1700 | I68: 2011 | J68: 388000 | K68: 78 | L68: 2021-09-23 | M68: 300000 | N68: 382862 | O68: Individual (married) | P68: N | Q68: N | R68: X | S68: T2 Pinellas focus | T68: =Assumptions!$C$15 -> 0.25 | U68: =J68*(1-T68) -> 291000 | V68: =IF((1-T68)>0.75,Assumptions!$C$11,IF((1-T68)>0.7,Assumptions!$C$12,Assumptions!$C$13)) -> 0.0725 | W68: =PMT(V68/12,Assumptions!$C$14,-U68)+J68*INDEX(Assumptions!$C$28:$C$34,MATCH(C68,Assumptions!$B$28:$B$34,0))/12+(INDEX(Assumptions!$D$28:$D$34,MATCH(C68,Assumptions!$B$28:$B$34,0))+INDEX(Assumptions!$C$22:$C$25,MATCH(R68,Assumptions!$B$22:$B$25,0)))/12 -> 3169.133 | X68: =W68*12*$B$18/Assumptions!$C$18 -> 47536.995 | Y68: =W68*12*$B$19/Assumptions!$C$18 -> 59421.243 | Z68: =J68*(T68+Assumptions!$C$16) -> 112520 | AA68: =IF(ISNUMBER(F68),F68,IF(H68>=2000,4,3)) -> 3 | AB68: =IFERROR(INDEX($E$18:$H$25,MATCH(D68,$D$18:$D$25,0),1+IF(AA68>=4,2,0)+IF(Q68="Y",1,0)),0) -> 45000 | AC68: =IFERROR(AB68/X68,0) -> 0.94663115 | AD68: =IF(ISNUMBER(SEARCH("Mobile",E68)),"EXCLUDED",IF(AB68>=Y68,"PASS",IF(AB68>=X68,"MARGINAL","FAIL"))) -> FAIL | AE68: Beds not in Pinellas public record; screen assumes 3BR <2,000 sf, 4BR >=2,000 sf.
A69: 197 Philadelphia Blvd # 26 | B69: Palm Harbor 34684 | C69: Pinellas | D69: Pinellas uninc/Largo (STR) | E69: Mobile Home | G69: 2 | H69: 1636 | I69: 2004 | J69: 389000 | K69: 173 | L69: 2004-06-17 | M69: 60000 | N69: 377071 | O69: Individual (married) | P69: N | Q69: N | R69: X | S69: T2 Pinellas focus | T69: =Assumptions!$C$15 -> 0.25 | U69: =J69*(1-T69) -> 291750 | V69: =IF((1-T69)>0.75,Assumptions!$C$11,IF((1-T69)>0.7,Assumptions!$C$12,Assumptions!$C$13)) -> 0.0725 | W69: =PMT(V69/12,Assumptions!$C$14,-U69)+J69*INDEX(Assumptions!$C$28:$C$34,MATCH(C69,Assumptions!$B$28:$B$34,0))/12+(INDEX(Assumptions!$D$28:$D$34,MATCH(C69,Assumptions!$B$28:$B$34,0))+INDEX(Assumptions!$C$22:$C$25,MATCH(R69,Assumptions!$B$22:$B$25,0)))/12 -> 3175.5826 | X69: =W69*12*$B$18/Assumptions!$C$18 -> 47633.739 | Y69: =W69*12*$B$19/Assumptions!$C$18 -> 59542.174 | Z69: =J69*(T69+Assumptions!$C$16) -> 112810 | AA69: =IF(ISNUMBER(F69),F69,IF(H69>=2000,4,3)) -> 3 | AB69: =IFERROR(INDEX($E$18:$H$25,MATCH(D69,$D$18:$D$25,0),1+IF(AA69>=4,2,0)+IF(Q69="Y",1,0)),0) -> 45000 | AC69: =IFERROR(AB69/X69,0) -> 0.94470853 | AD69: =IF(ISNUMBER(SEARCH("Mobile",E69)),"EXCLUDED",IF(AB69>=Y69,"PASS",IF(AB69>=X69,"MARGINAL","FAIL"))) -> EXCLUDED | AE69: Mobile/manufactured: not DSCR-eligible. Beds not in Pinellas public record; screen assumes 3BR <2,000 sf, 4BR >=2,000 sf.
A70: 1137 SW 37th St | B70: Cape Coral 33914 | C70: Lee | D70: Cape Coral pool (STR) | E70: Single Family Residence | F70: 3 | G70: 2 | H70: 1909 | I70: 2000 | J70: 449000 | K70: 157 | L70: 2020-10-28 | M70: 365000 | N70: 467611 | O70: LLC/Corp | P70: N | Q70: Y | R70: AE | S70: T3 Cape Coral pool | T70: =Assumptions!$C$15 -> 0.25 | U70: =J70*(1-T70) -> 336750 | V70: =IF((1-T70)>0.75,Assumptions!$C$11,IF((1-T70)>0.7,Assumptions!$C$12,Assumptions!$C$13)) -> 0.0725 | W70: =PMT(V70/12,Assumptions!$C$14,-U70)+J70*INDEX(Assumptions!$C$28:$C$34,MATCH(C70,Assumptions!$B$28:$B$34,0))/12+(INDEX(Assumptions!$D$28:$D$34,MATCH(C70,Assumptions!$B$28:$B$34,0))+INDEX(Assumptions!$C$22:$C$25,MATCH(R70,Assumptions!$B$22:$B$25,0)))/12 -> 3891.6453 | X70: =W70*12*$B$18/Assumptions!$C$18 -> 58374.679 | Y70: =W70*12*$B$19/Assumptions!$C$18 -> 72968.349 | Z70: =J70*(T70+Assumptions!$C$16) -> 130210 | AA70: =IF(ISNUMBER(F70),F70,IF(H70>=2000,4,3)) -> 3 | AB70: =IFERROR(INDEX($E$18:$H$25,MATCH(D70,$D$18:$D$25,0),1+IF(AA70>=4,2,0)+IF(Q70="Y",1,0)),0) -> 55000 | AC70: =IFERROR(AB70/X70,0) -> 0.94218933 | AD70: =IF(ISNUMBER(SEARCH("Mobile",E70)),"EXCLUDED",IF(AB70>=Y70,"PASS",IF(AB70>=X70,"MARGINAL","FAIL"))) -> FAIL
A71: 537 Melody Cir | B71: Sarasota 34237 | C71: Sarasota | D71: Sarasota City (7-night) | E71: Single Family Residence | F71: 4 | G71: 2 | H71: 1340 | I71: 1974 | J71: 439900 | K71: 102 | L71: 2005-07-07 | M71: 210000 | N71: 186498 | O71: Individual | P71: N | Q71: N | R71: X | S71: T1 Sarasota city | T71: =Assumptions!$C$15 -> 0.25 | U71: =J71*(1-T71) -> 329925 | V71: =IF((1-T71)>0.75,Assumptions!$C$11,IF((1-T71)>0.7,Assumptions!$C$12,Assumptions!$C$13)) -> 0.0725 | W71: =PMT(V71/12,Assumptions!$C$14,-U71)+J71*INDEX(Assumptions!$C$28:$C$34,MATCH(C71,Assumptions!$B$28:$B$34,0))/12+(INDEX(Assumptions!$D$28:$D$34,MATCH(C71,Assumptions!$B$28:$B$34,0))+INDEX(Assumptions!$C$22:$C$25,MATCH(R71,Assumptions!$B$22:$B$25,0)))/12 -> 3412.2243 | X71: =W71*12*$B$18/Assumptions!$C$18 -> 51183.364 | Y71: =W71*12*$B$19/Assumptions!$C$18 -> 63979.205 | Z71: =J71*(T71+Assumptions!$C$16) -> 127571 | AA71: =IF(ISNUMBER(F71),F71,IF(H71>=2000,4,3)) -> 4 | AB71: =IFERROR(INDEX($E$18:$H$25,MATCH(D71,$D$18:$D$25,0),1+IF(AA71>=4,2,0)+IF(Q71="Y",1,0)),0) -> 48000 | AC71: =IFERROR(AB71/X71,0) -> 0.93780472 | AD71: =IF(ISNUMBER(SEARCH("Mobile",E71)),"EXCLUDED",IF(AB71>=Y71,"PASS",IF(AB71>=X71,"MARGINAL","FAIL"))) -> FAIL
A72: 6211 Cornell Rd | B72: Bradenton 34207 | C72: Manatee | D72: Manatee W Bradenton (STR) | E72: Single Family Residence | F72: 3 | G72: 2 | H72: 1912 | I72: 1961 | J72: 399999 | K72: 60 | L72: 2024-04-15 | M72: 245000 | N72: 356658 | O72: LLC/Corp | P72: N | Q72: N | R72: X | S72: T1 Manatee beach | T72: =Assumptions!$C$15 -> 0.25 | U72: =J72*(1-T72) -> 299999.25 | V72: =IF((1-T72)>0.75,Assumptions!$C$11,IF((1-T72)>0.7,Assumptions!$C$12,Assumptions!$C$13)) -> 0.0725 | W72: =PMT(V72/12,Assumptions!$C$14,-U72)+J72*INDEX(Assumptions!$C$28:$C$34,MATCH(C72,Assumptions!$B$28:$B$34,0))/12+(INDEX(Assumptions!$D$28:$D$34,MATCH(C72,Assumptions!$B$28:$B$34,0))+INDEX(Assumptions!$C$22:$C$25,MATCH(R72,Assumptions!$B$22:$B$25,0)))/12 -> 3213.1891 | X72: =W72*12*$B$18/Assumptions!$C$18 -> 48197.837 | Y72: =W72*12*$B$19/Assumptions!$C$18 -> 60247.296 | Z72: =J72*(T72+Assumptions!$C$16) -> 115999.71 | AA72: =IF(ISNUMBER(F72),F72,IF(H72>=2000,4,3)) -> 3 | AB72: =IFERROR(INDEX($E$18:$H$25,MATCH(D72,$D$18:$D$25,0),1+IF(AA72>=4,2,0)+IF(Q72="Y",1,0)),0) -> 45000 | AC72: =IFERROR(AB72/X72,0) -> 0.93365185 | AD72: =IF(ISNUMBER(SEARCH("Mobile",E72)),"EXCLUDED",IF(AB72>=Y72,"PASS",IF(AB72>=X72,"MARGINAL","FAIL"))) -> FAIL
A73: 5507 Harbor Rd | B73: Bradenton 34209 | C73: Manatee | D73: Manatee W Bradenton (STR) | E73: Single Family Residence | F73: 3 | G73: 2 | H73: 1356 | I73: 1962 | J73: 400000 | K73: 44 | L73: 2016-06-17 | M73: 190000 | N73: 391606 | O73: Individual (married) | P73: N | Q73: N | R73: X | S73: T1 Manatee beach | T73: =Assumptions!$C$15 -> 0.25 | U73: =J73*(1-T73) -> 300000 | V73: =IF((1-T73)>0.75,Assumptions!$C$11,IF((1-T73)>0.7,Assumptions!$C$12,Assumptions!$C$13)) -> 0.0725 | W73: =PMT(V73/12,Assumptions!$C$14,-U73)+J73*INDEX(Assumptions!$C$28:$C$34,MATCH(C73,Assumptions!$B$28:$B$34,0))/12+(INDEX(Assumptions!$D$28:$D$34,MATCH(C73,Assumptions!$B$28:$B$34,0))+INDEX(Assumptions!$C$22:$C$25,MATCH(R73,Assumptions!$B$22:$B$25,0)))/12 -> 3213.1955 | X73: =W73*12*$B$18/Assumptions!$C$18 -> 48197.933 | Y73: =W73*12*$B$19/Assumptions!$C$18 -> 60247.416 | Z73: =J73*(T73+Assumptions!$C$16) -> 116000 | AA73: =IF(ISNUMBER(F73),F73,IF(H73>=2000,4,3)) -> 3 | AB73: =IFERROR(INDEX($E$18:$H$25,MATCH(D73,$D$18:$D$25,0),1+IF(AA73>=4,2,0)+IF(Q73="Y",1,0)),0) -> 45000 | AC73: =IFERROR(AB73/X73,0) -> 0.93365 | AD73: =IF(ISNUMBER(SEARCH("Mobile",E73)),"EXCLUDED",IF(AB73>=Y73,"PASS",IF(AB73>=X73,"MARGINAL","FAIL"))) -> FAIL
A74: 14623 Sunset Dr | B74: Largo 33774 | C74: Pinellas | D74: Pinellas uninc/Largo (STR) | E74: Single Family Residence | G74: 2 | H74: 1621 | I74: 1950 | J74: 395000 | K74: 51 | L74: 2020-08-14 | M74: 778400 | N74: 417439 | O74: LLC/Corp | P74: N | Q74: N | R74: X | S74: T2 Pinellas Largo/mid | T74: =Assumptions!$C$15 -> 0.25 | U74: =J74*(1-T74) -> 296250 | V74: =IF((1-T74)>0.75,Assumptions!$C$11,IF((1-T74)>0.7,Assumptions!$C$12,Assumptions!$C$13)) -> 0.0725 | W74: =PMT(V74/12,Assumptions!$C$14,-U74)+J74*INDEX(Assumptions!$C$28:$C$34,MATCH(C74,Assumptions!$B$28:$B$34,0))/12+(INDEX(Assumptions!$D$28:$D$34,MATCH(C74,Assumptions!$B$28:$B$34,0))+INDEX(Assumptions!$C$22:$C$25,MATCH(R74,Assumptions!$B$22:$B$25,0)))/12 -> 3214.2806 | X74: =W74*12*$B$18/Assumptions!$C$18 -> 48214.208 | Y74: =W74*12*$B$19/Assumptions!$C$18 -> 60267.761 | Z74: =J74*(T74+Assumptions!$C$16) -> 114550 | AA74: =IF(ISNUMBER(F74),F74,IF(H74>=2000,4,3)) -> 3 | AB74: =IFERROR(INDEX($E$18:$H$25,MATCH(D74,$D$18:$D$25,0),1+IF(AA74>=4,2,0)+IF(Q74="Y",1,0)),0) -> 45000 | AC74: =IFERROR(AB74/X74,0) -> 0.93333483 | AD74: =IF(ISNUMBER(SEARCH("Mobile",E74)),"EXCLUDED",IF(AB74>=Y74,"PASS",IF(AB74>=X74,"MARGINAL","FAIL"))) -> FAIL | AE74: Beds not in Pinellas public record; screen assumes 3BR <2,000 sf, 4BR >=2,000 sf.
A75: 2304 Bahia Vista St | B75: Sarasota 34239 | C75: Sarasota | D75: Sarasota City (7-night) | E75: Single Family Residence | F75: 3 | G75: 2 | H75: 951 | I75: 1952 | J75: 375000 | K75: 59 | L75: 2022-01-24 | M75: 315000 | N75: 29464 | O75: Individual | P75: N | Q75: N | R75: X | S75: T1 Sarasota beach | T75: =Assumptions!$C$15 -> 0.25 | U75: =J75*(1-T75) -> 281250 | V75: =IF((1-T75)>0.75,Assumptions!$C$11,IF((1-T75)>0.7,Assumptions!$C$12,Assumptions!$C$13)) -> 0.0725 | W75: =PMT(V75/12,Assumptions!$C$14,-U75)+J75*INDEX(Assumptions!$C$28:$C$34,MATCH(C75,Assumptions!$B$28:$B$34,0))/12+(INDEX(Assumptions!$D$28:$D$34,MATCH(C75,Assumptions!$B$28:$B$34,0))+INDEX(Assumptions!$C$22:$C$25,MATCH(R75,Assumptions!$B$22:$B$25,0)))/12 -> 3007.1625 | X75: =W75*12*$B$18/Assumptions!$C$18 -> 45107.437 | Y75: =W75*12*$B$19/Assumptions!$C$18 -> 56384.296 | Z75: =J75*(T75+Assumptions!$C$16) -> 108750 | AA75: =IF(ISNUMBER(F75),F75,IF(H75>=2000,4,3)) -> 3 | AB75: =IFERROR(INDEX($E$18:$H$25,MATCH(D75,$D$18:$D$25,0),1+IF(AA75>=4,2,0)+IF(Q75="Y",1,0)),0) -> 42000 | AC75: =IFERROR(AB75/X75,0) -> 0.93111032 | AD75: =IF(ISNUMBER(SEARCH("Mobile",E75)),"EXCLUDED",IF(AB75>=Y75,"PASS",IF(AB75>=X75,"MARGINAL","FAIL"))) -> FAIL
A76: 12663 Indian Rocks Rd | B76: Largo 33774 | C76: Pinellas | D76: Pinellas uninc/Largo (STR) | E76: Single Family Residence | G76: 2 | H76: 2250 | I76: 1958 | J76: 475000 | K76: 19 | L76: 2011-05-26 | M76: 150000 | N76: 396133 | O76: Individual (married) | P76: N | Q76: N | R76: X | S76: T2 Pinellas Largo/mid | T76: =Assumptions!$C$15 -> 0.25 | U76: =J76*(1-T76) -> 356250 | V76: =IF((1-T76)>0.75,Assumptions!$C$11,IF((1-T76)>0.7,Assumptions!$C$12,Assumptions!$C$13)) -> 0.0725 | W76: =PMT(V76/12,Assumptions!$C$14,-U76)+J76*INDEX(Assumptions!$C$28:$C$34,MATCH(C76,Assumptions!$B$28:$B$34,0))/12+(INDEX(Assumptions!$D$28:$D$34,MATCH(C76,Assumptions!$B$28:$B$34,0))+INDEX(Assumptions!$C$22:$C$25,MATCH(R76,Assumptions!$B$22:$B$25,0)))/12 -> 3730.253 | X76: =W76*12*$B$18/Assumptions!$C$18 -> 55953.795 | Y76: =W76*12*$B$19/Assumptions!$C$18 -> 69942.244 | Z76: =J76*(T76+Assumptions!$C$16) -> 137750 | AA76: =IF(ISNUMBER(F76),F76,IF(H76>=2000,4,3)) -> 4 | AB76: =IFERROR(INDEX($E$18:$H$25,MATCH(D76,$D$18:$D$25,0),1+IF(AA76>=4,2,0)+IF(Q76="Y",1,0)),0) -> 52000 | AC76: =IFERROR(AB76/X76,0) -> 0.92933822 | AD76: =IF(ISNUMBER(SEARCH("Mobile",E76)),"EXCLUDED",IF(AB76>=Y76,"PASS",IF(AB76>=X76,"MARGINAL","FAIL"))) -> FAIL | AE76: Beds not in Pinellas public record; screen assumes 3BR <2,000 sf, 4BR >=2,000 sf.
A77: 201 South St | B77: Palm Harbor 34683 | C77: Pinellas | D77: Pinellas uninc/Largo (STR) | E77: Single Family Residence | G77: 1 | H77: 1263 | I77: 1966 | J77: 519000 | K77: 20 | L77: 2024-01-10 | M77: 455000 | N77: 196320 | O77: Individual (married) | P77: N | Q77: Y | R77: AE | S77: T2 Pinellas focus | T77: =Assumptions!$C$15 -> 0.25 | U77: =J77*(1-T77) -> 389250 | V77: =IF((1-T77)>0.75,Assumptions!$C$11,IF((1-T77)>0.7,Assumptions!$C$12,Assumptions!$C$13)) -> 0.0725 | W77: =PMT(V77/12,Assumptions!$C$14,-U77)+J77*INDEX(Assumptions!$C$28:$C$34,MATCH(C77,Assumptions!$B$28:$B$34,0))/12+(INDEX(Assumptions!$D$28:$D$34,MATCH(C77,Assumptions!$B$28:$B$34,0))+INDEX(Assumptions!$C$22:$C$25,MATCH(R77,Assumptions!$B$22:$B$25,0)))/12 -> 4305.7045 | X77: =W77*12*$B$18/Assumptions!$C$18 -> 64585.568 | Y77: =W77*12*$B$19/Assumptions!$C$18 -> 80731.959 | Z77: =J77*(T77+Assumptions!$C$16) -> 150510 | AA77: =IF(ISNUMBER(F77),F77,IF(H77>=2000,4,3)) -> 3 | AB77: =IFERROR(INDEX($E$18:$H$25,MATCH(D77,$D$18:$D$25,0),1+IF(AA77>=4,2,0)+IF(Q77="Y",1,0)),0) -> 60000 | AC77: =IFERROR(AB77/X77,0) -> 0.92900012 | AD77: =IF(ISNUMBER(SEARCH("Mobile",E77)),"EXCLUDED",IF(AB77>=Y77,"PASS",IF(AB77>=X77,"MARGINAL","FAIL"))) -> FAIL | AE77: Beds not in Pinellas public record; screen assumes 3BR <2,000 sf, 4BR >=2,000 sf.
A78: 4750 Tivoli Ave | B78: Sarasota 34235 | C78: Sarasota | D78: Sarasota County (30-day) | E78: Single Family Residence | F78: 3 | G78: 2 | H78: 1911 | I78: 1989 | J78: 425000 | K78: 152 | L78: 2009-03-04 | M78: 325000 | N78: 449597 | O78: Individual | P78: N | Q78: Y | R78: X | S78: T1 Sarasota city | T78: =Assumptions!$C$15 -> 0.25 | U78: =J78*(1-T78) -> 318750 | V78: =IF((1-T78)>0.75,Assumptions!$C$11,IF((1-T78)>0.7,Assumptions!$C$12,Assumptions!$C$13)) -> 0.0725 | W78: =PMT(V78/12,Assumptions!$C$14,-U78)+J78*INDEX(Assumptions!$C$28:$C$34,MATCH(C78,Assumptions!$B$28:$B$34,0))/12+(INDEX(Assumptions!$D$28:$D$34,MATCH(C78,Assumptions!$B$28:$B$34,0))+INDEX(Assumptions!$C$22:$C$25,MATCH(R78,Assumptions!$B$22:$B$25,0)))/12 -> 3319.2286 | X78: =W78*12*$B$18/Assumptions!$C$18 -> 49788.428 | Y78: =W78*12*$B$19/Assumptions!$C$18 -> 62235.535 | Z78: =J78*(T78+Assumptions!$C$16) -> 123250 | AA78: =IF(ISNUMBER(F78),F78,IF(H78>=2000,4,3)) -> 3 | AB78: =IFERROR(INDEX($E$18:$H$25,MATCH(D78,$D$18:$D$25,0),1+IF(AA78>=4,2,0)+IF(Q78="Y",1,0)),0) -> 46000 | AC78: =IFERROR(AB78/X78,0) -> 0.92390946 | AD78: =IF(ISNUMBER(SEARCH("Mobile",E78)),"EXCLUDED",IF(AB78>=Y78,"PASS",IF(AB78>=X78,"MARGINAL","FAIL"))) -> FAIL
A79: 7782 93rd St N | B79: Seminole 33777 | C79: Pinellas | D79: Pinellas uninc/Largo (STR) | E79: PUD | H79: 1534 | I79: 2023 | J79: 389000 | K79: 38 | L79: 2023-09-20 | M79: 415000 | N79: 27861 | O79: Individual (married) | P79: N | Q79: N | R79: Unknown | S79: T2 Pinellas focus | T79: =Assumptions!$C$15 -> 0.25 | U79: =J79*(1-T79) -> 291750 | V79: =IF((1-T79)>0.75,Assumptions!$C$11,IF((1-T79)>0.7,Assumptions!$C$12,Assumptions!$C$13)) -> 0.0725 | W79: =PMT(V79/12,Assumptions!$C$14,-U79)+J79*INDEX(Assumptions!$C$28:$C$34,MATCH(C79,Assumptions!$B$28:$B$34,0))/12+(INDEX(Assumptions!$D$28:$D$34,MATCH(C79,Assumptions!$B$28:$B$34,0))+INDEX(Assumptions!$C$22:$C$25,MATCH(R79,Assumptions!$B$22:$B$25,0)))/12 -> 3258.916 | X79: =W79*12*$B$18/Assumptions!$C$18 -> 48883.739 | Y79: =W79*12*$B$19/Assumptions!$C$18 -> 61104.674 | Z79: =J79*(T79+Assumptions!$C$16) -> 112810 | AA79: =IF(ISNUMBER(F79),F79,IF(H79>=2000,4,3)) -> 3 | AB79: =IFERROR(INDEX($E$18:$H$25,MATCH(D79,$D$18:$D$25,0),1+IF(AA79>=4,2,0)+IF(Q79="Y",1,0)),0) -> 45000 | AC79: =IFERROR(AB79/X79,0) -> 0.92055151 | AD79: =IF(ISNUMBER(SEARCH("Mobile",E79)),"EXCLUDED",IF(AB79>=Y79,"PASS",IF(AB79>=X79,"MARGINAL","FAIL"))) -> FAIL | AE79: Beds not in Pinellas public record; screen assumes 3BR <2,000 sf, 4BR >=2,000 sf.
A80: 3328 70th Ct E | B80: Palmetto 34221 | C80: Manatee | D80: Manatee inland (STR) | E80: Single Family Residence | F80: 3 | G80: 2 | H80: 1487 | I80: 2005 | J80: 424990 | K80: 55 | N80: 26356 | O80: LLC/Corp | P80: N | Q80: Y | R80: X | S80: T1 Manatee other | T80: =Assumptions!$C$15 -> 0.25 | U80: =J80*(1-T80) -> 318742.5 | V80: =IF((1-T80)>0.75,Assumptions!$C$11,IF((1-T80)>0.7,Assumptions!$C$12,Assumptions!$C$13)) -> 0.0725 | W80: =PMT(V80/12,Assumptions!$C$14,-U80)+J80*INDEX(Assumptions!$C$28:$C$34,MATCH(C80,Assumptions!$B$28:$B$34,0))/12+(INDEX(Assumptions!$D$28:$D$34,MATCH(C80,Assumptions!$B$28:$B$34,0))+INDEX(Assumptions!$C$22:$C$25,MATCH(R80,Assumptions!$B$22:$B$25,0)))/12 -> 3372.2899 | X80: =W80*12*$B$18/Assumptions!$C$18 -> 50584.348 | Y80: =W80*12*$B$19/Assumptions!$C$18 -> 63230.436 | Z80: =J80*(T80+Assumptions!$C$16) -> 123247.1 | AA80: =IF(ISNUMBER(F80),F80,IF(H80>=2000,4,3)) -> 3 | AB80: =IFERROR(INDEX($E$18:$H$25,MATCH(D80,$D$18:$D$25,0),1+IF(AA80>=4,2,0)+IF(Q80="Y",1,0)),0) -> 46000 | AC80: =IFERROR(AB80/X80,0) -> 0.9093722 | AD80: =IF(ISNUMBER(SEARCH("Mobile",E80)),"EXCLUDED",IF(AB80>=Y80,"PASS",IF(AB80>=X80,"MARGINAL","FAIL"))) -> FAIL
A81: 235 Overbrook Dr E | B81: Largo 33770 | C81: Pinellas | D81: Pinellas uninc/Largo (STR) | E81: Single Family Residence | G81: 2.5 | H81: 1740 | I81: 1959 | J81: 579000 | K81: 30 | L81: 2017-11-02 | M81: 203000 | N81: 270969 | O81: Individual | P81: N | Q81: Y | R81: X | S81: T2 Pinellas Largo/mid | T81: =Assumptions!$C$15 -> 0.25 | U81: =J81*(1-T81) -> 434250 | V81: =IF((1-T81)>0.75,Assumptions!$C$11,IF((1-T81)>0.7,Assumptions!$C$12,Assumptions!$C$13)) -> 0.0725 | W81: =PMT(V81/12,Assumptions!$C$14,-U81)+J81*INDEX(Assumptions!$C$28:$C$34,MATCH(C81,Assumptions!$B$28:$B$34,0))/12+(INDEX(Assumptions!$D$28:$D$34,MATCH(C81,Assumptions!$B$28:$B$34,0))+INDEX(Assumptions!$C$22:$C$25,MATCH(R81,Assumptions!$B$22:$B$25,0)))/12 -> 4401.0172 | X81: =W81*12*$B$18/Assumptions!$C$18 -> 66015.257 | Y81: =W81*12*$B$19/Assumptions!$C$18 -> 82519.072 | Z81: =J81*(T81+Assumptions!$C$16) -> 167910 | AA81: =IF(ISNUMBER(F81),F81,IF(H81>=2000,4,3)) -> 3 | AB81: =IFERROR(INDEX($E$18:$H$25,MATCH(D81,$D$18:$D$25,0),1+IF(AA81>=4,2,0)+IF(Q81="Y",1,0)),0) -> 60000 | AC81: =IFERROR(AB81/X81,0) -> 0.9088808 | AD81: =IF(ISNUMBER(SEARCH("Mobile",E81)),"EXCLUDED",IF(AB81>=Y81,"PASS",IF(AB81>=X81,"MARGINAL","FAIL"))) -> FAIL | AE81: Beds not in Pinellas public record; screen assumes 3BR <2,000 sf, 4BR >=2,000 sf.
A82: 5949 32nd St N | B82: St Petersburg 33714 | C82: Pinellas | D82: Pinellas uninc/Largo (STR) | E82: Single Family Residence | G82: 1.5 | H82: 1228 | I82: 1962 | J82: 415000 | K82: 59 | L82: 1984-12-01 | M82: 41000 | N82: 269229 | O82: Individual (married) | P82: N | Q82: N | R82: X | S82: T2 Pinellas focus | T82: =Assumptions!$C$15 -> 0.25 | U82: =J82*(1-T82) -> 311250 | V82: =IF((1-T82)>0.75,Assumptions!$C$11,IF((1-T82)>0.7,Assumptions!$C$12,Assumptions!$C$13)) -> 0.0725 | W82: =PMT(V82/12,Assumptions!$C$14,-U82)+J82*INDEX(Assumptions!$C$28:$C$34,MATCH(C82,Assumptions!$B$28:$B$34,0))/12+(INDEX(Assumptions!$D$28:$D$34,MATCH(C82,Assumptions!$B$28:$B$34,0))+INDEX(Assumptions!$C$22:$C$25,MATCH(R82,Assumptions!$B$22:$B$25,0)))/12 -> 3343.2737 | X82: =W82*12*$B$18/Assumptions!$C$18 -> 50149.105 | Y82: =W82*12*$B$19/Assumptions!$C$18 -> 62686.381 | Z82: =J82*(T82+Assumptions!$C$16) -> 120350 | AA82: =IF(ISNUMBER(F82),F82,IF(H82>=2000,4,3)) -> 3 | AB82: =IFERROR(INDEX($E$18:$H$25,MATCH(D82,$D$18:$D$25,0),1+IF(AA82>=4,2,0)+IF(Q82="Y",1,0)),0) -> 45000 | AC82: =IFERROR(AB82/X82,0) -> 0.89732409 | AD82: =IF(ISNUMBER(SEARCH("Mobile",E82)),"EXCLUDED",IF(AB82>=Y82,"PASS",IF(AB82>=X82,"MARGINAL","FAIL"))) -> FAIL | AE82: Beds not in Pinellas public record; screen assumes 3BR <2,000 sf, 4BR >=2,000 sf.
A83: 2431 Grove Ridge Dr | B83: Palm Harbor 34683 | C83: Pinellas | D83: Pinellas uninc/Largo (STR) | E83: Single Family Residence | G83: 2 | H83: 1749 | I83: 1981 | J83: 415000 | K83: 96 | L83: 2019-06-19 | M83: 100 | N83: 440092 | O83: LLC/Corp | P83: N | Q83: N | R83: X | S83: T2 Pinellas focus | T83: =Assumptions!$C$15 -> 0.25 | U83: =J83*(1-T83) -> 311250 | V83: =IF((1-T83)>0.75,Assumptions!$C$11,IF((1-T83)>0.7,Assumptions!$C$12,Assumptions!$C$13)) -> 0.0725 | W83: =PMT(V83/12,Assumptions!$C$14,-U83)+J83*INDEX(Assumptions!$C$28:$C$34,MATCH(C83,Assumptions!$B$28:$B$34,0))/12+(INDEX(Assumptions!$D$28:$D$34,MATCH(C83,Assumptions!$B$28:$B$34,0))+INDEX(Assumptions!$C$22:$C$25,MATCH(R83,Assumptions!$B$22:$B$25,0)))/12 -> 3343.2737 | X83: =W83*12*$B$18/Assumptions!$C$18 -> 50149.105 | Y83: =W83*12*$B$19/Assumptions!$C$18 -> 62686.381 | Z83: =J83*(T83+Assumptions!$C$16) -> 120350 | AA83: =IF(ISNUMBER(F83),F83,IF(H83>=2000,4,3)) -> 3 | AB83: =IFERROR(INDEX($E$18:$H$25,MATCH(D83,$D$18:$D$25,0),1+IF(AA83>=4,2,0)+IF(Q83="Y",1,0)),0) -> 45000 | AC83: =IFERROR(AB83/X83,0) -> 0.89732409 | AD83: =IF(ISNUMBER(SEARCH("Mobile",E83)),"EXCLUDED",IF(AB83>=Y83,"PASS",IF(AB83>=X83,"MARGINAL","FAIL"))) -> FAIL | AE83: Beds not in Pinellas public record; screen assumes 3BR <2,000 sf, 4BR >=2,000 sf.
A84: 1516 Adele Pl | B84: Largo 33770 | C84: Pinellas | D84: Pinellas uninc/Largo (STR) | E84: Single Family Residence | G84: 1.5 | H84: 1305 | I84: 1959 | J84: 415000 | K84: 81 | N84: 144061 | O84: LLC/Corp | P84: N | Q84: N | R84: X | S84: T2 Pinellas Largo/mid | T84: =Assumptions!$C$15 -> 0.25 | U84: =J84*(1-T84) -> 311250 | V84: =IF((1-T84)>0.75,Assumptions!$C$11,IF((1-T84)>0.7,Assumptions!$C$12,Assumptions!$C$13)) -> 0.0725 | W84: =PMT(V84/12,Assumptions!$C$14,-U84)+J84*INDEX(Assumptions!$C$28:$C$34,MATCH(C84,Assumptions!$B$28:$B$34,0))/12+(INDEX(Assumptions!$D$28:$D$34,MATCH(C84,Assumptions!$B$28:$B$34,0))+INDEX(Assumptions!$C$22:$C$25,MATCH(R84,Assumptions!$B$22:$B$25,0)))/12 -> 3343.2737 | X84: =W84*12*$B$18/Assumptions!$C$18 -> 50149.105 | Y84: =W84*12*$B$19/Assumptions!$C$18 -> 62686.381 | Z84: =J84*(T84+Assumptions!$C$16) -> 120350 | AA84: =IF(ISNUMBER(F84),F84,IF(H84>=2000,4,3)) -> 3 | AB84: =IFERROR(INDEX($E$18:$H$25,MATCH(D84,$D$18:$D$25,0),1+IF(AA84>=4,2,0)+IF(Q84="Y",1,0)),0) -> 45000 | AC84: =IFERROR(AB84/X84,0) -> 0.89732409 | AD84: =IF(ISNUMBER(SEARCH("Mobile",E84)),"EXCLUDED",IF(AB84>=Y84,"PASS",IF(AB84>=X84,"MARGINAL","FAIL"))) -> FAIL | AE84: Beds not in Pinellas public record; screen assumes 3BR <2,000 sf, 4BR >=2,000 sf.
A85: 927 SW 28th Ter | B85: Cape Coral 33914 | C85: Lee | D85: Cape Coral pool (STR) | E85: Single Family Residence | F85: 3 | G85: 2 | H85: 2110 | I85: 2008 | J85: 525000 | K85: 38 | L85: 2009-04-15 | M85: 114900 | N85: 552939 | O85: Individual (married) | P85: N | Q85: Y | R85: X | S85: T3 Cape Coral pool | T85: =Assumptions!$C$15 -> 0.25 | U85: =J85*(1-T85) -> 393750 | V85: =IF((1-T85)>0.75,Assumptions!$C$11,IF((1-T85)>0.7,Assumptions!$C$12,Assumptions!$C$13)) -> 0.0725 | W85: =PMT(V85/12,Assumptions!$C$14,-U85)+J85*INDEX(Assumptions!$C$28:$C$34,MATCH(C85,Assumptions!$B$28:$B$34,0))/12+(INDEX(Assumptions!$D$28:$D$34,MATCH(C85,Assumptions!$B$28:$B$34,0))+INDEX(Assumptions!$C$22:$C$25,MATCH(R85,Assumptions!$B$22:$B$25,0)))/12 -> 4096.4858 | X85: =W85*12*$B$18/Assumptions!$C$18 -> 61447.287 | Y85: =W85*12*$B$19/Assumptions!$C$18 -> 76809.108 | Z85: =J85*(T85+Assumptions!$C$16) -> 152250 | AA85: =IF(ISNUMBER(F85),F85,IF(H85>=2000,4,3)) -> 3 | AB85: =IFERROR(INDEX($E$18:$H$25,MATCH(D85,$D$18:$D$25,0),1+IF(AA85>=4,2,0)+IF(Q85="Y",1,0)),0) -> 55000 | AC85: =IFERROR(AB85/X85,0) -> 0.89507614 | AD85: =IF(ISNUMBER(SEARCH("Mobile",E85)),"EXCLUDED",IF(AB85>=Y85,"PASS",IF(AB85>=X85,"MARGINAL","FAIL"))) -> FAIL
A86: 3332 SE 19th Ave | B86: Cape Coral 33904 | C86: Lee | D86: Cape Coral pool (STR) | E86: Single Family Residence | F86: 3 | G86: 2 | H86: 1714 | I86: 1967 | J86: 485000 | K86: 101 | L86: 2004-08-03 | M86: 360000 | N86: 474356 | O86: Individual (married) | P86: N | Q86: Y | R86: AE | S86: T3 Cape Coral pool | T86: =Assumptions!$C$15 -> 0.25 | U86: =J86*(1-T86) -> 363750 | V86: =IF((1-T86)>0.75,Assumptions!$C$11,IF((1-T86)>0.7,Assumptions!$C$12,Assumptions!$C$13)) -> 0.0725 | W86: =PMT(V86/12,Assumptions!$C$14,-U86)+J86*INDEX(Assumptions!$C$28:$C$34,MATCH(C86,Assumptions!$B$28:$B$34,0))/12+(INDEX(Assumptions!$D$28:$D$34,MATCH(C86,Assumptions!$B$28:$B$34,0))+INDEX(Assumptions!$C$22:$C$25,MATCH(R86,Assumptions!$B$22:$B$25,0)))/12 -> 4126.8329 | X86: =W86*12*$B$18/Assumptions!$C$18 -> 61902.493 | Y86: =W86*12*$B$19/Assumptions!$C$18 -> 77378.117 | Z86: =J86*(T86+Assumptions!$C$16) -> 140650 | AA86: =IF(ISNUMBER(F86),F86,IF(H86>=2000,4,3)) -> 3 | AB86: =IFERROR(INDEX($E$18:$H$25,MATCH(D86,$D$18:$D$25,0),1+IF(AA86>=4,2,0)+IF(Q86="Y",1,0)),0) -> 55000 | AC86: =IFERROR(AB86/X86,0) -> 0.8884941 | AD86: =IF(ISNUMBER(SEARCH("Mobile",E86)),"EXCLUDED",IF(AB86>=Y86,"PASS",IF(AB86>=X86,"MARGINAL","FAIL"))) -> FAIL
A87: 12080 66th Ave | B87: Seminole 33772 | C87: Pinellas | D87: Pinellas uninc/Largo (STR) | E87: Single Family Residence | G87: 2 | H87: 1601 | I87: 1981 | J87: 594999 | K87: 61 | L87: 2012-12-19 | M87: 232500 | N87: 362462 | O87: LLC/Corp | P87: N | Q87: Y | R87: X | S87: T2 Pinellas focus | T87: =Assumptions!$C$15 -> 0.25 | U87: =J87*(1-T87) -> 446249.25 | V87: =IF((1-T87)>0.75,Assumptions!$C$11,IF((1-T87)>0.7,Assumptions!$C$12,Assumptions!$C$13)) -> 0.0725 | W87: =PMT(V87/12,Assumptions!$C$14,-U87)+J87*INDEX(Assumptions!$C$28:$C$34,MATCH(C87,Assumptions!$B$28:$B$34,0))/12+(INDEX(Assumptions!$D$28:$D$34,MATCH(C87,Assumptions!$B$28:$B$34,0))+INDEX(Assumptions!$C$22:$C$25,MATCH(R87,Assumptions!$B$22:$B$25,0)))/12 -> 4504.2052 | X87: =W87*12*$B$18/Assumptions!$C$18 -> 67563.078 | Y87: =W87*12*$B$19/Assumptions!$C$18 -> 84453.848 | Z87: =J87*(T87+Assumptions!$C$16) -> 172549.71 | AA87: =IF(ISNUMBER(F87),F87,IF(H87>=2000,4,3)) -> 3 | AB87: =IFERROR(INDEX($E$18:$H$25,MATCH(D87,$D$18:$D$25,0),1+IF(AA87>=4,2,0)+IF(Q87="Y",1,0)),0) -> 60000 | AC87: =IFERROR(AB87/X87,0) -> 0.88805901 | AD87: =IF(ISNUMBER(SEARCH("Mobile",E87)),"EXCLUDED",IF(AB87>=Y87,"PASS",IF(AB87>=X87,"MARGINAL","FAIL"))) -> FAIL | AE87: Beds not in Pinellas public record; screen assumes 3BR <2,000 sf, 4BR >=2,000 sf.
A88: 403 SE 33rd Ter | B88: Cape Coral 33904 | C88: Lee | D88: Cape Coral pool (STR) | E88: Single Family Residence | F88: 3 | G88: 2 | H88: 1489 | I88: 1981 | J88: 489000 | K88: 39 | L88: 2022-06-14 | M88: 578000 | N88: 499457 | O88: LLC/Corp | P88: N | Q88: Y | R88: AE | S88: T3 Cape Coral pool | T88: =Assumptions!$C$15 -> 0.25 | U88: =J88*(1-T88) -> 366750 | V88: =IF((1-T88)>0.75,Assumptions!$C$11,IF((1-T88)>0.7,Assumptions!$C$12,Assumptions!$C$13)) -> 0.0725 | W88: =PMT(V88/12,Assumptions!$C$14,-U88)+J88*INDEX(Assumptions!$C$28:$C$34,MATCH(C88,Assumptions!$B$28:$B$34,0))/12+(INDEX(Assumptions!$D$28:$D$34,MATCH(C88,Assumptions!$B$28:$B$34,0))+INDEX(Assumptions!$C$22:$C$25,MATCH(R88,Assumptions!$B$22:$B$25,0)))/12 -> 4152.9648 | X88: =W88*12*$B$18/Assumptions!$C$18 -> 62294.473 | Y88: =W88*12*$B$19/Assumptions!$C$18 -> 77868.091 | Z88: =J88*(T88+Assumptions!$C$16) -> 141810 | AA88: =IF(ISNUMBER(F88),F88,IF(H88>=2000,4,3)) -> 3 | AB88: =IFERROR(INDEX($E$18:$H$25,MATCH(D88,$D$18:$D$25,0),1+IF(AA88>=4,2,0)+IF(Q88="Y",1,0)),0) -> 55000 | AC88: =IFERROR(AB88/X88,0) -> 0.88290337 | AD88: =IF(ISNUMBER(SEARCH("Mobile",E88)),"EXCLUDED",IF(AB88>=Y88,"PASS",IF(AB88>=X88,"MARGINAL","FAIL"))) -> FAIL
A89: 4633 Brooksdale Dr | B89: Sarasota 34232 | C89: Sarasota | D89: Sarasota County (30-day) | E89: Single Family Residence | F89: 3 | G89: 3 | H89: 1663 | I89: 1981 | J89: 449900 | K89: 100 | L89: 2018-06-19 | M89: 210000 | N89: 176189 | O89: LLC/Corp | P89: N | Q89: Y | R89: X | S89: T1 Sarasota city | T89: =Assumptions!$C$15 -> 0.25 | U89: =J89*(1-T89) -> 337425 | V89: =IF((1-T89)>0.75,Assumptions!$C$11,IF((1-T89)>0.7,Assumptions!$C$12,Assumptions!$C$13)) -> 0.0725 | W89: =PMT(V89/12,Assumptions!$C$14,-U89)+J89*INDEX(Assumptions!$C$28:$C$34,MATCH(C89,Assumptions!$B$28:$B$34,0))/12+(INDEX(Assumptions!$D$28:$D$34,MATCH(C89,Assumptions!$B$28:$B$34,0))+INDEX(Assumptions!$C$22:$C$25,MATCH(R89,Assumptions!$B$22:$B$25,0)))/12 -> 3474.6375 | X89: =W89*12*$B$18/Assumptions!$C$18 -> 52119.562 | Y89: =W89*12*$B$19/Assumptions!$C$18 -> 65149.453 | Z89: =J89*(T89+Assumptions!$C$16) -> 130471 | AA89: =IF(ISNUMBER(F89),F89,IF(H89>=2000,4,3)) -> 3 | AB89: =IFERROR(INDEX($E$18:$H$25,MATCH(D89,$D$18:$D$25,0),1+IF(AA89>=4,2,0)+IF(Q89="Y",1,0)),0) -> 46000 | AC89: =IFERROR(AB89/X89,0) -> 0.88258608 | AD89: =IF(ISNUMBER(SEARCH("Mobile",E89)),"EXCLUDED",IF(AB89>=Y89,"PASS",IF(AB89>=X89,"MARGINAL","FAIL"))) -> FAIL
A90: 740 Coral Dr | B90: Cape Coral 33904 | C90: Lee | D90: Cape Coral pool (STR) | E90: Single Family Residence | F90: 3 | G90: 2 | H90: 1899 | I90: 1976 | J90: 489900 | K90: 144 | L90: 2024-10-14 | M90: 448000 | N90: 371709 | O90: Individual | P90: N | Q90: Y | R90: AE | S90: T3 Cape Coral pool | T90: =Assumptions!$C$15 -> 0.25 | U90: =J90*(1-T90) -> 367425 | V90: =IF((1-T90)>0.75,Assumptions!$C$11,IF((1-T90)>0.7,Assumptions!$C$12,Assumptions!$C$13)) -> 0.0725 | W90: =PMT(V90/12,Assumptions!$C$14,-U90)+J90*INDEX(Assumptions!$C$28:$C$34,MATCH(C90,Assumptions!$B$28:$B$34,0))/12+(INDEX(Assumptions!$D$28:$D$34,MATCH(C90,Assumptions!$B$28:$B$34,0))+INDEX(Assumptions!$C$22:$C$25,MATCH(R90,Assumptions!$B$22:$B$25,0)))/12 -> 4158.8445 | X90: =W90*12*$B$18/Assumptions!$C$18 -> 62382.668 | Y90: =W90*12*$B$19/Assumptions!$C$18 -> 77978.335 | Z90: =J90*(T90+Assumptions!$C$16) -> 142071 | AA90: =IF(ISNUMBER(F90),F90,IF(H90>=2000,4,3)) -> 3 | AB90: =IFERROR(INDEX($E$18:$H$25,MATCH(D90,$D$18:$D$25,0),1+IF(AA90>=4,2,0)+IF(Q90="Y",1,0)),0) -> 55000 | AC90: =IFERROR(AB90/X90,0) -> 0.88165514 | AD90: =IF(ISNUMBER(SEARCH("Mobile",E90)),"EXCLUDED",IF(AB90>=Y90,"PASS",IF(AB90>=X90,"MARGINAL","FAIL"))) -> FAIL
A91: 5625 35th Way N | B91: St Petersburg 33714 | C91: Pinellas | D91: Pinellas uninc/Largo (STR) | E91: Single Family Residence | G91: 2 | H91: 1648 | I91: 2020 | J91: 424900 | K91: 12 | L91: 2019-05-15 | M91: 47500 | N91: -11297376 | O91: LLC/Corp | P91: N | Q91: N | R91: X | S91: T2 Pinellas focus | T91: =Assumptions!$C$15 -> 0.25 | U91: =J91*(1-T91) -> 318675 | V91: =IF((1-T91)>0.75,Assumptions!$C$11,IF((1-T91)>0.7,Assumptions!$C$12,Assumptions!$C$13)) -> 0.0725 | W91: =PMT(V91/12,Assumptions!$C$14,-U91)+J91*INDEX(Assumptions!$C$28:$C$34,MATCH(C91,Assumptions!$B$28:$B$34,0))/12+(INDEX(Assumptions!$D$28:$D$34,MATCH(C91,Assumptions!$B$28:$B$34,0))+INDEX(Assumptions!$C$22:$C$25,MATCH(R91,Assumptions!$B$22:$B$25,0)))/12 -> 3407.1253 | X91: =W91*12*$B$18/Assumptions!$C$18 -> 51106.879 | Y91: =W91*12*$B$19/Assumptions!$C$18 -> 63883.599 | Z91: =J91*(T91+Assumptions!$C$16) -> 123221 | AA91: =IF(ISNUMBER(F91),F91,IF(H91>=2000,4,3)) -> 3 | AB91: =IFERROR(INDEX($E$18:$H$25,MATCH(D91,$D$18:$D$25,0),1+IF(AA91>=4,2,0)+IF(Q91="Y",1,0)),0) -> 45000 | AC91: =IFERROR(AB91/X91,0) -> 0.88050769 | AD91: =IF(ISNUMBER(SEARCH("Mobile",E91)),"EXCLUDED",IF(AB91>=Y91,"PASS",IF(AB91>=X91,"MARGINAL","FAIL"))) -> FAIL | AE91: Beds not in Pinellas public record; screen assumes 3BR <2,000 sf, 4BR >=2,000 sf.
A92: 13822 Brewster Dr | B92: Largo 33774 | C92: Pinellas | D92: Pinellas uninc/Largo (STR) | E92: Single Family Residence | G92: 2 | H92: 1287 | I92: 1970 | J92: 429900 | K92: 12 | L92: 1984-10-01 | M92: 73000 | N92: 343633 | O92: Trust | P92: N | Q92: N | R92: X | S92: T2 Pinellas Largo/mid | T92: =Assumptions!$C$15 -> 0.25 | U92: =J92*(1-T92) -> 322425 | V92: =IF((1-T92)>0.75,Assumptions!$C$11,IF((1-T92)>0.7,Assumptions!$C$12,Assumptions!$C$13)) -> 0.0725 | W92: =PMT(V92/12,Assumptions!$C$14,-U92)+J92*INDEX(Assumptions!$C$28:$C$34,MATCH(C92,Assumptions!$B$28:$B$34,0))/12+(INDEX(Assumptions!$D$28:$D$34,MATCH(C92,Assumptions!$B$28:$B$34,0))+INDEX(Assumptions!$C$22:$C$25,MATCH(R92,Assumptions!$B$22:$B$25,0)))/12 -> 3439.3735 | X92: =W92*12*$B$18/Assumptions!$C$18 -> 51590.603 | Y92: =W92*12*$B$19/Assumptions!$C$18 -> 64488.254 | Z92: =J92*(T92+Assumptions!$C$16) -> 124671 | AA92: =IF(ISNUMBER(F92),F92,IF(H92>=2000,4,3)) -> 3 | AB92: =IFERROR(INDEX($E$18:$H$25,MATCH(D92,$D$18:$D$25,0),1+IF(AA92>=4,2,0)+IF(Q92="Y",1,0)),0) -> 45000 | AC92: =IFERROR(AB92/X92,0) -> 0.87225187 | AD92: =IF(ISNUMBER(SEARCH("Mobile",E92)),"EXCLUDED",IF(AB92>=Y92,"PASS",IF(AB92>=X92,"MARGINAL","FAIL"))) -> FAIL | AE92: Beds not in Pinellas public record; screen assumes 3BR <2,000 sf, 4BR >=2,000 sf.
A93: 2209 Euclid Cir S | B93: Clearwater 33764 | C93: Pinellas | D93: Pinellas uninc/Largo (STR) | E93: Single Family Residence | G93: 2 | H93: 1440 | I93: 1959 | J93: 429900 | K93: 60 | L93: 2021-12-10 | M93: 249900 | N93: 181349 | O93: Individual (married) | P93: N | Q93: N | R93: X | S93: T2 Pinellas Largo/mid | T93: =Assumptions!$C$15 -> 0.25 | U93: =J93*(1-T93) -> 322425 | V93: =IF((1-T93)>0.75,Assumptions!$C$11,IF((1-T93)>0.7,Assumptions!$C$12,Assumptions!$C$13)) -> 0.0725 | W93: =PMT(V93/12,Assumptions!$C$14,-U93)+J93*INDEX(Assumptions!$C$28:$C$34,MATCH(C93,Assumptions!$B$28:$B$34,0))/12+(INDEX(Assumptions!$D$28:$D$34,MATCH(C93,Assumptions!$B$28:$B$34,0))+INDEX(Assumptions!$C$22:$C$25,MATCH(R93,Assumptions!$B$22:$B$25,0)))/12 -> 3439.3735 | X93: =W93*12*$B$18/Assumptions!$C$18 -> 51590.603 | Y93: =W93*12*$B$19/Assumptions!$C$18 -> 64488.254 | Z93: =J93*(T93+Assumptions!$C$16) -> 124671 | AA93: =IF(ISNUMBER(F93),F93,IF(H93>=2000,4,3)) -> 3 | AB93: =IFERROR(INDEX($E$18:$H$25,MATCH(D93,$D$18:$D$25,0),1+IF(AA93>=4,2,0)+IF(Q93="Y",1,0)),0) -> 45000 | AC93: =IFERROR(AB93/X93,0) -> 0.87225187 | AD93: =IF(ISNUMBER(SEARCH("Mobile",E93)),"EXCLUDED",IF(AB93>=Y93,"PASS",IF(AB93>=X93,"MARGINAL","FAIL"))) -> FAIL | AE93: Beds not in Pinellas public record; screen assumes 3BR <2,000 sf, 4BR >=2,000 sf.
A94: 2872 Wesleyan Dr | B94: Palm Harbor 34684 | C94: Pinellas | D94: Pinellas uninc/Largo (STR) | E94: Single Family Residence | G94: 2 | H94: 1450 | I94: 1984 | J94: 430000 | K94: 3 | L94: 2014-06-10 | M94: 179000 | N94: 256497 | O94: Individual (multi) | P94: N | Q94: N | R94: X | S94: T2 Pinellas focus | T94: =Assumptions!$C$15 -> 0.25 | U94: =J94*(1-T94) -> 322500 | V94: =IF((1-T94)>0.75,Assumptions!$C$11,IF((1-T94)>0.7,Assumptions!$C$12,Assumptions!$C$13)) -> 0.0725 | W94: =PMT(V94/12,Assumptions!$C$14,-U94)+J94*INDEX(Assumptions!$C$28:$C$34,MATCH(C94,Assumptions!$B$28:$B$34,0))/12+(INDEX(Assumptions!$D$28:$D$34,MATCH(C94,Assumptions!$B$28:$B$34,0))+INDEX(Assumptions!$C$22:$C$25,MATCH(R94,Assumptions!$B$22:$B$25,0)))/12 -> 3440.0185 | X94: =W94*12*$B$18/Assumptions!$C$18 -> 51600.278 | Y94: =W94*12*$B$19/Assumptions!$C$18 -> 64500.347 | Z94: =J94*(T94+Assumptions!$C$16) -> 124700 | AA94: =IF(ISNUMBER(F94),F94,IF(H94>=2000,4,3)) -> 3 | AB94: =IFERROR(INDEX($E$18:$H$25,MATCH(D94,$D$18:$D$25,0),1+IF(AA94>=4,2,0)+IF(Q94="Y",1,0)),0) -> 45000 | AC94: =IFERROR(AB94/X94,0) -> 0.87208833 | AD94: =IF(ISNUMBER(SEARCH("Mobile",E94)),"EXCLUDED",IF(AB94>=Y94,"PASS",IF(AB94>=X94,"MARGINAL","FAIL"))) -> FAIL | AE94: Beds not in Pinellas public record; screen assumes 3BR <2,000 sf, 4BR >=2,000 sf.
A95: 2014 Country Meadows Ln | B95: Sarasota 34235 | C95: Sarasota | D95: Sarasota County (30-day) | E95: Single Family Residence | F95: 3 | G95: 2 | H95: 1821 | I95: 1986 | J95: 459000 | K95: 9 | L95: 2020-12-14 | M95: 350000 | N95: 136224 | O95: LLC/Corp | P95: N | Q95: Y | R95: X | S95: T1 Sarasota city | T95: =Assumptions!$C$15 -> 0.25 | U95: =J95*(1-T95) -> 344250 | V95: =IF((1-T95)>0.75,Assumptions!$C$11,IF((1-T95)>0.7,Assumptions!$C$12,Assumptions!$C$13)) -> 0.0725 | W95: =PMT(V95/12,Assumptions!$C$14,-U95)+J95*INDEX(Assumptions!$C$28:$C$34,MATCH(C95,Assumptions!$B$28:$B$34,0))/12+(INDEX(Assumptions!$D$28:$D$34,MATCH(C95,Assumptions!$B$28:$B$34,0))+INDEX(Assumptions!$C$22:$C$25,MATCH(R95,Assumptions!$B$22:$B$25,0)))/12 -> 3531.4335 | X95: =W95*12*$B$18/Assumptions!$C$18 -> 52971.503 | Y95: =W95*12*$B$19/Assumptions!$C$18 -> 66214.378 | Z95: =J95*(T95+Assumptions!$C$16) -> 133110 | AA95: =IF(ISNUMBER(F95),F95,IF(H95>=2000,4,3)) -> 3 | AB95: =IFERROR(INDEX($E$18:$H$25,MATCH(D95,$D$18:$D$25,0),1+IF(AA95>=4,2,0)+IF(Q95="Y",1,0)),0) -> 46000 | AC95: =IFERROR(AB95/X95,0) -> 0.86839145 | AD95: =IF(ISNUMBER(SEARCH("Mobile",E95)),"EXCLUDED",IF(AB95>=Y95,"PASS",IF(AB95>=X95,"MARGINAL","FAIL"))) -> FAIL
A96: 4708 Alligator Dr | B96: Venice 34293 | C96: Sarasota | D96: Sarasota County (30-day) | E96: Single Family Residence | F96: 3 | G96: 2 | H96: 1448 | I96: 1979 | J96: 460000 | K96: 24 | L96: 2023-07-21 | M96: 425000 | N96: 370730 | O96: LLC/Corp | P96: N | Q96: Y | R96: X | S96: T1 Sarasota beach | T96: =Assumptions!$C$15 -> 0.25 | U96: =J96*(1-T96) -> 345000 | V96: =IF((1-T96)>0.75,Assumptions!$C$11,IF((1-T96)>0.7,Assumptions!$C$12,Assumptions!$C$13)) -> 0.0725 | W96: =PMT(V96/12,Assumptions!$C$14,-U96)+J96*INDEX(Assumptions!$C$28:$C$34,MATCH(C96,Assumptions!$B$28:$B$34,0))/12+(INDEX(Assumptions!$D$28:$D$34,MATCH(C96,Assumptions!$B$28:$B$34,0))+INDEX(Assumptions!$C$22:$C$25,MATCH(R96,Assumptions!$B$22:$B$25,0)))/12 -> 3537.6748 | X96: =W96*12*$B$18/Assumptions!$C$18 -> 53065.122 | Y96: =W96*12*$B$19/Assumptions!$C$18 -> 66331.403 | Z96: =J96*(T96+Assumptions!$C$16) -> 133400 | AA96: =IF(ISNUMBER(F96),F96,IF(H96>=2000,4,3)) -> 3 | AB96: =IFERROR(INDEX($E$18:$H$25,MATCH(D96,$D$18:$D$25,0),1+IF(AA96>=4,2,0)+IF(Q96="Y",1,0)),0) -> 46000 | AC96: =IFERROR(AB96/X96,0) -> 0.8668594 | AD96: =IF(ISNUMBER(SEARCH("Mobile",E96)),"EXCLUDED",IF(AB96>=Y96,"PASS",IF(AB96>=X96,"MARGINAL","FAIL"))) -> FAIL
A97: 3226 SE 2nd Ave | B97: Cape Coral 33904 | C97: Lee | D97: Cape Coral pool (STR) | E97: Single Family Residence | F97: 3 | G97: 2 | H97: 1515 | I97: 1981 | J97: 550000 | K97: 184 | L97: 2017-09-22 | M97: 117000 | N97: 452744 | O97: Individual | P97: N | Q97: Y | R97: X | S97: T3 Cape Coral pool | T97: =Assumptions!$C$15 -> 0.25 | U97: =J97*(1-T97) -> 412500 | V97: =IF((1-T97)>0.75,Assumptions!$C$11,IF((1-T97)>0.7,Assumptions!$C$12,Assumptions!$C$13)) -> 0.0725 | W97: =PMT(V97/12,Assumptions!$C$14,-U97)+J97*INDEX(Assumptions!$C$28:$C$34,MATCH(C97,Assumptions!$B$28:$B$34,0))/12+(INDEX(Assumptions!$D$28:$D$34,MATCH(C97,Assumptions!$B$28:$B$34,0))+INDEX(Assumptions!$C$22:$C$25,MATCH(R97,Assumptions!$B$22:$B$25,0)))/12 -> 4259.8105 | X97: =W97*12*$B$18/Assumptions!$C$18 -> 63897.157 | Y97: =W97*12*$B$19/Assumptions!$C$18 -> 79871.447 | Z97: =J97*(T97+Assumptions!$C$16) -> 159500 | AA97: =IF(ISNUMBER(F97),F97,IF(H97>=2000,4,3)) -> 3 | AB97: =IFERROR(INDEX($E$18:$H$25,MATCH(D97,$D$18:$D$25,0),1+IF(AA97>=4,2,0)+IF(Q97="Y",1,0)),0) -> 55000 | AC97: =IFERROR(AB97/X97,0) -> 0.86075817 | AD97: =IF(ISNUMBER(SEARCH("Mobile",E97)),"EXCLUDED",IF(AB97>=Y97,"PASS",IF(AB97>=X97,"MARGINAL","FAIL"))) -> FAIL
A98: 2958 Dundee Dr | B98: Palm Harbor 34684 | C98: Pinellas | D98: Pinellas uninc/Largo (STR) | E98: Single Family Residence | G98: 2 | H98: 1320 | I98: 1976 | J98: 439000 | K98: 89 | L98: 2009-10-29 | M98: 135000 | N98: 431598 | O98: LLC/Corp | P98: N | Q98: N | R98: X | S98: T2 Pinellas focus | T98: =Assumptions!$C$15 -> 0.25 | U98: =J98*(1-T98) -> 329250 | V98: =IF((1-T98)>0.75,Assumptions!$C$11,IF((1-T98)>0.7,Assumptions!$C$12,Assumptions!$C$13)) -> 0.0725 | W98: =PMT(V98/12,Assumptions!$C$14,-U98)+J98*INDEX(Assumptions!$C$28:$C$34,MATCH(C98,Assumptions!$B$28:$B$34,0))/12+(INDEX(Assumptions!$D$28:$D$34,MATCH(C98,Assumptions!$B$28:$B$34,0))+INDEX(Assumptions!$C$22:$C$25,MATCH(R98,Assumptions!$B$22:$B$25,0)))/12 -> 3498.0654 | X98: =W98*12*$B$18/Assumptions!$C$18 -> 52470.981 | Y98: =W98*12*$B$19/Assumptions!$C$18 -> 65588.726 | Z98: =J98*(T98+Assumptions!$C$16) -> 127310 | AA98: =IF(ISNUMBER(F98),F98,IF(H98>=2000,4,3)) -> 3 | AB98: =IFERROR(INDEX($E$18:$H$25,MATCH(D98,$D$18:$D$25,0),1+IF(AA98>=4,2,0)+IF(Q98="Y",1,0)),0) -> 45000 | AC98: =IFERROR(AB98/X98,0) -> 0.8576169 | AD98: =IF(ISNUMBER(SEARCH("Mobile",E98)),"EXCLUDED",IF(AB98>=Y98,"PASS",IF(AB98>=X98,"MARGINAL","FAIL"))) -> FAIL | AE98: Beds not in Pinellas public record; screen assumes 3BR <2,000 sf, 4BR >=2,000 sf.
A99: 3225 Laurel Ave | B99: Clearwater 33762 | C99: Pinellas | D99: Pinellas uninc/Largo (STR) | E99: Single Family Residence | G99: 2 | H99: 1268 | I99: 2024 | J99: 394000 | K99: 135 | L99: 2022-10-21 | M99: 81500 | N99: 62783 | O99: LLC/Corp | P99: N | Q99: N | R99: AE | S99: T2 Pinellas Largo/mid | T99: =Assumptions!$C$15 -> 0.25 | U99: =J99*(1-T99) -> 295500 | V99: =IF((1-T99)>0.75,Assumptions!$C$11,IF((1-T99)>0.7,Assumptions!$C$12,Assumptions!$C$13)) -> 0.0725 | W99: =PMT(V99/12,Assumptions!$C$14,-U99)+J99*INDEX(Assumptions!$C$28:$C$34,MATCH(C99,Assumptions!$B$28:$B$34,0))/12+(INDEX(Assumptions!$D$28:$D$34,MATCH(C99,Assumptions!$B$28:$B$34,0))+INDEX(Assumptions!$C$22:$C$25,MATCH(R99,Assumptions!$B$22:$B$25,0)))/12 -> 3499.4976 | X99: =W99*12*$B$18/Assumptions!$C$18 -> 52492.464 | Y99: =W99*12*$B$19/Assumptions!$C$18 -> 65615.58 | Z99: =J99*(T99+Assumptions!$C$16) -> 114260 | AA99: =IF(ISNUMBER(F99),F99,IF(H99>=2000,4,3)) -> 3 | AB99: =IFERROR(INDEX($E$18:$H$25,MATCH(D99,$D$18:$D$25,0),1+IF(AA99>=4,2,0)+IF(Q99="Y",1,0)),0) -> 45000 | AC99: =IFERROR(AB99/X99,0) -> 0.85726592 | AD99: =IF(ISNUMBER(SEARCH("Mobile",E99)),"EXCLUDED",IF(AB99>=Y99,"PASS",IF(AB99>=X99,"MARGINAL","FAIL"))) -> FAIL | AE99: Beds not in Pinellas public record; screen assumes 3BR <2,000 sf, 4BR >=2,000 sf.
A100: 414 Still Meadows Cir E | B100: Palm Harbor 34683 | C100: Pinellas | D100: Pinellas uninc/Largo (STR) | E100: Single Family Residence | G100: 2.5 | H100: 2161 | I100: 1985 | J100: 525000 | K100: 83 | L100: 2018-10-23 | M100: 100 | N100: 572236 | O100: LLC/Corp | P100: N | Q100: N | R100: X | S100: T2 Pinellas focus | T100: =Assumptions!$C$15 -> 0.25 | U100: =J100*(1-T100) -> 393750 | V100: =IF((1-T100)>0.75,Assumptions!$C$11,IF((1-T100)>0.7,Assumptions!$C$12,Assumptions!$C$13)) -> 0.0725 | W100: =PMT(V100/12,Assumptions!$C$14,-U100)+J100*INDEX(Assumptions!$C$28:$C$34,MATCH(C100,Assumptions!$B$28:$B$34,0))/12+(INDEX(Assumptions!$D$28:$D$34,MATCH(C100,Assumptions!$B$28:$B$34,0))+INDEX(Assumptions!$C$22:$C$25,MATCH(R100,Assumptions!$B$22:$B$25,0)))/12 -> 4052.7358 | X100: =W100*12*$B$18/Assumptions!$C$18 -> 60791.037 | Y100: =W100*12*$B$19/Assumptions!$C$18 -> 75988.796 | Z100: =J100*(T100+Assumptions!$C$16) -> 152250 | AA100: =IF(ISNUMBER(F100),F100,IF(H100>=2000,4,3)) -> 4 | AB100: =IFERROR(INDEX($E$18:$H$25,MATCH(D100,$D$18:$D$25,0),1+IF(AA100>=4,2,0)+IF(Q100="Y",1,0)),0) -> 52000 | AC100: =IFERROR(AB100/X100,0) -> 0.85538926 | AD100: =IF(ISNUMBER(SEARCH("Mobile",E100)),"EXCLUDED",IF(AB100>=Y100,"PASS",IF(AB100>=X100,"MARGINAL","FAIL"))) -> FAIL | AE100: Beds not in Pinellas public record; screen assumes 3BR <2,000 sf, 4BR >=2,000 sf.
A101: 4815 Sorrento Ct | B101: Cape Coral 33904 | C101: Lee | D101: Cape Coral pool (STR) | E101: Single Family Residence | F101: 3 | G101: 2 | H101: 1370 | I101: 1972 | J101: 519900 | K101: 185 | L101: 2023-02-15 | M101: 475000 | N101: 582390 | O101: LLC/Corp | P101: N | Q101: Y | R101: AE | S101: T3 Cape Coral pool | T101: =Assumptions!$C$15 -> 0.25 | U101: =J101*(1-T101) -> 389925 | V101: =IF((1-T101)>0.75,Assumptions!$C$11,IF((1-T101)>0.7,Assumptions!$C$12,Assumptions!$C$13)) -> 0.0725 | W101: =PMT(V101/12,Assumptions!$C$14,-U101)+J101*INDEX(Assumptions!$C$28:$C$34,MATCH(C101,Assumptions!$B$28:$B$34,0))/12+(INDEX(Assumptions!$D$28:$D$34,MATCH(C101,Assumptions!$B$28:$B$34,0))+INDEX(Assumptions!$C$22:$C$25,MATCH(R101,Assumptions!$B$22:$B$25,0)))/12 -> 4354.8342 | X101: =W101*12*$B$18/Assumptions!$C$18 -> 65322.513 | Y101: =W101*12*$B$19/Assumptions!$C$18 -> 81653.141 | Z101: =J101*(T101+Assumptions!$C$16) -> 150771 | AA101: =IF(ISNUMBER(F101),F101,IF(H101>=2000,4,3)) -> 3 | AB101: =IFERROR(INDEX($E$18:$H$25,MATCH(D101,$D$18:$D$25,0),1+IF(AA101>=4,2,0)+IF(Q101="Y",1,0)),0) -> 55000 | AC101: =IFERROR(AB101/X101,0) -> 0.84197618 | AD101: =IF(ISNUMBER(SEARCH("Mobile",E101)),"EXCLUDED",IF(AB101>=Y101,"PASS",IF(AB101>=X101,"MARGINAL","FAIL"))) -> FAIL
A102: 8403 13th Ave NW | B102: Bradenton 34209 | C102: Manatee | D102: Manatee W Bradenton (STR) | E102: Single Family Residence | F102: 3 | G102: 2 | H102: 1946 | I102: 1986 | J102: 619000 | K102: 147 | L102: 2016-04-04 | M102: 297900 | N102: 629480 | O102: Individual | P102: N | Q102: Y | R102: X | S102: T1 Manatee beach | T102: =Assumptions!$C$15 -> 0.25 | U102: =J102*(1-T102) -> 464250 | V102: =IF((1-T102)>0.75,Assumptions!$C$11,IF((1-T102)>0.7,Assumptions!$C$12,Assumptions!$C$13)) -> 0.0725 | W102: =PMT(V102/12,Assumptions!$C$14,-U102)+J102*INDEX(Assumptions!$C$28:$C$34,MATCH(C102,Assumptions!$B$28:$B$34,0))/12+(INDEX(Assumptions!$D$28:$D$34,MATCH(C102,Assumptions!$B$28:$B$34,0))+INDEX(Assumptions!$C$22:$C$25,MATCH(R102,Assumptions!$B$22:$B$25,0)))/12 -> 4607.42 | X102: =W102*12*$B$18/Assumptions!$C$18 -> 69111.301 | Y102: =W102*12*$B$19/Assumptions!$C$18 -> 86389.126 | Z102: =J102*(T102+Assumptions!$C$16) -> 179510 | AA102: =IF(ISNUMBER(F102),F102,IF(H102>=2000,4,3)) -> 3 | AB102: =IFERROR(INDEX($E$18:$H$25,MATCH(D102,$D$18:$D$25,0),1+IF(AA102>=4,2,0)+IF(Q102="Y",1,0)),0) -> 58000 | AC102: =IFERROR(AB102/X102,0) -> 0.83922599 | AD102: =IF(ISNUMBER(SEARCH("Mobile",E102)),"EXCLUDED",IF(AB102>=Y102,"PASS",IF(AB102>=X102,"MARGINAL","FAIL"))) -> FAIL | AE102: Already in workbook (see market tab).
A103: 1344 Ribolla Dr | B103: Palm Harbor 34683 | C103: Pinellas | D103: Pinellas uninc/Largo (STR) | E103: PUD | H103: 2464 | I103: 2007 | J103: 539000 | K103: 25 | L103: 2007-01-22 | M103: 438700 | N103: 525559 | O103: Individual | P103: N | Q103: N | R103: X | S103: T2 Pinellas focus | T103: =Assumptions!$C$15 -> 0.25 | U103: =J103*(1-T103) -> 404250 | V103: =IF((1-T103)>0.75,Assumptions!$C$11,IF((1-T103)>0.7,Assumptions!$C$12,Assumptions!$C$13)) -> 0.0725 | W103: =PMT(V103/12,Assumptions!$C$14,-U103)+J103*INDEX(Assumptions!$C$28:$C$34,MATCH(C103,Assumptions!$B$28:$B$34,0))/12+(INDEX(Assumptions!$D$28:$D$34,MATCH(C103,Assumptions!$B$28:$B$34,0))+INDEX(Assumptions!$C$22:$C$25,MATCH(R103,Assumptions!$B$22:$B$25,0)))/12 -> 4143.0309 | X103: =W103*12*$B$18/Assumptions!$C$18 -> 62145.464 | Y103: =W103*12*$B$19/Assumptions!$C$18 -> 77681.83 | Z103: =J103*(T103+Assumptions!$C$16) -> 156310 | AA103: =IF(ISNUMBER(F103),F103,IF(H103>=2000,4,3)) -> 4 | AB103: =IFERROR(INDEX($E$18:$H$25,MATCH(D103,$D$18:$D$25,0),1+IF(AA103>=4,2,0)+IF(Q103="Y",1,0)),0) -> 52000 | AC103: =IFERROR(AB103/X103,0) -> 0.83674651 | AD103: =IF(ISNUMBER(SEARCH("Mobile",E103)),"EXCLUDED",IF(AB103>=Y103,"PASS",IF(AB103>=X103,"MARGINAL","FAIL"))) -> FAIL | AE103: Beds not in Pinellas public record; screen assumes 3BR <2,000 sf, 4BR >=2,000 sf.
...

Sheet Other SWFL Markets
A1: West-Coast Florida STR Markets Ranked for This Buyer (25% down, ~7.25%)
A2: Typical 3-4BR pool house; DSCR = typical gross / est. PITIA (no haircut). Vendor revenue data conflicts up to 2x: treat DSCR as +/-0.15. Listing-level documented income beats market averages: the top Manatee picks run ~1.6x.
A4: Rank | B4: Market (target ZIPs) | C4: Typical qualifying house | D4: Est. PITIA ($/yr) | E4: Typical gross ($/yr) | F4: DSCR (typical) | G4: STR legality | H4: Momentum / 'hot' signals | I4: Key risks | J4: Verdict
A5: 1 | B5: Manatee mainland near AMI (W. Bradenton 34205/34207/34209/34210) | C5: 3-4BR pool, $475-600k | D5: ~$51-55k | E5: $50-90k (documented picks $73-89k) | F5: 1.0-1.6 | G5: Uninc. Manatee: no ordinance yet (draft pending); City of Bradenton certificate | H5: Manatee bed tax record $4.61M (Jun 2026, +27.6%); AMI demand spillover | I5: Pending county ordinance; flood zones near bays | J5: BEST: current #1-#3 picks
A6: 2 | B6: Pinellas: unincorporated (Seminole/Largo/Lealman areas) + Largo (33770-33778, 33714) | C6: 3-4BR pool, $450-650k | D6: ~$48-55k | E6: $50-85k (documented listings) | F6: 1.0-1.6 | G6: Unincorporated: legal w/ Certificate of Use $450/yr + $150 inspection, max 10 guests; Largo legal | H6: Record spring 2026 tourist tax ($36.16M Feb-Apr); county 3.5 months supply | I6: Helene/Milton flooding; mailing city != jurisdiction (verify parcel) | J6: STRONG: see Pinellas tab
A7: 2b | B7: Indian Rocks Beach / Indian Shores (33785) | C7: 3-4BR house (SFH median ~$895k) | D7: ~$60-70k | E7: $63-64k avg (AirROI); good 3-4BR $70-100k | F7: ~1.0-1.4 | G7: IRB: registration $300 + $150 inspection, 2026 crackdown; Indian Shores likely legal | H7: Beach-front demand; legal nightly | I7: Few houses under $700k; older ground-level homes = 50% rule + flood $12-15k | J7: Target only if a house appears <= $700k
A8: 2c | B8: Pinellas barrier towns: St. Pete Beach, Treasure Island RU-75, Madeira R-1/R-2, Redington Shores, Clearwater residential | C8: - | D8: - | E8: - | F8: - | G8: 30 days to 6-month minimums (grandfathered pre-2011) | H8: - | I8: Nightly history there may be illegal | J8: Avoid for STR-income DSCR
A9: 3 | B9: Cape Coral Gulf-access canals (33904, 33914, S. 33991) | C9: 3-4BR pool, ~$575k | D9: $55.6k | E9: $50-65k | F9: 0.90-1.17 | G9: City registration $350/yr since 1/1/2026; no minimum stay; few HOAs | H9: Lee bed tax +11.8% YoY (Aug 2026); months supply 7.0 -> 4.8; prices bottomed (+1-3% YoY) | I9: STR supply +19%; ADR down ~6.6%; AE flood $3-8k; Ian flood history | J9: Best non-Tampa-Bay alternative
A10: 1b | B10: Cape Coral freshwater canals (33909, 33993, 33990) | C10: 3BR pool, ~$425k | D10: $41.3k (+$3.4k if assessed) | E10: $38-48k | F10: 0.95-1.04 | G10: Same as above | H10: Cheapest pool-home entry | I10: North Cape utility assessments (~$32k/lot); far from beach | J10: Value play
